Workbook

Sheet RuleSets
A3: SNORT (v2.9) | N3: RuleSets Omitidos
N4: Talos Community SIN interés
A5: Paquete de Reglas | B5: Descripción | C5: Fichero | D5: Nº de Reglas | E5: Versión | F5: Fecha | G5: RS1 | H5: RS2 | I5: RS3 | J5: RS4 | K5: RS5 | L5: RS6 | N5: RS7 | O5: RS8 | P5: RS9 | R5: RS10 ≈ RS3 (RS7 sólo aporta 1 SID) | S5: RS11 = RS6 | T5: RS12 = RS6
A6: Talos Registered (por defecto) | B6: Reglas supervisadas por el grupo Talos, tal como se descargan para Snort v2.9 (sin modificar configuración ni reglas comentadas) Fusión de todos los ficheros ".rules" del paquete (preproc_rules, rules y so_rules) que tienen el "include" SIN comentar | C6: registered-all.rules | D6: 15684 | F6: 46113 | G6: ✔ | I6: ✔ | P6: ✔ | R6: ✔ | U6: https://www.snort.org/downloads Community: community-rules.tar.gz Registered: snortrules-snapshot-xxx.tar.gz
A7: ETOpen (por defecto) | B7: Reglas "Emerging Threats", tal como se descargan (sin modificar configuración ni reglas comentadas) | C7: emerging-all.rules | D7: 36658 | E7: 11168 | F7: 46113 | H7: ✔ | I7: ✔ | P7: ✔ | R7: ✔ | U7: https://rules.emergingthreats.net/open/snort-2.9.0/
A8: Talos Registered (máxima CD) | B8: Talos Registered, descomentando todas las reglas (#) y todos los "include" de ficheros ".rules" (salvo el fichero "deleted.rules", con "DELETED" al principio del "msg") Fusión de todos los ficheros ".rules" del paquete | C8: registered-all-descomentadas.rules | D8: 53465 | F8: 46113 | J8: ✔ | L8: ✔ | S8: ✔ | T8: ✔
A9: ETOpen (máxima CD) | B9: ETOpen, descomentando todas las reglas (salvo las reglas marcadas como "msg:"ET DELETED" o fichero "emerging-deleted.rules" - hay "12271" deleted) | C9: emerging-all-descomentadas.rules | D9: 64762 | F9: 46113 | K9: ✔ | L9: ✔ | S9: ✔ | T9: ✔
A10: Talos Community (por defecto) | B10: Reglas de la Comunidad (GPLv2), tal como se descargan (sin modificar reglas comentadas) | C10: community.rules | D10: 561 * Talos Registered por defecto: Todas salvo 1 (sid:59735) * Registered máxima CD: Todas | F10: 46113 | N10: ✔ | R10: ✔ (sólo aporta 1 SID, 59735) | S10: ✔ (contenido en RS4)
A11: Talos Community (máxima CD) | B11: Reglas de la Comunidad (GPLv2), descomentando todas las reglas | C11: community.rules | D11: 4013 * Talos Registered por defecto: No contiene 3453 (560 reglas en común, las no comentadas, salvo "sid:59735") * Registered máxima CD: Todas | F11: 46113 | O11: ✔ | P11: ✔ | T11: ✔ (contenido en RS4)
A15: FORTIGATE
A16: Nombre Reglas | B16: Descripción | C16: #Reglas IPS (Security Profiles / IPS Signatures) | D16: #Reglas Aplicación (Security Profiles / Application Signatures) | E16: IPS Definitions | F16: IPS Engine | G16: Fecha | H16: Dispositivo
A17: FortiGate | B17: Consulta de reglas IPS: https://fortiguard.fortinet.com/encyclopedia/ips/xxx | C17: 12202 | D17: 9407 | E17: Version 33.00053 | F17: Version 7.00600 | G17: 46139 | H17: FGVM02
A19: PALOALTO NGFW
A20: Nombre Reglas | B20: Descripción | C20: #Reglas IPS (OBJECTS > Security Profiles > Vulnerability Protection > ESI > Exceptions > Marcar "Show All signatures") | D20: #Reglas Aplicación (OBJECTS > Applications) | E20: IPS Definitions | F20: IPS Engine | G20: Fecha | H20: Dispositivo
A21: PaloAlto | B21: Consulta de reglas IPS: https://threatvault.paloaltonetworks.com/?query=xxxxx | C21: 22085 | D21: 5420 | E21: PAN-OS 10.2.11 | F21: PAN-OS 10.2.11 | G21: 46139 | H21: PA-VM
A23: Niveles de Prioridad/Riesgo/Severidad
A24: N (Nivel de Riesgo) | B24: Snort [Priority] | C24: FG | E24: PA
C25: IPS (severity) | D25: APP (apprisk) | E25: IPS (severity_number) | F25: APP (risk_of_app)
A26: 1 | B26: Crítica | C26: info | D26: information | E26: Informational | F26: Information | G26: ADVERTIR: Snort y FG/PA usan "N" en orden inverso (e.g. N=1 es máximo para Snort y mínimo para FG/PA)
A27: 2 | B27: Alta | C27: low | D27: low | E27: Lowal | F27: Low
A28: 3 | B28: Media | C28: medium | D28: medium | E28: Medium | F28: Medium
A29: 4 | B29: Baja | C29: high | D29: high | E29: High | F29: High
A30: 5 | B30: - | C30: critical | D30: elevated | E30: Critical | F30: Elevated

Sheet Tabla 3 (Legítimo)
B1: Snort [Priority <= 4 (Any)] | K1: FG | M1: PA
A2: Metric | B2: RS1 | C2: RS2 | D2: RS3 | E2: RS4 | F2: RS5 | G2: RS6 | H2: RS7 | I2: RS8 | J2: RS9 | K2: [IPS severity >=1 (Any)] | L2: [IPS severity >=1 (Any)] || [App apprisk >= 1 (Any)] | M2: [IPS severity >=1 (Any)] | N2: [IPS severity_number >=1 (Any)] || [App risk_of_app >= 1 (Any)]
A3: #Flows | B3: ='(B) Legitimo'!D3 -> 78694206
A4: #Alerts | B4: ='(B) Legitimo'!G3 -> 9778069 | C4: ='(B) Legitimo'!M3 -> 5500009 | D4: ='(B) Legitimo'!S3 -> 15278078 | E4: ='(B) Legitimo'!Y3 -> 15309135 | F4: ='(B) Legitimo'!AE3 -> 14539188 | G4: ='(B) Legitimo'!AK3 -> 29848323 | H4: ='(B) Legitimo'!AQ3 -> 6990 | I4: ='(B) Legitimo'!AW3 -> 8738223 | J4: ='(B) Legitimo'!BC3 -> 24009324 | K4: ='(B) Legitimo'!JZ3+'(B) Legitimo'!KF3+'(B) Legitimo'!KL3+'(B) Legitimo'!KR3+'(B) Legitimo'!KX3 -> 4445687 | L4: ='(B) Legitimo'!JQ3 -> 25983916 | M4: ='(B) Legitimo'!MH3 -> 31273 | N4: ='(B) Legitimo'!MH3 -> 31273
A5: #Flow-correlated Alerts | B5: ='(B) Legitimo'!I3 -> 8620288 | C5: ='(B) Legitimo'!O3 -> 5136879 | D5: ='(B) Legitimo'!U3 -> 13757167 | E5: ='(B) Legitimo'!AA3 -> 13128811 | F5: ='(B) Legitimo'!AG3 -> 13066562 | G5: ='(B) Legitimo'!AM3 -> 26195373 | H5: ='(B) Legitimo'!AS3 -> 6420 | I5: ='(B) Legitimo'!AY3 -> 7505544 | J5: ='(B) Legitimo'!BE3 -> 21256304 | K5: ='(B) Legitimo'!KB3+'(B) Legitimo'!KH3+'(B) Legitimo'!KN3+'(B) Legitimo'!KT3+'(B) Legitimo'!KZ3 -> 4421445 | L5: ='(B) Legitimo'!JR3 -> 25704108 | M5: ='(B) Legitimo'!MI3 -> 56932 | N5: ='(B) Legitimo'!MI3 -> 56932
A6: #SIDs, #AttackID o #ThreatID | B6: ='(B) Legitimo'!K3 -> 22 | C6: ='(B) Legitimo'!Q3 -> 71 | D6: ='(B) Legitimo'!W3 -> 93 | E6: ='(B) Legitimo'!AC3 -> 214 | F6: ='(B) Legitimo'!AI3 -> 229 | G6: ='(B) Legitimo'!AO3 -> 443 | H6: ='(B) Legitimo'!AU3 -> 2 | I6: ='(B) Legitimo'!BA3 -> 63 | J6: ='(B) Legitimo'!BG3 -> 154 | K6: ='(B) Legitimo'!KD3+'(B) Legitimo'!KV3+'(B) Legitimo'!KJ3+'(B) Legitimo'!KP3+'(B) Legitimo'!LB3 -> 30 | L6: ='(B) Legitimo'!JS3 -> 30 | M6: ='(B) Legitimo'!MJ3 -> 14 | N6: ='(B) Legitimo'!MJ3 -> 14
A7: #AppID | B7: N/A | C7: N/A | D7: N/A | E7: N/A | F7: N/A | G7: N/A | H7: N/A | I7: N/A | J7: N/A | K7: N/A | L7: ='(B) Legitimo'!JT3 -> 134 | M7: N/A | N7: ='(B) Legitimo'!MK3 -> 14
A8: #Flows_FP | B8: ='(B) Legitimo'!L3 -> 3391362 | C8: ='(B) Legitimo'!R3 -> 4719941 | D8: ='(B) Legitimo'!X3 -> 7276338 | E8: ='(B) Legitimo'!AD3 -> 6879262 | F8: ='(B) Legitimo'!AJ3 -> 6115454 | G8: ='(B) Legitimo'!AP3 -> 9478500 | H8: ='(B) Legitimo'!AV3 -> 6398 | I8: ='(B) Legitimo'!BB3 -> 7470907 | J8: ='(B) Legitimo'!BH3 -> 10855081 | K8: ='(B) Legitimo'!JV3 -> 4412536 | L8: ='(B) Legitimo'!JX3 -> 18610671 | M8: ='(B) Legitimo'!MM3 -> 28174 | N8: ='(B) Legitimo'!MO3 -> 28174
A9: #Flows_TN | B9: =$B$3-B8 -> 75302844 | C9: =$B$3-C8 -> 73974265 | D9: =$B$3-D8 -> 71417868 | E9: =$B$3-E8 -> 71814944 | F9: =$B$3-F8 -> 72578752 | G9: =$B$3-G8 -> 69215706 | H9: =$B$3-H8 -> 78687808 | I9: =$B$3-I8 -> 71223299 | ... N9: =$B$3-N8 -> 78666032
A10: %Flows_FP | B10: =B8/$B$3 -> 0.043095447 | C10: =C8/$B$3 -> 0.059978253 | D10: =D8/$B$3 -> 0.092463453 | E10: =E8/$B$3 -> 0.087417643 | F10: =F8/$B$3 -> 0.077711617 | G10: =G8/$B$3 -> 0.12044724 | H10: =H8/$B$3 -> 8.1302047e-05 | I10: =I8/$B$3 -> 0.094935922 | ... N10: =N8/$B$3 -> 0.00035801873
A11: %Flows_TN | B11: =1-B10 -> 0.95690455 | C11: =1-C10 -> 0.94002175 | D11: =1-D10 -> 0.90753655 | E11: =1-E10 -> 0.91258236 | F11: =1-F10 -> 0.92228838 | G11: =1-G10 -> 0.87955276 | H11: =1-H10 -> 0.9999187 | I11: =1-I10 -> 0.90506408 | ... N11: =1-N10 -> 0.99964198
B13: Snort [Priority <=3] | K13: FG | M13: PA
A14: Metric | B14: RS1 | C14: RS2 | D14: RS3 | E14: RS4 | F14: RS5 | G14: RS6 | H14: RS7 | I14: RS8 | J14: RS9 | K14: [IPS severity >=2] | L14: [IPS severity >=2 ] || [App apprisk >= 2] | M14: [IPS severity >=2] | N14: [IPS severity_number >=2] || [App risk_of_app >= 2]
A15: #Flows | B15: =B3 -> 78694206
A16: #Alerts | B16: 9778069 | C16: 5500009 | D16: 15278078 | E16: 15309135 | F16: 14539188 | G16: 29848323 | H16: 6990 | I16: 8738223 | J16: 24009324 | K16: 4424853 | L16: 25932651 | M16: 24194 | N16: 54938
A17: #Flow-correlated Alerts | B17: 8620288 | C17: 5136879 | D17: 13757167 | E17: 13128811 | F17: 13066562 | G17: 26195373 | H17: 6420 | I17: 7505544 | J17: 21256304 | K17: 4403661 | L17: 25655131 | M17: 22009 | N17: 49743
A18: #SIDs, #AttackID o #ThreatID | B18: 22 | C18: 71 | D18: 93 | E18: 214 | F18: 229 | G18: 443 | H18: 2 | I18: 63 | J18: 154 | K18: 26 | L18: 26 | M18: 7 | N18: 7
A19: #AppID | B19: N/A | C19: N/A | D19: N/A | E19: N/A | F19: N/A | G19: N/A | H19: N/A | I19: N/A | J19: N/A | K19: N/A | L19: 134 | M19: N/A | N19: 9
A20: #Flows_FP | B20: 3391362 | C20: 4719941 | D20: 7276338 | E20: 6879262 | F20: 6115454 | G20: 9478500 | H20: 6398 | I20: 7470907 | J20: 10855081 | K20: 4403121 | L20: 18609931 | M20: 21995 | N20: 27763
A21: #Flows_TN | B21: 75302844 | C21: 73974265 | D21: 71417868 | E21: 71814944 | F21: 72578752 | G21: 69215706 | H21: 78687808 | I21: 71223299 | J21: 67839125 | K21: 74291085 | L21: 60084275 | M21: 78672211 | N21: 78666443
A22: %Flows_FP | B22: 4.3095% | C22: 5.9978% | D22: 9.2463% | E22: 8.7418% | F22: 7.7712% | G22: 12.0447% | H22: 0.0081% | I22: 9.4936% | J22: 13.7940% | K22: 5.5952% | L22: 23.6484% | M22: 0.0279% | N22: 0.0353%
A23: %Flows_TN | B23: 95.6905% | C23: 94.0022% | D23: 90.7537% | E23: 91.2582% | F23: 92.2288% | G23: 87.9553% | H23: 99.9919% | I23: 90.5064% | J23: 86.2060% | K23: 94.4048% | L23: 76.3516% | M23: 99.9721% | N23: 99.9647%
B25: Snort [Priority <=2] | K25: FG | M25: PA
A26: Metric | B26: RS1 | C26: RS2 | D26: RS3 | E26: RS4 | F26: RS5 | G26: RS6 | H26: RS7 | I26: RS8 | J26: RS9 | K26: [IPS severity >=3] | L26: [IPS severity >=3 ] || [App apprisk >= 3] | M26: [IPS severity >=3] | N26: [IPS severity_number >=3] || [App risk_of_app >= 3]
A27: #Flows | B27: =B15 -> 78694206
A28: #Alerts | B28: 2858397 | C28: 385457 | D28: 3243854 | E28: 7886066 | F28: 4188364 | G28: 12074430 | H28: 6990 | I28: 4692620 | J28: 7929497 | K28: 4417024 | L28: 25529814 | M28: 24182 | N28: 53560
A29: #Flow-correlated Alerts | B29: 1738549 | C29: 381283 | D29: 2119832 | E29: 6020530 | F29: 3299324 | G29: 9319854 | H29: 6420 | I29: 3932063 | J29: 6045488 | K29: 4396049 | L29: 25295028 | M29: 21997 | N29: 48376
A30: #SIDs, #AttackID o #ThreatID | B30: 15 | C30: 45 | D30: 60 | E30: 155 | F30: 160 | G30: 315 | H30: 2 | I30: 39 | J30: 97 | K30: 12 | L30: 12 | M30: 6 | N30: 6
A31: #AppID | B31: N/A | C31: N/A | D31: N/A | E31: N/A | F31: N/A | G31: N/A | H31: N/A | I31: N/A | J31: N/A | K31: N/A | L31: 121 | M31: N/A | N31: 6
A32: #Flows_FP | B32: 1686398 | C32: 204091 | D32: 1724606 | E32: 3895907 | F32: 3012278 | G32: 5822763 | H32: 6398 | I32: 3922641 | J32: 5306206 | K32: 4395669 | L32: 18279194 | M32: 21983 | N32: 26434
A33: #Flows_TN | B33: 77007808 | C33: 78490115 | D33: 76969600 | E33: 74798299 | F33: 75681928 | G33: 72871443 | H33: 78687808 | I33: 74771565 | J33: 73388000 | K33: 74298537 | L33: 60415012 | M33: 78672223 | N33: 78667772
A34: %Flows_FP | B34: 2.1430% | C34: 0.2593% | D34: 2.1915% | E34: 4.9507% | F34: 3.8278% | G34: 7.3992% | H34: 0.0081% | I34: 4.9847% | J34: 6.7428% | K34: 5.5858% | L34: 23.2281% | M34: 0.0279% | N34: 0.0336%
A35: %Flows_TN | B35: 97.8570% | C35: 99.7407% | D35: 97.8085% | E35: 95.0493% | F35: 96.1722% | G35: 92.6008% | H35: 99.9919% | I35: 95.0153% | J35: 93.2572% | K35: 94.4142% | L35: 76.7719% | M35: 99.9721% | N35: 99.9664%
B37: Snort [Priority <=1] | K37: FG | M37: PA
A38: Metric | B38: RS1 | C38: RS2 | D38: RS3 | E38: RS4 | F38: RS5 | G38: RS6 | H38: RS7 | I38: RS8 | J38: RS9 | K38: [IPS severity >=4] | L38: [IPS severity >=4 ] || [App apprisk >= 4] | M38: [IPS severity >=4] | N38: [IPS severity_number >=4] || [App risk_of_app >= 4]
A39: #Flows | B39: =B27 -> 78694206
A40: #Alerts | B40: 6987 | C40: 338711 | D40: 345698 | E40: 2527690 | F40: 673827 | G40: 3201517 | H40: 6990 | I40: 21553 | J40: 360274 | K40: 4244616 | L40: 22445972 | M40: 28 | N40: 27691
A41: #Flow-correlated Alerts | B41: 6417 | C41: 338311 | D41: 344728 | E41: 2445673 | F41: 571742 | G41: 3017415 | H41: 6420 | I41: 14558 | J41: 352879 | K41: 4224161 | L41: 22211706 | M41: 28 | N41: 24694
A42: #SIDs, #AttackID o #ThreatID | B42: 3 | C42: 13 | D42: 16 | E42: 79 | F42: 42 | G42: 121 | H42: 2 | I42: 10 | J42: 24 | K42: 10 | L42: 10 | M42: 2 | N42: 2
A43: #AppID | B43: N/A | C43: N/A | D43: N/A | E43: N/A | F43: N/A | G43: N/A | H43: N/A | I43: N/A | J43: N/A | K43: N/A | L43: 103 | M43: N/A | N43: 2
A44: #Flows_FP | B44: 6395 | C44: 169036 | D44: 175400 | E44: 1067860 | F44: 421616 | G44: 1243621 | H44: 6398 | I44: 14498 | J44: 182455 | K44: 4224014 | L44: 17178374 | M44: 28 | N44: 24694
A45: #Flows_TN | B45: 78687811 | C45: 78525170 | D45: 78518806 | E45: 77626346 | F45: 78272590 | G45: 77450585 | H45: 78687808 | I45: 78679708 | J45: 78511751 | K45: 74470192 | L45: 61515832 | M45: 78694178 | N45: 78669512
A46: %Flows_FP | B46: 0.0081% | C46: 0.2148% | D46: 0.2229% | E46: 1.3570% | F46: 0.5358% | G46: 1.5803% | H46: 0.0081% | I46: 0.0184% | J46: 0.2319% | K46: 5.3676% | L46: 21.8293% | M46: 0.0000% | N46: 0.0314%
A47: %Flows_TN | B47: 99.9919% | C47: 99.7852% | D47: 99.7771% | E47: 98.6430% | F47: 99.4642% | G47: 98.4197% | H47: 99.9919% | I47: 99.9816% | J47: 99.7681% | K47: 94.6324% | L47: 78.1707% | M47: 100.0000% | N47: 99.9686%
K49: FG | M49: PA
A50: Metric | K50: [IPS severity >=5] | L50: [IPS severity >=5 ] || [App apprisk >= 5] | M50: [IPS severity >=5] | N50: [IPS severity_number >=5] || [App risk_of_app >= 5]
A51: #Flows | B51: =B39 -> 78694206
A52: #Alerts | B52: N/A | C52: N/A | D52: N/A | E52: N/A | F52: N/A | G52: N/A | H52: N/A | I52: N/A | J52: N/A | K52: 189068 | L52: 14371055 | M52: 27 | N52: 27
A53: #Flow-correlated Alerts | B53: N/A | C53: N/A | D53: N/A | E53: N/A | F53: N/A | G53: N/A | H53: N/A | I53: N/A | J53: N/A | K53: 186956 | L53: 14155132 | M53: 27 | N53: 27
A54: #SIDs, #AttackID o #ThreatID | B54: N/A | C54: N/A | D54: N/A | E54: N/A | F54: N/A | G54: N/A | H54: N/A | I54: N/A | J54: N/A | K54: 6 | L54: 6 | M54: 1 | N54: 1
A55: #AppID | B55: N/A | C55: N/A | D55: N/A | E55: N/A | F55: N/A | G55: N/A | H55: N/A | I55: N/A | J55: N/A | K55: N/A | L55: 100 | M55: N/A | N55: 0
A56: #Flows_FP | B56: N/A | C56: N/A | D56: N/A | E56: N/A | F56: N/A | G56: N/A | H56: N/A | I56: N/A | J56: N/A | K56: 186956 | L56: 13158924 | M56: 27 | N56: 27
A57: #Flows_TN | B57: N/A | C57: N/A | D57: N/A | E57: N/A | F57: N/A | G57: N/A | H57: N/A | I57: N/A | J57: N/A | K57: 78507250 | L57: 65535282 | M57: 78694179 | N57: 78694179
A58: %Flows_FP | B58: N/A | C58: N/A | D58: N/A | E58: N/A | F58: N/A | G58: N/A | H58: N/A | I58: N/A | J58: N/A | K58: 0.2376% | L58: 16.7216% | M58: 0.0000% | N58: 0.0000%
A59: %Flows_TN | B59: N/A | C59: N/A | D59: N/A | E59: N/A | F59: N/A | G59: N/A | H59: N/A | I59: N/A | J59: N/A | K59: 99.7624% | L59: 83.2784% | M59: 100.0000% | N59: 100.0000%

Sheet T2 (At) S<=4, FG>=1
A1: Nº | B1: Technique | C1: Description | D1: #pcaps | E1: #flows | F1: #pcaps (#flows) | G1: RS1 [Priority <= 4 (Any)] | M1: RS2 | S1: RS3 | Y1: RS4 | AE1: RS5 | AK1: RS6 | AQ1: RS7 | AW1: RS8 | BC1: RS9 | BI1: FG [IPS severity >=1 (Any)] | BO1: FG [IPS severity >=1 (Any)] || [App apprisk >= 1 (Any)] | BV1: PA [IPS severity_number >=1 (Any)] | CB1: PA [IPS severity_number >=1 (Any)] || [App risk_of_app >= 1 (Any)]
G2: #Alerts | H2: #Flow-correlated Alerts | I2: #Flow-correlated Alerts (total) | J2: #SID | K2: %Detection_pcaps | L2: #Attack_Flows | M2: #Alerts | N2: #Flow-correlated Alerts | O2: #Flow-correlated Alerts (total) | P2: #SID | Q2: %Detection_pcaps | R2: #Attack_Flows | S2: #Alerts | T2: #Flow-correlated Alerts | U2: #Flow-correlated Alerts (total) | V2: #SID | W2: %Detection_pcaps | X2: #Attack_Flows | Y2: #Alerts | Z2: #Flow-correlated Alerts | AA2: #Flow-correlated Alerts (total) | AB2: #SID | AC2: %Detection_pcaps | AD2: #Attack_Flows | AE2: #Alerts | AF2: #Flow-correlated Alerts | AG2: #Flow-correlated Alerts (total) | AH2: #SID | AI2: %Detection_pcaps | AJ2: #Attack_Flows | AK2: #Alerts | AL2: #Flow-correlated Alerts | AM2: #Flow-correlated Alerts (total) | AN2: #SID | AO2: %Detection_pcaps | AP2: #Attack_Flows | AQ2: #Alerts | AR2: #Flow-correlated Alerts | AS2: #Flow-correlated Alerts (total) | AT2: #SID | AU2: %Detection_pcaps | AV2: #Attack_Flows | AW2: #Alerts | AX2: #Flow-correlated Alerts | AY2: #Flow-correlated Alerts (total) | AZ2: #SID | BA2: %Detection_pcaps | BB2: #Attack_Flows | BC2: #Alerts | BD2: #Flow-correlated Alerts | BE2: #Flow-correlated Alerts (total) | BF2: #SID | BG2: %Detection_pcaps | BH2: #Attack_Flows | BI2: #Alerts | BJ2: #Flow-correlated Alerts | BK2: #Flow-correlated Alerts (total) | BL2: #AttackID | BM2: %Detection_pcaps AttackID | BN2: #Attack_Flows AttackID | BO2: #Alerts | BP2: #Flow-correlated Alerts | BQ2: #Flow-correlated Alerts (total) | BR2: #AttackID | BS2: #AppID | BT2: %Detection_pcaps | BU2: #Attack_Flows | BV2: #Alerts | BW2: #Flow-correlated Alerts | BX2: #Flow-correlated Alerts (total) | BY2: #ThreatID | BZ2: %Detection_pcaps ThreatID | CA2: #Attack_Flows ThreatID | CB2: #Alerts | CC2: #Flow-correlated Alerts | CD2: #Flow-correlated Alerts (total) | CE2: #ThreatID | CF2: #AppID | CG2: %Detection_pcaps | CH2: #Attack_Flows
A3: 1 | B3: =IFERROR(VLOOKUP(A3,'Tabla 2 - Ataques detec (Imple)'!$B$3:$D$112,3,FALSE),"") -> T1001 | C3: =IFERROR(VLOOKUP(B3,Techniques!$B$3:$H$213,2,FALSE),"") -> Data Obfuscation | D3: =SUMPRODUCT( ('Tabla 2 - Ataques detec (Imple)'!$D$3:$D$112=$B3)* (LEN('Tabla 2 - Ataques detec (Imple)'!$C$3:$C$112)>0) ) -> 2 | E3: =SUMIF('Tabla 2 - Ataques detec (Imple)'!$D$3:$D$112,$B3,'Tabla 2 - Ataques detec (Imple)'!$E$3:$E$112) -> 2 | F3: =D3&" ("&E3&")" -> 2 (2) | G3: =SUMIF('Tabla 2 - Ataques detec (Imple)'!$D$3:$D$112,$B3,'Tabla 2 - Ataques detec (Imple)'!F$3:F$112) -> 9 | H3: =SUMIF('Tabla 2 - Ataques detec (Imple)'!$D$3:$D$112,$B3,'Tabla 2 - Ataques detec (Imple)'!G$3:G$112) -> 6 | I3: =H3 & " (" & G3 & ")" -> 6 (9) | J3: =SUMIF('Tabla 2 - Ataques detec (Imple)'!$D$3:$D$112,$B3,'Tabla 2 - Ataques detec (Imple)'!$H$3:$H$112) -> 6 | K3: =AVERAGEIF('Tabla 2 - Ataques detec (Imple)'!$D$3:$D$112,$B3,'Tabla 2 - Ataques detec (Imple)'!$J$3:$J$112) -> 1 | L3: =SUMIF('Tabla 2 - Ataques detec (Imple)'!$D$3:$D$112,$B3,'Tabla 2 - Ataques detec (Imple)'!$I$3:$I$112) -> 2 | M3: =SUMIF('Tabla 2 - Ataques detec (Imple)'!$D$3:$D$112,$B3,'Tabla 2 - Ataques detec (Imple)'!K$3:K$112) -> 0 | N3: =SUMIF('Tabla 2 - Ataques detec (Imple)'!$D$3:$D$112,$B3,'Tabla 2 - Ataques detec (Imple)'!L$3:L$112) -> 0 | O3: =N3 & " (" & M3 & ")" -> 0 (0) | P3: =SUMIF('Tabla 2 - Ataques detec (Imple)'!$D$3:$D$112,$B3,'Tabla 2 - Ataques detec (Imple)'!$M$3:$M$112) -> 0 | Q3: =AVERAGEIF('Tabla 2 - Ataques detec (Imple)'!$D$3:$D$112,$B3,'Tabla 2 - Ataques detec (Imple)'!$O$3:$O$112) -> 0 | R3: =SUMIF('Tabla 2 - Ataques detec (Imple)'!$D$3:$D$112,$B3,'Tabla 2 - Ataques detec (Imple)'!$N$3:$N$112) -> 0 | S3: =SUMIF('Tabla 2 - Ataques detec (Imple)'!$D$3:$D$112,$B3,'Tabla 2 - Ataques detec (Imple)'!P$3:P$112) -> 9 | T3: =SUMIF('Tabla 2 - Ataques detec (Imple)'!$D$3:$D$112,$B3,'Tabla 2 - Ataques detec (Imple)'!Q$3:Q$112) -> 6 | U3: =T3 & " (" & S3 & ")" -> 6 (9) | V3: =SUMIF('Tabla 2 - Ataques detec (Imple)'!$D$3:$D$112,$B3,'Tabla 2 - Ataques detec (Imple)'!$R$3:$R$112) -> 6 | W3: =AVERAGEIF('Tabla 2 - Ataques detec (Imple)'!$D$3:$D$112,$B3,'Tabla 2 - Ataques detec (Imple)'!$T$3:$T$112) -> 1 | X3: =SUMIF('Tabla 2 - Ataques detec (Imple)'!$D$3:$D$112,$B3,'Tabla 2 - Ataques detec (Imple)'!$S$3:$S$112) -> 2 | Y3: =SUMIF('Tabla 2 - Ataques detec (Imple)'!$D$3:$D$112,$B3,'Tabla 2 - Ataques detec (Imple)'!U$3:U$112) -> 9 | Z3: =SUMIF('Tabla 2 - Ataques detec (Imple)'!$D$3:$D$112,$B3,'Tabla 2 - Ataques detec (Imple)'!V$3:V$112) -> 6 | AA3: =Z3 & " (" & Y3 & ")" -> 6 (9) | AB3: =SUMIF('Tabla 2 - Ataques detec (Imple)'!$D$3:$D$112,$B3,'Tabla 2 - Ataques detec (Imple)'!$R$3:$R$112) -> 6 | AC3: =AVERAGEIF('Tabla 2 - Ataques detec (Imple)'!$D$3:$D$112,$B3,'Tabla 2 - Ataques detec (Imple)'!$Y$3:$Y$112) -> 1 | AD3: =SUMIF('Tabla 2 - Ataques detec (Imple)'!$D$3:$D$112,$B3,'Tabla 2 - Ataques detec (Imple)'!$X$3:$X$112) -> 2 | AE3: =SUMIF('Tabla 2 - Ataques detec (Imple)'!$D$3:$D$112,$B3,'Tabla 2 - Ataques detec (Imple)'!Z$3:Z$112) -> 8 | AF3: =SUMIF('Tabla 2 - Ataques detec (Imple)'!$D$3:$D$112,$B3,'Tabla 2 - Ataques detec (Imple)'!AA$3:AA$112) -> 4 | AG3: =AF3 & " (" & AE3 & ")" -> 4 (8) | AH3: =SUMIF('Tabla 2 - Ataques detec (Imple)'!$D$3:$D$112,$B3,'Tabla 2 - Ataques detec (Imple)'!$AB$3:$AB$112) -> 4 | AI3: =AVERAGEIF('Tabla 2 - Ataques detec (Imple)'!$D$3:$D$112,$B3,'Tabla 2 - Ataques detec (Imple)'!$AD$3:$AD$112) -> 1 | AJ3: =SUMIF('Tabla 2 - Ataques detec (Imple)'!$D$3:$D$112,$B3,'Tabla 2 - Ataques detec (Imple)'!$AC$3:$AC$112) -> 2 | AK3: =SUMIF('Tabla 2 - Ataques detec (Imple)'!$D$3:$D$112,$B3,'Tabla 2 - Ataques detec (Imple)'!AE$3:AE$112) -> 17 | AL3: =SUMIF('Tabla 2 - Ataques detec (Imple)'!$D$3:$D$112,$B3,'Tabla 2 - Ataques detec (Imple)'!AF$3:AF$112) -> 10 | AM3: =AL3 & " (" & AK3 & ")" -> 10 (17) | AN3: =SUMIF('Tabla 2 - Ataques detec (Imple)'!$D$3:$D$112,$B3,'Tabla 2 - Ataques detec (Imple)'!$AG$3:$AG$112) -> 10 | AO3: =AVERAGEIF('Tabla 2 - Ataques detec (Imple)'!$D$3:$D$112,$B3,'Tabla 2 - Ataques detec (Imple)'!$AI$3:$AI$112) -> 1 | AP3: =SUMIF('Tabla 2 - Ataques detec (Imple)'!$D$3:$D$112,$B3,'Tabla 2 - Ataques detec (Imple)'!$AH$3:$AH$112) -> 2 | AQ3: =SUMIF('Tabla 2 - Ataques detec (Imple)'!$D$3:$D$112,$B3,'Tabla 2 - Ataques detec (Imple)'!AJ$3:AJ$112) -> 0 | AR3: =SUMIF('Tabla 2 - Ataques detec (Imple)'!$D$3:$D$112,$B3,'Tabla 2 - Ataques detec (Imple)'!AK$3:AK$112) -> 0 | AS3: =AR3 & " (" & AQ3 & ")" -> 0 (0) | AT3: =SUMIF('Tabla 2 - Ataques detec (Imple)'!$D$3:$D$112,$B3,'Tabla 2 - Ataques detec (Imple)'!$AL$3:$AL$112) -> 0 | AU3: =AVERAGEIF('Tabla 2 - Ataques detec (Imple)'!$D$3:$D$112,$B3,'Tabla 2 - Ataques detec (Imple)'!$AN$3:$AN$112) -> 0 | AV3: =SUMIF('Tabla 2 - Ataques detec (Imple)'!$D$3:$D$112,$B3,'Tabla 2 - Ataques detec (Imple)'!$AM$3:$AM$112) -> 0 | AW3: =SUMIF('Tabla 2 - Ataques detec (Imple)'!$D$3:$D$112,$B3,'Tabla 2 - Ataques detec (Imple)'!AO$3:AO$112) -> 0 | AX3: =SUMIF('Tabla 2 - Ataques detec (Imple)'!$D$3:$D$112,$B3,'Tabla 2 - Ataques detec (Imple)'!AP$3:AP$112) -> 0 | AY3: =AX3 & " (" & AW3 & ")" -> 0 (0) | AZ3: =SUMIF('Tabla 2 - Ataques detec (Imple)'!$D$3:$D$112,$B3,'Tabla 2 - Ataques detec (Imple)'!$AQ$3:$AQ$112) -> 0 | BA3: =AVERAGEIF('Tabla 2 - Ataques detec (Imple)'!$D$3:$D$112,$B3,'Tabla 2 - Ataques detec (Imple)'!$AS$3:$AS$112) -> 0 | BB3: =SUMIF('Tabla 2 - Ataques detec (Imple)'!$D$3:$D$112,$B3,'Tabla 2 - Ataques detec (Imple)'!$AR$3:$AR$112) -> 0 | BC3: =SUMIF('Tabla 2 - Ataques detec (Imple)'!$D$3:$D$112,$B3,'Tabla 2 - Ataques detec (Imple)'!AT$3:AT$112) -> 9 | BD3: =SUMIF('Tabla 2 - Ataques detec (Imple)'!$D$3:$D$112,$B3,'Tabla 2 - Ataques detec (Imple)'!AU$3:AU$112) -> 6 | BE3: =BD3 & " (" & BC3 & ")" -> 6 (9) | BF3: =SUMIF('Tabla 2 - Ataques detec (Imple)'!$D$3:$D$112,$B3,'Tabla 2 - Ataques detec (Imple)'!$AV$3:$AV$112) -> 6 | BG3: =AVERAGEIF('Tabla 2 - Ataques detec (Imple)'!$D$3:$D$112,$B3,'Tabla 2 - Ataques detec (Imple)'!$AX$3:$AX$112) -> 1 | BH3: =SUMIF('Tabla 2 - Ataques detec (Imple)'!$D$3:$D$112,$B3,'Tabla 2 - Ataques detec (Imple)'!$AW$3:$AW$112) -> 2 | BI3: =SUMIF('Tabla 2 - Ataques detec (Imple)'!$D$3:$D$112,$B3,'Tabla 2 - Ataques detec (Imple)'!AY$3:AY$112) -> 1 | BJ3: =SUMIF('Tabla 2 - Ataques detec (Imple)'!$D$3:$D$112,$B3,'Tabla 2 - Ataques detec (Imple)'!AZ$3:AZ$112) -> 1 | BK3: =BJ3 & " (" & BI3 & ")" -> 1 (1) | BL3: =SUMIF('Tabla 2 - Ataques detec (Imple)'!$D$3:$D$112,$B3,'Tabla 2 - Ataques detec (Imple)'!BA$3:BA$112) -> 1 | BM3: =AVERAGEIF('Tabla 2 - Ataques detec (Imple)'!$D$3:$D$112,$B3,'Tabla 2 - Ataques detec (Imple)'!$BC$3:$BC$112) -> 0.5 | BN3: =SUMIF('Tabla 2 - Ataques detec (Imple)'!$D$3:$D$112,$B3,'Tabla 2 - Ataques detec (Imple)'!$BB$3:$BB$112) -> 1 | BO3: =SUMIF('Tabla 2 - Ataques detec (Imple)'!$D$3:$D$112,$B3,'Tabla 2 - Ataques detec (Imple)'!BD$3:BD$112) -> 3 | BP3: =SUMIF('Tabla 2 - Ataques detec (Imple)'!$D$3:$D$112,$B3,'Tabla 2 - Ataques detec (Imple)'!BE$3:BE$112) -> 3 | BQ3: =BP3 & " (" & BO3 & ")" -> 3 (3) | BR3: =SUMIF('Tabla 2 - Ataques detec (Imple)'!$D$3:$D$112,$B3,'Tabla 2 - Ataques detec (Imple)'!BF$3:BF$112) -> 1 | BS3: =SUMIF('Tabla 2 - Ataques detec (Imple)'!$D$3:$D$112,$B3,'Tabla 2 - Ataques detec (Imple)'!BG$3:BG$112) -> 2 | BT3: =AVERAGEIF('Tabla 2 - Ataques detec (Imple)'!$D$3:$D$112,$B3,'Tabla 2 - Ataques detec (Imple)'!$BI$3:$BI$112) -> 1 | BU3: =SUMIF('Tabla 2 - Ataques detec (Imple)'!$D$3:$D$112,$B3,'Tabla 2 - Ataques detec (Imple)'!$BH$3:$BH$112) -> 2 | BV3: 3 | BW3: 3 | BX3: =BW3 & " (" & BV3 & ")" -> 3 (3) | BY3: 3 | BZ3: 1 | CA3: 2 | CB3: 6 | CC3: 5 | CD3: =CC3 & " (" & CB3 & ")" -> 5 (6) | CE3: 3 | CF3: 2 | CG3: 1 | CH3: 2
A4: =A3+1 -> 2 | B4: =IFERROR(VLOOKUP(A4,'Tabla 2 - Ataques detec (Imple)'!$B$3:$D$112,3,FALSE),"") -> T1003 | C4: =IFERROR(VLOOKUP(B4,Techniques!$B$3:$H$213,2,FALSE),"") -> OS Credential Dumping | D4: =SUMPRODUCT( ('Tabla 2 - Ataques detec (Imple)'!$D$3:$D$112=$B4)* (LEN('Tabla 2 - Ataques detec (Imple)'!$C$3:$C$112)>0) ) -> 1 | E4: =SUMIF('Tabla 2 - Ataques detec (Imple)'!$D$3:$D$112,$B4,'Tabla 2 - Ataques detec (Imple)'!$E$3:$E$112) -> 3 | F4: =D4&" ("&E4&")" -> 1 (3) | G4: =SUMIF('Tabla 2 - Ataques detec (Imple)'!$D$3:$D$112,$B4,'Tabla 2 - Ataques detec (Imple)'!F$3:F$112) -> 3 | H4: =SUMIF('Tabla 2 - Ataques detec (Imple)'!$D$3:$D$112,$B4,'Tabla 2 - Ataques detec (Imple)'!G$3:G$112) -> 2 | I4: =H4 & " (" & G4 & ")" -> 2 (3) | J4: =SUMIF('Tabla 2 - Ataques detec (Imple)'!$D$3:$D$112,$B4,'Tabla 2 - Ataques detec (Imple)'!$H$3:$H$112) -> 2 | K4: =AVERAGEIF('Tabla 2 - Ataques detec (Imple)'!$D$3:$D$112,$B4,'Tabla 2 - Ataques detec (Imple)'!$J$3:$J$112) -> 1 | L4: =SUMIF('Tabla 2 - Ataques detec (Imple)'!$D$3:$D$112,$B4,'Tabla 2 - Ataques detec (Imple)'!$I$3:$I$112) -> 1 | M4: =SUMIF('Tabla 2 - Ataques detec (Imple)'!$D$3:$D$112,$B4,'Tabla 2 - Ataques detec (Imple)'!K$3:K$112) -> 0 | N4: =SUMIF('Tabla 2 - Ataques detec (Imple)'!$D$3:$D$112,$B4,'Tabla 2 - Ataques detec (Imple)'!L$3:L$112) -> 0 | O4: =N4 & " (" & M4 & ")" -> 0 (0) | P4: =SUMIF('Tabla 2 - Ataques detec (Imple)'!$D$3:$D$112,$B4,'Tabla 2 - Ataques detec (Imple)'!$M$3:$M$112) -> 0 | Q4: =AVERAGEIF('Tabla 2 - Ataques detec (Imple)'!$D$3:$D$112,$B4,'Tabla 2 - Ataques detec (Imple)'!$O$3:$O$112) -> 0 | R4: =SUMIF('Tabla 2 - Ataques detec (Imple)'!$D$3:$D$112,$B4,'Tabla 2 - Ataques detec (Imple)'!$N$3:$N$112) -> 0 | S4: =SUMIF('Tabla 2 - Ataques detec (Imple)'!$D$3:$D$112,$B4,'Tabla 2 - Ataques detec (Imple)'!P$3:P$112) -> 3 | T4: =SUMIF('Tabla 2 - Ataques detec (Imple)'!$D$3:$D$112,$B4,'Tabla 2 - Ataques detec (Imple)'!Q$3:Q$112) -> 2 | U4: =T4 & " (" & S4 & ")" -> 2 (3) | V4: =SUMIF('Tabla 2 - Ataques detec (Imple)'!$D$3:$D$112,$B4,'Tabla 2 - Ataques detec (Imple)'!$R$3:$R$112) -> 2 | W4: =AVERAGEIF('Tabla 2 - Ataques detec (Imple)'!$D$3:$D$112,$B4,'Tabla 2 - Ataques detec (Imple)'!$T$3:$T$112) -> 1 | X4: =SUMIF('Tabla 2 - Ataques detec (Imple)'!$D$3:$D$112,$B4,'Tabla 2 - Ataques detec (Imple)'!$S$3:$S$112) -> 1 | Y4: =SUMIF('Tabla 2 - Ataques detec (Imple)'!$D$3:$D$112,$B4,'Tabla 2 - Ataques detec (Imple)'!U$3:U$112) -> 4 | Z4: =SUMIF('Tabla 2 - Ataques detec (Imple)'!$D$3:$D$112,$B4,'Tabla 2 - Ataques detec (Imple)'!V$3:V$112) -> 3 | AA4: =Z4 & " (" & Y4 & ")" -> 3 (4) | AB4: =SUMIF('Tabla 2 - Ataques detec (Imple)'!$D$3:$D$112,$B4,'Tabla 2 - Ataques detec (Imple)'!$R$3:$R$112) -> 2 | AC4: =AVERAGEIF('Tabla 2 - Ataques detec (Imple)'!$D$3:$D$112,$B4,'Tabla 2 - Ataques detec (Imple)'!$Y$3:$Y$112) -> 1 | AD4: =SUMIF('Tabla 2 - Ataques detec (Imple)'!$D$3:$D$112,$B4,'Tabla 2 - Ataques detec (Imple)'!$X$3:$X$112) -> 2 | AE4: =SUMIF('Tabla 2 - Ataques detec (Imple)'!$D$3:$D$112,$B4,'Tabla 2 - Ataques detec (Imple)'!Z$3:Z$112) -> 4 | AF4: =SUMIF('Tabla 2 - Ataques detec (Imple)'!$D$3:$D$112,$B4,'Tabla 2 - Ataques detec (Imple)'!AA$3:AA$112) -> 2 | AG4: =AF4 & " (" & AE4 & ")" -> 2 (4) | AH4: =SUMIF('Tabla 2 - Ataques detec (Imple)'!$D$3:$D$112,$B4,'Tabla 2 - Ataques detec (Imple)'!$AB$3:$AB$112) -> 2 | AI4: =AVERAGEIF('Tabla 2 - Ataques detec (Imple)'!$D$3:$D$112,$B4,'Tabla 2 - Ataques detec (Imple)'!$AD$3:$AD$112) -> 1 | AJ4: =SUMIF('Tabla 2 - Ataques detec (Imple)'!$D$3:$D$112,$B4,'Tabla 2 - Ataques detec (Imple)'!$AC$3:$AC$112) -> 1 | AK4: =SUMIF('Tabla 2 - Ataques detec (Imple)'!$D$3:$D$112,$B4,'Tabla 2 - Ataques detec (Imple)'!AE$3:AE$112) -> 8 | AL4: =SUMIF('Tabla 2 - Ataques detec (Imple)'!$D$3:$D$112,$B4,'Tabla 2 - Ataques detec (Imple)'!AF$3:AF$112) -> 5 | AM4: =AL4 & " (" & AK4 & ")" -> 5 (8) | AN4: =SUMIF('Tabla 2 - Ataques detec (Imple)'!$D$3:$D$112,$B4,'Tabla 2 - Ataques detec (Imple)'!$AG$3:$AG$112) -> 5 | AO4: =AVERAGEIF('Tabla 2 - Ataques detec (Imple)'!$D$3:$D$112,$B4,'Tabla 2 - Ataques detec (Imple)'!$AI$3:$AI$112) -> 1 | AP4: =SUMIF('Tabla 2 - Ataques detec (Imple)'!$D$3:$D$112,$B4,'Tabla 2 - Ataques detec (Imple)'!$AH$3:$AH$112) -> 3 | AQ4: =SUMIF('Tabla 2 - Ataques detec (Imple)'!$D$3:$D$112,$B4,'Tabla 2 - Ataques detec (Imple)'!AJ$3:AJ$112) -> 0 | AR4: =SUMIF('Tabla 2 - Ataques detec (Imple)'!$D$3:$D$112,$B4,'Tabla 2 - Ataques detec (Imple)'!AK$3:AK$112) -> 0 | AS4: =AR4 & " (" & AQ4 & ")" -> 0 (0) | AT4: =SUMIF('Tabla 2 - Ataques detec (Imple)'!$D$3:$D$112,$B4,'Tabla 2 - Ataques detec (Imple)'!$AL$3:$AL$112) -> 0 | AU4: =AVERAGEIF('Tabla 2 - Ataques detec (Imple)'!$D$3:$D$112,$B4,'Tabla 2 - Ataques detec (Imple)'!$AN$3:$AN$112) -> 0 | AV4: =SUMIF('Tabla 2 - Ataques detec (Imple)'!$D$3:$D$112,$B4,'Tabla 2 - Ataques detec (Imple)'!$AM$3:$AM$112) -> 0 | AW4: =SUMIF('Tabla 2 - Ataques detec (Imple)'!$D$3:$D$112,$B4,'Tabla 2 - Ataques detec (Imple)'!AO$3:AO$112) -> 0 | AX4: =SUMIF('Tabla 2 - Ataques detec (Imple)'!$D$3:$D$112,$B4,'Tabla 2 - Ataques detec (Imple)'!AP$3:AP$112) -> 0 | AY4: =AX4 & " (" & AW4 & ")" -> 0 (0) | AZ4: =SUMIF('Tabla 2 - Ataques detec (Imple)'!$D$3:$D$112,$B4,'Tabla 2 - Ataques detec (Imple)'!$AQ$3:$AQ$112) -> 0 | BA4: =AVERAGEIF('Tabla 2 - Ataques detec (Imple)'!$D$3:$D$112,$B4,'Tabla 2 - Ataques detec (Imple)'!$AS$3:$AS$112) -> 0 | BB4: =SUMIF('Tabla 2 - Ataques detec (Imple)'!$D$3:$D$112,$B4,'Tabla 2 - Ataques detec (Imple)'!$AR$3:$AR$112) -> 0 | BC4: =SUMIF('Tabla 2 - Ataques detec (Imple)'!$D$3:$D$112,$B4,'Tabla 2 - Ataques detec (Imple)'!AT$3:AT$112) -> 3 | BD4: =SUMIF('Tabla 2 - Ataques detec (Imple)'!$D$3:$D$112,$B4,'Tabla 2 - Ataques detec (Imple)'!AU$3:AU$112) -> 2 | BE4: =BD4 & " (" & BC4 & ")" -> 2 (3) | BF4: =SUMIF('Tabla 2 - Ataques detec (Imple)'!$D$3:$D$112,$B4,'Tabla 2 - Ataques detec (Imple)'!$AV$3:$AV$112) -> 2 | BG4: =AVERAGEIF('Tabla 2 - Ataques detec (Imple)'!$D$3:$D$112,$B4,'Tabla 2 - Ataques detec (Imple)'!$AX$3:$AX$112) -> 1 | BH4: =SUMIF('Tabla 2 - Ataques detec (Imple)'!$D$3:$D$112,$B4,'Tabla 2 - Ataques detec (Imple)'!$AW$3:$AW$112) -> 1 | BI4: =SUMIF('Tabla 2 - Ataques detec (Imple)'!$D$3:$D$112,$B4,'Tabla 2 - Ataques detec (Imple)'!AY$3:AY$112) -> 0 | BJ4: =SUMIF('Tabla 2 - Ataques detec (Imple)'!$D$3:$D$112,$B4,'Tabla 2 - Ataques detec (Imple)'!AZ$3:AZ$112) -> 0 | BK4: =BJ4 & " (" & BI4 & ")" -> 0 (0) | BL4: =SUMIF('Tabla 2 - Ataques detec (Imple)'!$D$3:$D$112,$B4,'Tabla 2 - Ataques detec (Imple)'!BA$3:BA$112) -> 0 | BM4: =AVERAGEIF('Tabla 2 - Ataques detec (Imple)'!$D$3:$D$112,$B4,'Tabla 2 - Ataques detec (Imple)'!$BC$3:$BC$112) -> 0 | BN4: =SUMIF('Tabla 2 - Ataques detec (Imple)'!$D$3:$D$112,$B4,'Tabla 2 - Ataques detec (Imple)'!$BB$3:$BB$112) -> 0 | BO4: =SUMIF('Tabla 2 - Ataques detec (Imple)'!$D$3:$D$112,$B4,'Tabla 2 - Ataques detec (Imple)'!BD$3:BD$112) -> 3 | BP4: =SUMIF('Tabla 2 - Ataques detec (Imple)'!$D$3:$D$112,$B4,'Tabla 2 - Ataques detec (Imple)'!BE$3:BE$112) -> 3 | BQ4: =BP4 & " (" & BO4 & ")" -> 3 (3) | BR4: =SUMIF('Tabla 2 - Ataques detec (Imple)'!$D$3:$D$112,$B4,'Tabla 2 - Ataques detec (Imple)'!BF$3:BF$112) -> 0 | BS4: =SUMIF('Tabla 2 - Ataques detec (Imple)'!$D$3:$D$112,$B4,'Tabla 2 - Ataques detec (Imple)'!BG$3:BG$112) -> 3 | BT4: =AVERAGEIF('Tabla 2 - Ataques detec (Imple)'!$D$3:$D$112,$B4,'Tabla 2 - Ataques detec (Imple)'!$BI$3:$BI$112) -> 1 | BU4: =SUMIF('Tabla 2 - Ataques detec (Imple)'!$D$3:$D$112,$B4,'Tabla 2 - Ataques detec (Imple)'!$BH$3:$BH$112) -> 3 | BV4: 0 | BW4: 0 | BX4: =BW4 & " (" & BV4 & ")" -> 0 (0) | BY4: 0 | BZ4: 0 | CA4: 0 | CB4: 0 | CC4: 0 | CD4: =CC4 & " (" & CB4 & ")" -> 0 (0) | CE4: 0 | CF4: 0 | CG4: 0 | CH4: 0
A5: =A4+1 -> 3 | B5: =IFERROR(VLOOKUP(A5,'Tabla 2 - Ataques detec (Imple)'!$B$3:$D$112,3,FALSE),"") -> T1008 | C5: =IFERROR(VLOOKUP(B5,Techniques!$B$3:$H$213,2,FALSE),"") -> Fallback Channels | D5: =SUMPRODUCT( ('Tabla 2 - Ataques detec (Imple)'!$D$3:$D$112=$B5)* (LEN('Tabla 2 - Ataques detec (Imple)'!$C$3:$C$112)>0) ) -> 1 | E5: =SUMIF('Tabla 2 - Ataques detec (Imple)'!$D$3:$D$112,$B5,'Tabla 2 - Ataques detec (Imple)'!$E$3:$E$112) -> 6 | F5: =D5&" ("&E5&")" -> 1 (6) | G5: =SUMIF('Tabla 2 - Ataques detec (Imple)'!$D$3:$D$112,$B5,'Tabla 2 - Ataques detec (Imple)'!F$3:F$112) -> 15 | H5: =SUMIF('Tabla 2 - Ataques detec (Imple)'!$D$3:$D$112,$B5,'Tabla 2 - Ataques detec (Imple)'!G$3:G$112) -> 1 | I5: =H5 & " (" & G5 & ")" -> 1 (15) | J5: =SUMIF('Tabla 2 - Ataques detec (Imple)'!$D$3:$D$112,$B5,'Tabla 2 - Ataques detec (Imple)'!$H$3:$H$112) -> 1 | K5: =AVERAGEIF('Tabla 2 - Ataques detec (Imple)'!$D$3:$D$112,$B5,'Tabla 2 - Ataques detec (Imple)'!$J$3:$J$112) -> 1 | L5: =SUMIF('Tabla 2 - Ataques detec (Imple)'!$D$3:$D$112,$B5,'Tabla 2 - Ataques detec (Imple)'!$I$3:$I$112) -> 1 | M5: =SUMIF('Tabla 2 - Ataques detec (Imple)'!$D$3:$D$112,$B5,'Tabla 2 - Ataques detec (Imple)'!K$3:K$112) -> 17 | N5: =SUMIF('Tabla 2 - Ataques detec (Imple)'!$D$3:$D$112,$B5,'Tabla 2 - Ataques detec (Imple)'!L$3:L$112) -> 7 | O5: =N5 & " (" & M5 & ")" -> 7 (17) | P5: =SUMIF('Tabla 2 - Ataques detec (Imple)'!$D$3:$D$112,$B5,'Tabla 2 - Ataques detec (Imple)'!$M$3:$M$112) -> 4 | Q5: =AVERAGEIF('Tabla 2 - Ataques detec (Imple)'!$D$3:$D$112,$B5,'Tabla 2 - Ataques detec (Imple)'!$O$3:$O$112) -> 1 | R5: =SUMIF('Tabla 2 - Ataques detec (Imple)'!$D$3:$D$112,$B5,'Tabla 2 - Ataques detec (Imple)'!$N$3:$N$112) -> 3 | S5: =SUMIF('Tabla 2 - Ataques detec (Imple)'!$D$3:$D$112,$B5,'Tabla 2 - Ataques detec (Imple)'!P$3:P$112) -> 32 | T5: =SUMIF('Tabla 2 - Ataques detec (Imple)'!$D$3:$D$112,$B5,'Tabla 2 - Ataques detec (Imple)'!Q$3:Q$112) -> 8 | U5: =T5 & " (" & S5 & ")" -> 8 (32) | V5: =SUMIF('Tabla 2 - Ataques detec (Imple)'!$D$3:$D$112,$B5,'Tabla 2 - Ataques detec (Imple)'!$R$3:$R$112) -> 5 | W5: =AVERAGEIF('Tabla 2 - Ataques detec (Imple)'!$D$3:$D$112,$B5,'Tabla 2 - Ataques detec (Imple)'!$T$3:$T$112) -> 1 | X5: =SUMIF('Tabla 2 - Ataques detec (Imple)'!$D$3:$D$112,$B5,'Tabla 2 - Ataques detec (Imple)'!$S$3:$S$112) -> 3 | Y5: =SUMIF('Tabla 2 - Ataques detec (Imple)'!$D$3:$D$112,$B5,'Tabla 2 - Ataques detec (Imple)'!U$3:U$112) -> 99 | Z5: =SUMIF('Tabla 2 - Ataques detec (Imple)'!$D$3:$D$112,$B5,'Tabla 2 - Ataques detec (Imple)'!V$3:V$112) -> 4 | AA5: =Z5 & " (" & Y5 & ")" -> 4 (99) | AB5: =SUMIF('Tabla 2 - Ataques detec (Imple)'!$D$3:$D$112,$B5,'Tabla 2 - Ataques detec (Imple)'!$R$3:$R$112) -> 5 | AC5: =AVERAGEIF('Tabla 2 - Ataques detec (Imple)'!$D$3:$D$112,$B5,'Tabla 2 - Ataques detec (Imple)'!$Y$3:$Y$112) -> 1 | AD5: =SUMIF('Tabla 2 - Ataques detec (Imple)'!$D$3:$D$112,$B5,'Tabla 2 - Ataques detec (Imple)'!$X$3:$X$112) -> 3 | AE5: =SUMIF('Tabla 2 - Ataques detec (Imple)'!$D$3:$D$112,$B5,'Tabla 2 - Ataques detec (Imple)'!Z$3:Z$112) -> 57 | AF5: =SUMIF('Tabla 2 - Ataques detec (Imple)'!$D$3:$D$112,$B5,'Tabla 2 - Ataques detec (Imple)'!AA$3:AA$112) -> 28 | AG5: =AF5 & " (" & AE5 & ")" -> 28 (57) | AH5: =SUMIF('Tabla 2 - Ataques detec (Imple)'!$D$3:$D$112,$B5,'Tabla 2 - Ataques detec (Imple)'!$AB$3:$AB$112) -> 22 | AI5: =AVERAGEIF('Tabla 2 - Ataques detec (Imple)'!$D$3:$D$112,$B5,'Tabla 2 - Ataques detec (Imple)'!$AD$3:$AD$112) -> 1 | AJ5: =SUMIF('Tabla 2 - Ataques detec (Imple)'!$D$3:$D$112,$B5,'Tabla 2 - Ataques detec (Imple)'!$AC$3:$AC$112) -> 5 | AK5: =SUMIF('Tabla 2 - Ataques detec (Imple)'!$D$3:$D$112,$B5,'Tabla 2 - Ataques detec (Imple)'!AE$3:AE$112) -> 156 | AL5: =SUMIF('Tabla 2 - Ataques detec (Imple)'!$D$3:$D$112,$B5,'Tabla 2 - Ataques detec (Imple)'!AF$3:AF$112) -> 32 | AM5: =AL5 & " (" & AK5 & ")" -> 32 (156) | AN5: =SUMIF('Tabla 2 - Ataques detec (Imple)'!$D$3:$D$112,$B5,'Tabla 2 - Ataques detec (Imple)'!$AG$3:$AG$112) -> 25 | AO5: =AVERAGEIF('Tabla 2 - Ataques detec (Imple)'!$D$3:$D$112,$B5,'Tabla 2 - Ataques detec (Imple)'!$AI$3:$AI$112) -> 1 | AP5: =SUMIF('Tabla 2 - Ataques detec (Imple)'!$D$3:$D$112,$B5,'Tabla 2 - Ataques detec (Imple)'!$AH$3:$AH$112) -> 5 | AQ5: =SUMIF('Tabla 2 - Ataques detec (Imple)'!$D$3:$D$112,$B5,'Tabla 2 - Ataques detec (Imple)'!AJ$3:AJ$112) -> 0 | AR5: =SUMIF('Tabla 2 - Ataques detec (Imple)'!$D$3:$D$112,$B5,'Tabla 2 - Ataques detec (Imple)'!AK$3:AK$112) -> 0 | AS5: =AR5 & " (" & AQ5 & ")" -> 0 (0) | AT5: =SUMIF('Tabla 2 - Ataques detec (Imple)'!$D$3:$D$112,$B5,'Tabla 2 - Ataques detec (Imple)'!$AL$3:$AL$112) -> 0 | AU5: =AVERAGEIF('Tabla 2 - Ataques detec (Imple)'!$D$3:$D$112,$B5,'Tabla 2 - Ataques detec (Imple)'!$AN$3:$AN$112) -> 0 | AV5: =SUMIF('Tabla 2 - Ataques detec (Imple)'!$D$3:$D$112,$B5,'Tabla 2 - Ataques detec (Imple)'!$AM$3:$AM$112) -> 0 | AW5: =SUMIF('Tabla 2 - Ataques detec (Imple)'!$D$3:$D$112,$B5,'Tabla 2 - Ataques detec (Imple)'!AO$3:AO$112) -> 0 | AX5: =SUMIF('Tabla 2 - Ataques detec (Imple)'!$D$3:$D$112,$B5,'Tabla 2 - Ataques detec (Imple)'!AP$3:AP$112) -> 0 | AY5: =AX5 & " (" & AW5 & ")" -> 0 (0) | AZ5: =SUMIF('Tabla 2 - Ataques detec (Imple)'!$D$3:$D$112,$B5,'Tabla 2 - Ataques detec (Imple)'!$AQ$3:$AQ$112) -> 0 | BA5: =AVERAGEIF('Tabla 2 - Ataques detec (Imple)'!$D$3:$D$112,$B5,'Tabla 2 - Ataques detec (Imple)'!$AS$3:$AS$112) -> 0 | BB5: =SUMIF('Tabla 2 - Ataques detec (Imple)'!$D$3:$D$112,$B5,'Tabla 2 - Ataques detec (Imple)'!$AR$3:$AR$112) -> 0 | BC5: =SUMIF('Tabla 2 - Ataques detec (Imple)'!$D$3:$D$112,$B5,'Tabla 2 - Ataques detec (Imple)'!AT$3:AT$112) -> 32 | BD5: =SUMIF('Tabla 2 - Ataques detec (Imple)'!$D$3:$D$112,$B5,'Tabla 2 - Ataques detec (Imple)'!AU$3:AU$112) -> 8 | BE5: =BD5 & " (" & BC5 & ")" -> 8 (32) | BF5: =SUMIF('Tabla 2 - Ataques detec (Imple)'!$D$3:$D$112,$B5,'Tabla 2 - Ataques detec (Imple)'!$AV$3:$AV$112) -> 5 | BG5: =AVERAGEIF('Tabla 2 - Ataques detec (Imple)'!$D$3:$D$112,$B5,'Tabla 2 - Ataques detec (Imple)'!$AX$3:$AX$112) -> 1 | BH5: =SUMIF('Tabla 2 - Ataques detec (Imple)'!$D$3:$D$112,$B5,'Tabla 2 - Ataques detec (Imple)'!$AW$3:$AW$112) -> 3 | BI5: =SUMIF('Tabla 2 - Ataques detec (Imple)'!$D$3:$D$112,$B5,'Tabla 2 - Ataques detec (Imple)'!AY$3:AY$112) -> 6 | BJ5: =SUMIF('Tabla 2 - Ataques detec (Imple)'!$D$3:$D$112,$B5,'Tabla 2 - Ataques detec (Imple)'!AZ$3:AZ$112) -> 4 | BK5: =BJ5 & " (" & BI5 & ")" -> 4 (6) | BL5: =SUMIF('Tabla 2 - Ataques detec (Imple)'!$D$3:$D$112,$B5,'Tabla 2 - Ataques detec (Imple)'!BA$3:BA$112) -> 2 | BM5: =AVERAGEIF('Tabla 2 - Ataques detec (Imple)'!$D$3:$D$112,$B5,'Tabla 2 - Ataques detec (Imple)'!$BC$3:$BC$112) -> 1 | BN5: =SUMIF('Tabla 2 - Ataques detec (Imple)'!$D$3:$D$112,$B5,'Tabla 2 - Ataques detec (Imple)'!$BB$3:$BB$112) -> 2 | BO5: =SUMIF('Tabla 2 - Ataques detec (Imple)'!$D$3:$D$112,$B5,'Tabla 2 - Ataques detec (Imple)'!BD$3:BD$112) -> 17 | BP5: =SUMIF('Tabla 2 - Ataques detec (Imple)'!$D$3:$D$112,$B5,'Tabla 2 - Ataques detec (Imple)'!BE$3:BE$112) -> 12 | BQ5: =BP5 & " (" & BO5 & ")" -> 12 (17) | BR5: =SUMIF('Tabla 2 - Ataques detec (Imple)'!$D$3:$D$112,$B5,'Tabla 2 - Ataques detec (Imple)'!BF$3:BF$112) -> 2 | BS5: =SUMIF('Tabla 2 - Ataques detec (Imple)'!$D$3:$D$112,$B5,'Tabla 2 - Ataques detec (Imple)'!BG$3:BG$112) -> 6 | BT5: =AVERAGEIF('Tabla 2 - Ataques detec (Imple)'!$D$3:$D$112,$B5,'Tabla 2 - Ataques detec (Imple)'!$BI$3:$BI$112) -> 1 | BU5: =SUMIF('Tabla 2 - Ataques detec (Imple)'!$D$3:$D$112,$B5,'Tabla 2 - Ataques detec (Imple)'!$BH$3:$BH$112) -> 5 | BV5: 11 | BW5: 5 | BX5: =BW5 & " (" & BV5 & ")" -> 5 (11) | BY5: 3 | BZ5: 1 | CA5: 3 | CB5: 22 | CC5: 8 | CD5: =CC5 & " (" & CB5 & ")" -> 8 (22) | CE5: 3 | CF5: 2 | CG5: 1 | CH5: 3
A6: =A5+1 -> 4 | B6: =IFERROR(VLOOKUP(A6,'Tabla 2 - Ataques detec (Imple)'!$B$3:$D$112,3,FALSE),"") -> T1011 | C6: =IFERROR(VLOOKUP(B6,Techniques!$B$3:$H$213,2,FALSE),"") -> Exfiltration Over Other Network Medium | D6: =SUMPRODUCT( ('Tabla 2 - Ataques detec (Imple)'!$D$3:$D$112=$B6)* (LEN('Tabla 2 - Ataques detec (Imple)'!$C$3:$C$112)>0) ) -> 1 | E6: =SUMIF('Tabla 2 - Ataques detec (Imple)'!$D$3:$D$112,$B6,'Tabla 2 - Ataques detec (Imple)'!$E$3:$E$112) -> 1 | F6: =D6&" ("&E6&")" -> 1 (1) | G6: =SUMIF('Tabla 2 - Ataques detec (Imple)'!$D$3:$D$112,$B6,'Tabla 2 - Ataques detec (Imple)'!F$3:F$112) -> 1 | H6: =SUMIF('Tabla 2 - Ataques detec (Imple)'!$D$3:$D$112,$B6,'Tabla 2 - Ataques detec (Imple)'!G$3:G$112) -> 1 | I6: =H6 & " (" & G6 & ")" -> 1 (1) | J6: =SUMIF('Tabla 2 - Ataques detec (Imple)'!$D$3:$D$112,$B6,'Tabla 2 - Ataques detec (Imple)'!$H$3:$H$112) -> 1 | K6: =AVERAGEIF('Tabla 2 - Ataques detec (Imple)'!$D$3:$D$112,$B6,'Tabla 2 - Ataques detec (Imple)'!$J$3:$J$112) -> 1 | L6: =SUMIF('Tabla 2 - Ataques detec (Imple)'!$D$3:$D$112,$B6,'Tabla 2 - Ataques detec (Imple)'!$I$3:$I$112) -> 1 | M6: =SUMIF('Tabla 2 - Ataques detec (Imple)'!$D$3:$D$112,$B6,'Tabla 2 - Ataques detec (Imple)'!K$3:K$112) -> 0 | N6: =SUMIF('Tabla 2 - Ataques detec (Imple)'!$D$3:$D$112,$B6,'Tabla 2 - Ataques detec (Imple)'!L$3:L$112) -> 0 | O6: =N6 & " (" & M6 & ")" -> 0 (0) | P6: =SUMIF('Tabla 2 - Ataques detec (Imple)'!$D$3:$D$112,$B6,'Tabla 2 - Ataques detec (Imple)'!$M$3:$M$112) -> 0 | Q6: =AVERAGEIF('Tabla 2 - Ataques detec (Imple)'!$D$3:$D$112,$B6,'Tabla 2 - Ataques detec (Imple)'!$O$3:$O$112) -> 0 | R6: =SUMIF('Tabla 2 - Ataques detec (Imple)'!$D$3:$D$112,$B6,'Tabla 2 - Ataques detec (Imple)'!$N$3:$N$112) -> 0 | S6: =SUMIF('Tabla 2 - Ataques detec (Imple)'!$D$3:$D$112,$B6,'Tabla 2 - Ataques detec (Imple)'!P$3:P$112) -> 1 | T6: =SUMIF('Tabla 2 - Ataques detec (Imple)'!$D$3:$D$112,$B6,'Tabla 2 - Ataques detec (Imple)'!Q$3:Q$112) -> 1 | U6: =T6 & " (" & S6 & ")" -> 1 (1) | V6: =SUMIF('Tabla 2 - Ataques detec (Imple)'!$D$3:$D$112,$B6,'Tabla 2 - Ataques detec (Imple)'!$R$3:$R$112) -> 1 | W6: =AVERAGEIF('Tabla 2 - Ataques detec (Imple)'!$D$3:$D$112,$B6,'Tabla 2 - Ataques detec (Imple)'!$T$3:$T$112) -> 1 | X6: =SUMIF('Tabla 2 - Ataques detec (Imple)'!$D$3:$D$112,$B6,'Tabla 2 - Ataques detec (Imple)'!$S$3:$S$112) -> 1 | Y6: =SUMIF('Tabla 2 - Ataques detec (Imple)'!$D$3:$D$112,$B6,'Tabla 2 - Ataques detec (Imple)'!U$3:U$112) -> 1 | Z6: =SUMIF('Tabla 2 - Ataques detec (Imple)'!$D$3:$D$112,$B6,'Tabla 2 - Ataques detec (Imple)'!V$3:V$112) -> 1 | AA6: =Z6 & " (" & Y6 & ")" -> 1 (1) | AB6: =SUMIF('Tabla 2 - Ataques detec (Imple)'!$D$3:$D$112,$B6,'Tabla 2 - Ataques detec (Imple)'!$R$3:$R$112) -> 1 | AC6: =AVERAGEIF('Tabla 2 - Ataques detec (Imple)'!$D$3:$D$112,$B6,'Tabla 2 - Ataques detec (Imple)'!$Y$3:$Y$112) -> 1 | AD6: =SUMIF('Tabla 2 - Ataques detec (Imple)'!$D$3:$D$112,$B6,'Tabla 2 - Ataques detec (Imple)'!$X$3:$X$112) -> 1 | AE6: =SUMIF('Tabla 2 - Ataques detec (Imple)'!$D$3:$D$112,$B6,'Tabla 2 - Ataques detec (Imple)'!Z$3:Z$112) -> 4 | AF6: =SUMIF('Tabla 2 - Ataques detec (Imple)'!$D$3:$D$112,$B6,'Tabla 2 - Ataques detec (Imple)'!AA$3:AA$112) -> 2 | AG6: =AF6 & " (" & AE6 & ")" -> 2 (4) | AH6: =SUMIF('Tabla 2 - Ataques detec (Imple)'!$D$3:$D$112,$B6,'Tabla 2 - Ataques detec (Imple)'!$AB$3:$AB$112) -> 2 | AI6: =AVERAGEIF('Tabla 2 - Ataques detec (Imple)'!$D$3:$D$112,$B6,'Tabla 2 - Ataques detec (Imple)'!$AD$3:$AD$112) -> 1 | AJ6: =SUMIF('Tabla 2 - Ataques detec (Imple)'!$D$3:$D$112,$B6,'Tabla 2 - Ataques detec (Imple)'!$AC$3:$AC$112) -> 1 | AK6: =SUMIF('Tabla 2 - Ataques detec (Imple)'!$D$3:$D$112,$B6,'Tabla 2 - Ataques detec (Imple)'!AE$3:AE$112) -> 5 | AL6: =SUMIF('Tabla 2 - Ataques detec (Imple)'!$D$3:$D$112,$B6,'Tabla 2 - Ataques detec (Imple)'!AF$3:AF$112) -> 3 | AM6: =AL6 & " (" & AK6 & ")" -> 3 (5) | AN6: =SUMIF('Tabla 2 - Ataques detec (Imple)'!$D$3:$D$112,$B6,'Tabla 2 - Ataques detec (Imple)'!$AG$3:$AG$112) -> 3 | AO6: =AVERAGEIF('Tabla 2 - Ataques detec (Imple)'!$D$3:$D$112,$B6,'Tabla 2 - Ataques detec (Imple)'!$AI$3:$AI$112) -> 1 | AP6: =SUMIF('Tabla 2 - Ataques detec (Imple)'!$D$3:$D$112,$B6,'Tabla 2 - Ataques detec (Imple)'!$AH$3:$AH$112) -> 1 | AQ6: =SUMIF('Tabla 2 - Ataques detec (Imple)'!$D$3:$D$112,$B6,'Tabla 2 - Ataques detec (Imple)'!AJ$3:AJ$112) -> 0 | AR6: =SUMIF('Tabla 2 - Ataques detec (Imple)'!$D$3:$D$112,$B6,'Tabla 2 - Ataques detec (Imple)'!AK$3:AK$112) -> 0 | AS6: =AR6 & " (" & AQ6 & ")" -> 0 (0) | AT6: =SUMIF('Tabla 2 - Ataques detec (Imple)'!$D$3:$D$112,$B6,'Tabla 2 - Ataques detec (Imple)'!$AL$3:$AL$112) -> 0 | AU6: =AVERAGEIF('Tabla 2 - Ataques detec (Imple)'!$D$3:$D$112,$B6,'Tabla 2 - Ataques detec (Imple)'!$AN$3:$AN$112) -> 0 | AV6: =SUMIF('Tabla 2 - Ataques detec (Imple)'!$D$3:$D$112,$B6,'Tabla 2 - Ataques detec (Imple)'!$AM$3:$AM$112) -> 0 | AW6: =SUMIF('Tabla 2 - Ataques detec (Imple)'!$D$3:$D$112,$B6,'Tabla 2 - Ataques detec (Imple)'!AO$3:AO$112) -> 0 | AX6: =SUMIF('Tabla 2 - Ataques detec (Imple)'!$D$3:$D$112,$B6,'Tabla 2 - Ataques detec (Imple)'!AP$3:AP$112) -> 0 | AY6: =AX6 & " (" & AW6 & ")" -> 0 (0) | AZ6: =SUMIF('Tabla 2 - Ataques detec (Imple)'!$D$3:$D$112,$B6,'Tabla 2 - Ataques detec (Imple)'!$AQ$3:$AQ$112) -> 0 | BA6: =AVERAGEIF('Tabla 2 - Ataques detec (Imple)'!$D$3:$D$112,$B6,'Tabla 2 - Ataques detec (Imple)'!$AS$3:$AS$112) -> 0 | BB6: =SUMIF('Tabla 2 - Ataques detec (Imple)'!$D$3:$D$112,$B6,'Tabla 2 - Ataques detec (Imple)'!$AR$3:$AR$112) -> 0 | BC6: =SUMIF('Tabla 2 - Ataques detec (Imple)'!$D$3:$D$112,$B6,'Tabla 2 - Ataques detec (Imple)'!AT$3:AT$112) -> 1 | BD6: =SUMIF('Tabla 2 - Ataques detec (Imple)'!$D$3:$D$112,$B6,'Tabla 2 - Ataques detec (Imple)'!AU$3:AU$112) -> 1 | BE6: =BD6 & " (" & BC6 & ")" -> 1 (1) | BF6: =SUMIF('Tabla 2 - Ataques detec (Imple)'!$D$3:$D$112,$B6,'Tabla 2 - Ataques detec (Imple)'!$AV$3:$AV$112) -> 1 | BG6: =AVERAGEIF('Tabla 2 - Ataques detec (Imple)'!$D$3:$D$112,$B6,'Tabla 2 - Ataques detec (Imple)'!$AX$3:$AX$112) -> 1 | BH6: =SUMIF('Tabla 2 - Ataques detec (Imple)'!$D$3:$D$112,$B6,'Tabla 2 - Ataques detec (Imple)'!$AW$3:$AW$112) -> 1 | BI6: =SUMIF('Tabla 2 - Ataques detec (Imple)'!$D$3:$D$112,$B6,'Tabla 2 - Ataques detec (Imple)'!AY$3:AY$112) -> 0 | BJ6: =SUMIF('Tabla 2 - Ataques detec (Imple)'!$D$3:$D$112,$B6,'Tabla 2 - Ataques detec (Imple)'!AZ$3:AZ$112) -> 0 | BK6: =BJ6 & " (" & BI6 & ")" -> 0 (0) | BL6: =SUMIF('Tabla 2 - Ataques detec (Imple)'!$D$3:$D$112,$B6,'Tabla 2 - Ataques detec (Imple)'!BA$3:BA$112) -> 0 | BM6: =AVERAGEIF('Tabla 2 - Ataques detec (Imple)'!$D$3:$D$112,$B6,'Tabla 2 - Ataques detec (Imple)'!$BC$3:$BC$112) -> 0 | BN6: =SUMIF('Tabla 2 - Ataques detec (Imple)'!$D$3:$D$112,$B6,'Tabla 2 - Ataques detec (Imple)'!$BB$3:$BB$112) -> 0 | BO6: =SUMIF('Tabla 2 - Ataques detec (Imple)'!$D$3:$D$112,$B6,'Tabla 2 - Ataques detec (Imple)'!BD$3:BD$112) -> 0 | BP6: =SUMIF('Tabla 2 - Ataques detec (Imple)'!$D$3:$D$112,$B6,'Tabla 2 - Ataques detec (Imple)'!BE$3:BE$112) -> 0 | BQ6: =BP6 & " (" & BO6 & ")" -> 0 (0) | BR6: =SUMIF('Tabla 2 - Ataques detec (Imple)'!$D$3:$D$112,$B6,'Tabla 2 - Ataques detec (Imple)'!BF$3:BF$112) -> 0 | BS6: =SUMIF('Tabla 2 - Ataques detec (Imple)'!$D$3:$D$112,$B6,'Tabla 2 - Ataques detec (Imple)'!BG$3:BG$112) -> 0 | BT6: =AVERAGEIF('Tabla 2 - Ataques detec (Imple)'!$D$3:$D$112,$B6,'Tabla 2 - Ataques detec (Imple)'!$BI$3:$BI$112) -> 0 | BU6: =SUMIF('Tabla 2 - Ataques detec (Imple)'!$D$3:$D$112,$B6,'Tabla 2 - Ataques detec (Imple)'!$BH$3:$BH$112) -> 0 | BV6: 0 | BW6: 0 | BX6: =BW6 & " (" & BV6 & ")" -> 0 (0) | BY6: 0 | BZ6: 0 | CA6: 0 | CB6: 0 | CC6: 0 | CD6: =CC6 & " (" & CB6 & ")" -> 0 (0) | CE6: 0 | CF6: 0 | CG6: 0 | CH6: 0
A7: =A6+1 -> 5 | B7: =IFERROR(VLOOKUP(A7,'Tabla 2 - Ataques detec (Imple)'!$B$3:$D$112,3,FALSE),"") -> T1018 | C7: =IFERROR(VLOOKUP(B7,Techniques!$B$3:$H$213,2,FALSE),"") -> Remote System Discovery | D7: =SUMPRODUCT( ('Tabla 2 - Ataques detec (Imple)'!$D$3:$D$112=$B7)* (LEN('Tabla 2 - Ataques detec (Imple)'!$C$3:$C$112)>0) ) -> 1 | E7: =SUMIF('Tabla 2 - Ataques detec (Imple)'!$D$3:$D$112,$B7,'Tabla 2 - Ataques detec (Imple)'!$E$3:$E$112) -> 1002 | F7: =D7&" ("&E7&")" -> 1 (1002) | G7: =SUMIF('Tabla 2 - Ataques detec (Imple)'!$D$3:$D$112,$B7,'Tabla 2 - Ataques detec (Imple)'!F$3:F$112) -> 0 | H7: =SUMIF('Tabla 2 - Ataques detec (Imple)'!$D$3:$D$112,$B7,'Tabla 2 - Ataques detec (Imple)'!G$3:G$112) -> 0 | I7: =H7 & " (" & G7 & ")" -> 0 (0) | J7: =SUMIF('Tabla 2 - Ataques detec (Imple)'!$D$3:$D$112,$B7,'Tabla 2 - Ataques detec (Imple)'!$H$3:$H$112) -> 0 | K7: =AVERAGEIF('Tabla 2 - Ataques detec (Imple)'!$D$3:$D$112,$B7,'Tabla 2 - Ataques detec (Imple)'!$J$3:$J$112) -> 0 | L7: =SUMIF('Tabla 2 - Ataques detec (Imple)'!$D$3:$D$112,$B7,'Tabla 2 - Ataques detec (Imple)'!$I$3:$I$112) -> 0 | M7: =SUMIF('Tabla 2 - Ataques detec (Imple)'!$D$3:$D$112,$B7,'Tabla 2 - Ataques detec (Imple)'!K$3:K$112) -> 6 | N7: =SUMIF('Tabla 2 - Ataques detec (Imple)'!$D$3:$D$112,$B7,'Tabla 2 - Ataques detec (Imple)'!L$3:L$112) -> 6 | O7: =N7 & " (" & M7 & ")" -> 6 (6) | P7: =SUMIF('Tabla 2 - Ataques detec (Imple)'!$D$3:$D$112,$B7,'Tabla 2 - Ataques detec (Imple)'!$M$3:$M$112) -> 6 | Q7: =AVERAGEIF('Tabla 2 - Ataques detec (Imple)'!$D$3:$D$112,$B7,'Tabla 2 - Ataques detec (Imple)'!$O$3:$O$112) -> 1 | R7: =SUMIF('Tabla 2 - Ataques detec (Imple)'!$D$3:$D$112,$B7,'Tabla 2 - Ataques detec (Imple)'!$N$3:$N$112) -> 6 | S7: =SUMIF('Tabla 2 - Ataques detec (Imple)'!$D$3:$D$112,$B7,'Tabla 2 - Ataques detec (Imple)'!P$3:P$112) -> 6 | T7: =SUMIF('Tabla 2 - Ataques detec (Imple)'!$D$3:$D$112,$B7,'Tabla 2 - Ataques detec (Imple)'!Q$3:Q$112) -> 6 | U7: =T7 & " (" & S7 & ")" -> 6 (6) | V7: =SUMIF('Tabla 2 - Ataques detec (Imple)'!$D$3:$D$112,$B7,'Tabla 2 - Ataques detec (Imple)'!$R$3:$R$112) -> 6 | W7: =AVERAGEIF('Tabla 2 - Ataques detec (Imple)'!$D$3:$D$112,$B7,'Tabla 2 - Ataques detec (Imple)'!$T$3:$T$112) -> 1 | X7: =SUMIF('Tabla 2 - Ataques detec (Imple)'!$D$3:$D$112,$B7,'Tabla 2 - Ataques detec (Imple)'!$S$3:$S$112) -> 6 | Y7: =SUMIF('Tabla 2 - Ataques detec (Imple)'!$D$3:$D$112,$B7,'Tabla 2 - Ataques detec (Imple)'!U$3:U$112) -> 2 | Z7: =SUMIF('Tabla 2 - Ataques detec (Imple)'!$D$3:$D$112,$B7,'Tabla 2 - Ataques detec (Imple)'!V$3:V$112) -> 2 | AA7: =Z7 & " (" & Y7 & ")" -> 2 (2) | AB7: =SUMIF('Tabla 2 - Ataques detec (Imple)'!$D$3:$D$112,$B7,'Tabla 2 - Ataques detec (Imple)'!$R$3:$R$112) -> 6 | AC7: =AVERAGEIF('Tabla 2 - Ataques detec (Imple)'!$D$3:$D$112,$B7,'Tabla 2 - Ataques detec (Imple)'!$Y$3:$Y$112) -> 1 | AD7: =SUMIF('Tabla 2 - Ataques detec (Imple)'!$D$3:$D$112,$B7,'Tabla 2 - Ataques detec (Imple)'!$X$3:$X$112) -> 2 | AE7: =SUMIF('Tabla 2 - Ataques detec (Imple)'!$D$3:$D$112,$B7,'Tabla 2 - Ataques detec (Imple)'!Z$3:Z$112) -> 11 | AF7: =SUMIF('Tabla 2 - Ataques detec (Imple)'!$D$3:$D$112,$B7,'Tabla 2 - Ataques detec (Imple)'!AA$3:AA$112) -> 9 | AG7: =AF7 & " (" & AE7 & ")" -> 9 (11) | AH7: =SUMIF('Tabla 2 - Ataques detec (Imple)'!$D$3:$D$112,$B7,'Tabla 2 - Ataques detec (Imple)'!$AB$3:$AB$112) -> 9 | AI7: =AVERAGEIF('Tabla 2 - Ataques detec (Imple)'!$D$3:$D$112,$B7,'Tabla 2 - Ataques detec (Imple)'!$AD$3:$AD$112) -> 1 | AJ7: =SUMIF('Tabla 2 - Ataques detec (Imple)'!$D$3:$D$112,$B7,'Tabla 2 - Ataques detec (Imple)'!$AC$3:$AC$112) -> 8 | AK7: =SUMIF('Tabla 2 - Ataques detec (Imple)'!$D$3:$D$112,$B7,'Tabla 2 - Ataques detec (Imple)'!AE$3:AE$112) -> 13 | AL7: =SUMIF('Tabla 2 - Ataques detec (Imple)'!$D$3:$D$112,$B7,'Tabla 2 - Ataques detec (Imple)'!AF$3:AF$112) -> 11 | AM7: =AL7 & " (" & AK7 & ")" -> 11 (13) | AN7: =SUMIF('Tabla 2 - Ataques detec (Imple)'!$D$3:$D$112,$B7,'Tabla 2 - Ataques detec (Imple)'!$AG$3:$AG$112) -> 11 | AO7: =AVERAGEIF('Tabla 2 - Ataques detec (Imple)'!$D$3:$D$112,$B7,'Tabla 2 - Ataques detec (Imple)'!$AI$3:$AI$112) -> 1 | AP7: =SUMIF('Tabla 2 - Ataques detec (Imple)'!$D$3:$D$112,$B7,'Tabla 2 - Ataques detec (Imple)'!$AH$3:$AH$112) -> 9 | AQ7: =SUMIF('Tabla 2 - Ataques detec (Imple)'!$D$3:$D$112,$B7,'Tabla 2 - Ataques detec (Imple)'!AJ$3:AJ$112) -> 0 | AR7: =SUMIF('Tabla 2 - Ataques detec (Imple)'!$D$3:$D$112,$B7,'Tabla 2 - Ataques detec (Imple)'!AK$3:AK$112) -> 0 | AS7: =AR7 & " (" & AQ7 & ")" -> 0 (0) | AT7: =SUMIF('Tabla 2 - Ataques detec (Imple)'!$D$3:$D$112,$B7,'Tabla 2 - Ataques detec (Imple)'!$AL$3:$AL$112) -> 0 | AU7: =AVERAGEIF('Tabla 2 - Ataques detec (Imple)'!$D$3:$D$112,$B7,'Tabla 2 - Ataques detec (Imple)'!$AN$3:$AN$112) -> 0 | AV7: =SUMIF('Tabla 2 - Ataques detec (Imple)'!$D$3:$D$112,$B7,'Tabla 2 - Ataques detec (Imple)'!$AM$3:$AM$112) -> 0 | AW7: =SUMIF('Tabla 2 - Ataques detec (Imple)'!$D$3:$D$112,$B7,'Tabla 2 - Ataques detec (Imple)'!AO$3:AO$112) -> 2 | AX7: =SUMIF('Tabla 2 - Ataques detec (Imple)'!$D$3:$D$112,$B7,'Tabla 2 - Ataques detec (Imple)'!AP$3:AP$112) -> 2 | AY7: =AX7 & " (" & AW7 & ")" -> 2 (2) | AZ7: =SUMIF('Tabla 2 - Ataques detec (Imple)'!$D$3:$D$112,$B7,'Tabla 2 - Ataques detec (Imple)'!$AQ$3:$AQ$112) -> 2 | BA7: =AVERAGEIF('Tabla 2 - Ataques detec (Imple)'!$D$3:$D$112,$B7,'Tabla 2 - Ataques detec (Imple)'!$AS$3:$AS$112) -> 1 | BB7: =SUMIF('Tabla 2 - Ataques detec (Imple)'!$D$3:$D$112,$B7,'Tabla 2 - Ataques detec (Imple)'!$AR$3:$AR$112) -> 2 | BC7: =SUMIF('Tabla 2 - Ataques detec (Imple)'!$D$3:$D$112,$B7,'Tabla 2 - Ataques detec (Imple)'!AT$3:AT$112) -> 8 | BD7: =SUMIF('Tabla 2 - Ataques detec (Imple)'!$D$3:$D$112,$B7,'Tabla 2 - Ataques detec (Imple)'!AU$3:AU$112) -> 8 | BE7: =BD7 & " (" & BC7 & ")" -> 8 (8) | BF7: =SUMIF('Tabla 2 - Ataques detec (Imple)'!$D$3:$D$112,$B7,'Tabla 2 - Ataques detec (Imple)'!$AV$3:$AV$112) -> 8 | BG7: =AVERAGEIF('Tabla 2 - Ataques detec (Imple)'!$D$3:$D$112,$B7,'Tabla 2 - Ataques detec (Imple)'!$AX$3:$AX$112) -> 1 | BH7: =SUMIF('Tabla 2 - Ataques detec (Imple)'!$D$3:$D$112,$B7,'Tabla 2 - Ataques detec (Imple)'!$AW$3:$AW$112) -> 8 | BI7: =SUMIF('Tabla 2 - Ataques detec (Imple)'!$D$3:$D$112,$B7,'Tabla 2 - Ataques detec (Imple)'!AY$3:AY$112) -> 6 | BJ7: =SUMIF('Tabla 2 - Ataques detec (Imple)'!$D$3:$D$112,$B7,'Tabla 2 - Ataques detec (Imple)'!AZ$3:AZ$112) -> 6 | BK7: =BJ7 & " (" & BI7 & ")" -> 6 (6) | BL7: =SUMIF('Tabla 2 - Ataques detec (Imple)'!$D$3:$D$112,$B7,'Tabla 2 - Ataques detec (Imple)'!BA$3:BA$112) -> 1 | BM7: =AVERAGEIF('Tabla 2 - Ataques detec (Imple)'!$D$3:$D$112,$B7,'Tabla 2 - Ataques detec (Imple)'!$BC$3:$BC$112) -> 1 | BN7: =SUMIF('Tabla 2 - Ataques detec (Imple)'!$D$3:$D$112,$B7,'Tabla 2 - Ataques detec (Imple)'!$BB$3:$BB$112) -> 6 | BO7: =SUMIF('Tabla 2 - Ataques detec (Imple)'!$D$3:$D$112,$B7,'Tabla 2 - Ataques detec (Imple)'!BD$3:BD$112) -> 6 | BP7: =SUMIF('Tabla 2 - Ataques detec (Imple)'!$D$3:$D$112,$B7,'Tabla 2 - Ataques detec (Imple)'!BE$3:BE$112) -> 6 | BQ7: =BP7 & " (" & BO7 & ")" -> 6 (6) | BR7: =SUMIF('Tabla 2 - Ataques detec (Imple)'!$D$3:$D$112,$B7,'Tabla 2 - Ataques detec (Imple)'!BF$3:BF$112) -> 1 | BS7: =SUMIF('Tabla 2 - Ataques detec (Imple)'!$D$3:$D$112,$B7,'Tabla 2 - Ataques detec (Imple)'!BG$3:BG$112) -> 0 | BT7: =AVERAGEIF('Tabla 2 - Ataques detec (Imple)'!$D$3:$D$112,$B7,'Tabla 2 - Ataques detec (Imple)'!$BI$3:$BI$112) -> 1 | BU7: =SUMIF('Tabla 2 - Ataques detec (Imple)'!$D$3:$D$112,$B7,'Tabla 2 - Ataques detec (Imple)'!$BH$3:$BH$112) -> 6 | BV7: 0 | BW7: 0 | BX7: =BW7 & " (" & BV7 & ")" -> 0 (0) | BY7: 0 | BZ7: 0 | CA7: 0 | CB7: 0 | CC7: 0 | CD7: =CC7 & " (" & CB7 & ")" -> 0 (0) | CE7: 0 | CF7: 0 | CG7: 0 | CH7: 0
A8: =A7+1 -> 6 | B8: =IFERROR(VLOOKUP(A8,'Tabla 2 - Ataques detec (Imple)'!$B$3:$D$112,3,FALSE),"") -> T1020 | C8: =IFERROR(VLOOKUP(B8,Techniques!$B$3:$H$213,2,FALSE),"") -> Automated Exfiltration | D8: =SUMPRODUCT( ('Tabla 2 - Ataques detec (Imple)'!$D$3:$D$112=$B8)* (LEN('Tabla 2 - Ataques detec (Imple)'!$C$3:$C$112)>0) ) -> 1 | E8: =SUMIF('Tabla 2 - Ataques detec (Imple)'!$D$3:$D$112,$B8,'Tabla 2 - Ataques detec (Imple)'!$E$3:$E$112) -> 26 | F8: =D8&" ("&E8&")" -> 1 (26) | G8: =SUMIF('Tabla 2 - Ataques detec (Imple)'!$D$3:$D$112,$B8,'Tabla 2 - Ataques detec (Imple)'!F$3:F$112) -> 11 | H8: =SUMIF('Tabla 2 - Ataques detec (Imple)'!$D$3:$D$112,$B8,'Tabla 2 - Ataques detec (Imple)'!G$3:G$112) -> 2 | I8: =H8 & " (" & G8 & ")" -> 2 (11) | J8: =SUMIF('Tabla 2 - Ataques detec (Imple)'!$D$3:$D$112,$B8,'Tabla 2 - Ataques detec (Imple)'!$H$3:$H$112) -> 1 | K8: =AVERAGEIF('Tabla 2 - Ataques detec (Imple)'!$D$3:$D$112,$B8,'Tabla 2 - Ataques detec (Imple)'!$J$3:$J$112) -> 1 | L8: =SUMIF('Tabla 2 - Ataques detec (Imple)'!$D$3:$D$112,$B8,'Tabla 2 - Ataques detec (Imple)'!$I$3:$I$112) -> 2 | M8: =SUMIF('Tabla 2 - Ataques detec (Imple)'!$D$3:$D$112,$B8,'Tabla 2 - Ataques detec (Imple)'!K$3:K$112) -> 6 | N8: =SUMIF('Tabla 2 - Ataques detec (Imple)'!$D$3:$D$112,$B8,'Tabla 2 - Ataques detec (Imple)'!L$3:L$112) -> 1 | O8: =N8 & " (" & M8 & ")" -> 1 (6) | P8: =SUMIF('Tabla 2 - Ataques detec (Imple)'!$D$3:$D$112,$B8,'Tabla 2 - Ataques detec (Imple)'!$M$3:$M$112) -> 1 | Q8: =AVERAGEIF('Tabla 2 - Ataques detec (Imple)'!$D$3:$D$112,$B8,'Tabla 2 - Ataques detec (Imple)'!$O$3:$O$112) -> 1 | R8: =SUMIF('Tabla 2 - Ataques detec (Imple)'!$D$3:$D$112,$B8,'Tabla 2 - Ataques detec (Imple)'!$N$3:$N$112) -> 1 | S8: =SUMIF('Tabla 2 - Ataques detec (Imple)'!$D$3:$D$112,$B8,'Tabla 2 - Ataques detec (Imple)'!P$3:P$112) -> 17 | T8: =SUMIF('Tabla 2 - Ataques detec (Imple)'!$D$3:$D$112,$B8,'Tabla 2 - Ataques detec (Imple)'!Q$3:Q$112) -> 3 | U8: =T8 & " (" & S8 & ")" -> 3 (17) | V8: =SUMIF('Tabla 2 - Ataques detec (Imple)'!$D$3:$D$112,$B8,'Tabla 2 - Ataques detec (Imple)'!$R$3:$R$112) -> 2 | W8: =AVERAGEIF('Tabla 2 - Ataques detec (Imple)'!$D$3:$D$112,$B8,'Tabla 2 - Ataques detec (Imple)'!$T$3:$T$112) -> 1 | X8: =SUMIF('Tabla 2 - Ataques detec (Imple)'!$D$3:$D$112,$B8,'Tabla 2 - Ataques detec (Imple)'!$S$3:$S$112) -> 3 | Y8: =SUMIF('Tabla 2 - Ataques detec (Imple)'!$D$3:$D$112,$B8,'Tabla 2 - Ataques detec (Imple)'!U$3:U$112) -> 39 | Z8: =SUMIF('Tabla 2 - Ataques detec (Imple)'!$D$3:$D$112,$B8,'Tabla 2 - Ataques detec (Imple)'!V$3:V$112) -> 3 | AA8: =Z8 & " (" & Y8 & ")" -> 3 (39) | AB8: =SUMIF('Tabla 2 - Ataques detec (Imple)'!$D$3:$D$112,$B8,'Tabla 2 - Ataques detec (Imple)'!$R$3:$R$112) -> 2 | AC8: =AVERAGEIF('Tabla 2 - Ataques detec (Imple)'!$D$3:$D$112,$B8,'Tabla 2 - Ataques detec (Imple)'!$Y$3:$Y$112) -> 1 | AD8: =SUMIF('Tabla 2 - Ataques detec (Imple)'!$D$3:$D$112,$B8,'Tabla 2 - Ataques detec (Imple)'!$X$3:$X$112) -> 3 | AE8: =SUMIF('Tabla 2 - Ataques detec (Imple)'!$D$3:$D$112,$B8,'Tabla 2 - Ataques detec (Imple)'!Z$3:Z$112) -> 16 | AF8: =SUMIF('Tabla 2 - Ataques detec (Imple)'!$D$3:$D$112,$B8,'Tabla 2 - Ataques detec (Imple)'!AA$3:AA$112) -> 9 | AG8: =AF8 & " (" & AE8 & ")" -> 9 (16) | AH8: =SUMIF('Tabla 2 - Ataques detec (Imple)'!$D$3:$D$112,$B8,'Tabla 2 - Ataques detec (Imple)'!$AB$3:$AB$112) -> 3 | AI8: =AVERAGEIF('Tabla 2 - Ataques detec (Imple)'!$D$3:$D$112,$B8,'Tabla 2 - Ataques detec (Imple)'!$AD$3:$AD$112) -> 1 | AJ8: =SUMIF('Tabla 2 - Ataques detec (Imple)'!$D$3:$D$112,$B8,'Tabla 2 - Ataques detec (Imple)'!$AC$3:$AC$112) -> 7 | AK8: =SUMIF('Tabla 2 - Ataques detec (Imple)'!$D$3:$D$112,$B8,'Tabla 2 - Ataques detec (Imple)'!AE$3:AE$112) -> 55 | AL8: =SUMIF('Tabla 2 - Ataques detec (Imple)'!$D$3:$D$112,$B8,'Tabla 2 - Ataques detec (Imple)'!AF$3:AF$112) -> 12 | AM8: =AL8 & " (" & AK8 & ")" -> 12 (55) | AN8: =SUMIF('Tabla 2 - Ataques detec (Imple)'!$D$3:$D$112,$B8,'Tabla 2 - Ataques detec (Imple)'!$AG$3:$AG$112) -> 5 | AO8: =AVERAGEIF('Tabla 2 - Ataques detec (Imple)'!$D$3:$D$112,$B8,'Tabla 2 - Ataques detec (Imple)'!$AI$3:$AI$112) -> 1 | AP8: =SUMIF('Tabla 2 - Ataques detec (Imple)'!$D$3:$D$112,$B8,'Tabla 2 - Ataques detec (Imple)'!$AH$3:$AH$112) -> 9 | AQ8: =SUMIF('Tabla 2 - Ataques detec (Imple)'!$D$3:$D$112,$B8,'Tabla 2 - Ataques detec (Imple)'!AJ$3:AJ$112) -> 0 | AR8: =SUMIF('Tabla 2 - Ataques detec (Imple)'!$D$3:$D$112,$B8,'Tabla 2 - Ataques detec (Imple)'!AK$3:AK$112) -> 0 | AS8: =AR8 & " (" & AQ8 & ")" -> 0 (0) | AT8: =SUMIF('Tabla 2 - Ataques detec (Imple)'!$D$3:$D$112,$B8,'Tabla 2 - Ataques detec (Imple)'!$AL$3:$AL$112) -> 0 | AU8: =AVERAGEIF('Tabla 2 - Ataques detec (Imple)'!$D$3:$D$112,$B8,'Tabla 2 - Ataques detec (Imple)'!$AN$3:$AN$112) -> 0 | AV8: =SUMIF('Tabla 2 - Ataques detec (Imple)'!$D$3:$D$112,$B8,'Tabla 2 - Ataques detec (Imple)'!$AM$3:$AM$112) -> 0 | AW8: =SUMIF('Tabla 2 - Ataques detec (Imple)'!$D$3:$D$112,$B8,'Tabla 2 - Ataques detec (Imple)'!AO$3:AO$112) -> 28 | AX8: =SUMIF('Tabla 2 - Ataques detec (Imple)'!$D$3:$D$112,$B8,'Tabla 2 - Ataques detec (Imple)'!AP$3:AP$112) -> 1 | AY8: =AX8 & " (" & AW8 & ")" -> 1 (28) | AZ8: =SUMIF('Tabla 2 - Ataques detec (Imple)'!$D$3:$D$112,$B8,'Tabla 2 - Ataques detec (Imple)'!$AQ$3:$AQ$112) -> 1 | BA8: =AVERAGEIF('Tabla 2 - Ataques detec (Imple)'!$D$3:$D$112,$B8,'Tabla 2 - Ataques detec (Imple)'!$AS$3:$AS$112) -> 1 | BB8: =SUMIF('Tabla 2 - Ataques detec (Imple)'!$D$3:$D$112,$B8,'Tabla 2 - Ataques detec (Imple)'!$AR$3:$AR$112) -> 1 | BC8: =SUMIF('Tabla 2 - Ataques detec (Imple)'!$D$3:$D$112,$B8,'Tabla 2 - Ataques detec (Imple)'!AT$3:AT$112) -> 45 | BD8: =SUMIF('Tabla 2 - Ataques detec (Imple)'!$D$3:$D$112,$B8,'Tabla 2 - Ataques detec (Imple)'!AU$3:AU$112) -> 4 | BE8: =BD8 & " (" & BC8 & ")" -> 4 (45) | BF8: =SUMIF('Tabla 2 - Ataques detec (Imple)'!$D$3:$D$112,$B8,'Tabla 2 - Ataques detec (Imple)'!$AV$3:$AV$112) -> 3 | BG8: =AVERAGEIF('Tabla 2 - Ataques detec (Imple)'!$D$3:$D$112,$B8,'Tabla 2 - Ataques detec (Imple)'!$AX$3:$AX$112) -> 1 | BH8: =SUMIF('Tabla 2 - Ataques detec (Imple)'!$D$3:$D$112,$B8,'Tabla 2 - Ataques detec (Imple)'!$AW$3:$AW$112) -> 4 | BI8: =SUMIF('Tabla 2 - Ataques detec (Imple)'!$D$3:$D$112,$B8,'Tabla 2 - Ataques detec (Imple)'!AY$3:AY$112) -> 1 | BJ8: =SUMIF('Tabla 2 - Ataques detec (Imple)'!$D$3:$D$112,$B8,'Tabla 2 - Ataques detec (Imple)'!AZ$3:AZ$112) -> 1 | BK8: =BJ8 & " (" & BI8 & ")" -> 1 (1) | BL8: =SUMIF('Tabla 2 - Ataques detec (Imple)'!$D$3:$D$112,$B8,'Tabla 2 - Ataques detec (Imple)'!BA$3:BA$112) -> 1 | BM8: =AVERAGEIF('Tabla 2 - Ataques detec (Imple)'!$D$3:$D$112,$B8,'Tabla 2 - Ataques detec (Imple)'!$BC$3:$BC$112) -> 1 | BN8: =SUMIF('Tabla 2 - Ataques detec (Imple)'!$D$3:$D$112,$B8,'Tabla 2 - Ataques detec (Imple)'!$BB$3:$BB$112) -> 1 | BO8: =SUMIF('Tabla 2 - Ataques detec (Imple)'!$D$3:$D$112,$B8,'Tabla 2 - Ataques detec (Imple)'!BD$3:BD$112) -> 51 | BP8: =SUMIF('Tabla 2 - Ataques detec (Imple)'!$D$3:$D$112,$B8,'Tabla 2 - Ataques detec (Imple)'!BE$3:BE$112) -> 24 | BQ8: =BP8 & " (" & BO8 & ")" -> 24 (51) | BR8: =SUMIF('Tabla 2 - Ataques detec (Imple)'!$D$3:$D$112,$B8,'Tabla 2 - Ataques detec (Imple)'!BF$3:BF$112) -> 1 | BS8: =SUMIF('Tabla 2 - Ataques detec (Imple)'!$D$3:$D$112,$B8,'Tabla 2 - Ataques detec (Imple)'!BG$3:BG$112) -> 4 | BT8: =AVERAGEIF('Tabla 2 - Ataques detec (Imple)'!$D$3:$D$112,$B8,'Tabla 2 - Ataques detec (Imple)'!$BI$3:$BI$112) -> 1 | BU8: =SUMIF('Tabla 2 - Ataques detec (Imple)'!$D$3:$D$112,$B8,'Tabla 2 - Ataques detec (Imple)'!$BH$3:$BH$112) -> 23 | BV8: 1 | BW8: 1 | BX8: =BW8 & " (" & BV8 & ")" -> 1 (1) | BY8: 1 | BZ8: 1 | CA8: 1 | CB8: 2 | CC8: 2 | CD8: =CC8 & " (" & CB8 & ")" -> 2 (2) | CE8: 1 | CF8: 1 | CG8: 1 | CH8: 1
A9: =A8+1 -> 7 | B9: =IFERROR(VLOOKUP(A9,'Tabla 2 - Ataques detec (Imple)'!$B$3:$D$112,3,FALSE),"") -> T1021 | C9: =IFERROR(VLOOKUP(B9,Techniques!$B$3:$H$213,2,FALSE),"") -> Remote Services | D9: =SUMPRODUCT( ('Tabla 2 - Ataques detec (Imple)'!$D$3:$D$112=$B9)* (LEN('Tabla 2 - Ataques detec (Imple)'!$C$3:$C$112)>0) ) -> 1 | E9: =SUMIF('Tabla 2 - Ataques detec (Imple)'!$D$3:$D$112,$B9,'Tabla 2 - Ataques detec (Imple)'!$E$3:$E$112) -> 1 | F9: =D9&" ("&E9&")" -> 1 (1) | G9: =SUMIF('Tabla 2 - Ataques detec (Imple)'!$D$3:$D$112,$B9,'Tabla 2 - Ataques detec (Imple)'!F$3:F$112) -> 3 | H9: =SUMIF('Tabla 2 - Ataques detec (Imple)'!$D$3:$D$112,$B9,'Tabla 2 - Ataques detec (Imple)'!G$3:G$112) -> 1 | I9: =H9 & " (" & G9 & ")" -> 1 (3) | J9: =SUMIF('Tabla 2 - Ataques detec (Imple)'!$D$3:$D$112,$B9,'Tabla 2 - Ataques detec (Imple)'!$H$3:$H$112) -> 1 | K9: =AVERAGEIF('Tabla 2 - Ataques detec (Imple)'!$D$3:$D$112,$B9,'Tabla 2 - Ataques detec (Imple)'!$J$3:$J$112) -> 1 | L9: =SUMIF('Tabla 2 - Ataques detec (Imple)'!$D$3:$D$112,$B9,'Tabla 2 - Ataques detec (Imple)'!$I$3:$I$112) -> 1 | M9: =SUMIF('Tabla 2 - Ataques detec (Imple)'!$D$3:$D$112,$B9,'Tabla 2 - Ataques detec (Imple)'!K$3:K$112) -> 0 | N9: =SUMIF('Tabla 2 - Ataques detec (Imple)'!$D$3:$D$112,$B9,'Tabla 2 - Ataques detec (Imple)'!L$3:L$112) -> 0 | O9: =N9 & " (" & M9 & ")" -> 0 (0) | P9: =SUMIF('Tabla 2 - Ataques detec (Imple)'!$D$3:$D$112,$B9,'Tabla 2 - Ataques detec (Imple)'!$M$3:$M$112) -> 0 | Q9: =AVERAGEIF('Tabla 2 - Ataques detec (Imple)'!$D$3:$D$112,$B9,'Tabla 2 - Ataques detec (Imple)'!$O$3:$O$112) -> 0 | R9: =SUMIF('Tabla 2 - Ataques detec (Imple)'!$D$3:$D$112,$B9,'Tabla 2 - Ataques detec (Imple)'!$N$3:$N$112) -> 0 | S9: =SUMIF('Tabla 2 - Ataques detec (Imple)'!$D$3:$D$112,$B9,'Tabla 2 - Ataques detec (Imple)'!P$3:P$112) -> 3 | T9: =SUMIF('Tabla 2 - Ataques detec (Imple)'!$D$3:$D$112,$B9,'Tabla 2 - Ataques detec (Imple)'!Q$3:Q$112) -> 1 | U9: =T9 & " (" & S9 & ")" -> 1 (3) | V9: =SUMIF('Tabla 2 - Ataques detec (Imple)'!$D$3:$D$112,$B9,'Tabla 2 - Ataques detec (Imple)'!$R$3:$R$112) -> 1 | W9: =AVERAGEIF('Tabla 2 - Ataques detec (Imple)'!$D$3:$D$112,$B9,'Tabla 2 - Ataques detec (Imple)'!$T$3:$T$112) -> 1 | X9: =SUMIF('Tabla 2 - Ataques detec (Imple)'!$D$3:$D$112,$B9,'Tabla 2 - Ataques detec (Imple)'!$S$3:$S$112) -> 1 | Y9: =SUMIF('Tabla 2 - Ataques detec (Imple)'!$D$3:$D$112,$B9,'Tabla 2 - Ataques detec (Imple)'!U$3:U$112) -> 4 | Z9: =SUMIF('Tabla 2 - Ataques detec (Imple)'!$D$3:$D$112,$B9,'Tabla 2 - Ataques detec (Imple)'!V$3:V$112) -> 2 | AA9: =Z9 & " (" & Y9 & ")" -> 2 (4) | AB9: =SUMIF('Tabla 2 - Ataques detec (Imple)'!$D$3:$D$112,$B9,'Tabla 2 - Ataques detec (Imple)'!$R$3:$R$112) -> 1 | AC9: =AVERAGEIF('Tabla 2 - Ataques detec (Imple)'!$D$3:$D$112,$B9,'Tabla 2 - Ataques detec (Imple)'!$Y$3:$Y$112) -> 1 | AD9: =SUMIF('Tabla 2 - Ataques detec (Imple)'!$D$3:$D$112,$B9,'Tabla 2 - Ataques detec (Imple)'!$X$3:$X$112) -> 1 | AE9: =SUMIF('Tabla 2 - Ataques detec (Imple)'!$D$3:$D$112,$B9,'Tabla 2 - Ataques detec (Imple)'!Z$3:Z$112) -> 4 | AF9: =SUMIF('Tabla 2 - Ataques detec (Imple)'!$D$3:$D$112,$B9,'Tabla 2 - Ataques detec (Imple)'!AA$3:AA$112) -> 2 | AG9: =AF9 & " (" & AE9 & ")" -> 2 (4) | AH9: =SUMIF('Tabla 2 - Ataques detec (Imple)'!$D$3:$D$112,$B9,'Tabla 2 - Ataques detec (Imple)'!$AB$3:$AB$112) -> 2 | AI9: =AVERAGEIF('Tabla 2 - Ataques detec (Imple)'!$D$3:$D$112,$B9,'Tabla 2 - Ataques detec (Imple)'!$AD$3:$AD$112) -> 1 | AJ9: =SUMIF('Tabla 2 - Ataques detec (Imple)'!$D$3:$D$112,$B9,'Tabla 2 - Ataques detec (Imple)'!$AC$3:$AC$112) -> 1 | AK9: =SUMIF('Tabla 2 - Ataques detec (Imple)'!$D$3:$D$112,$B9,'Tabla 2 - Ataques detec (Imple)'!AE$3:AE$112) -> 8 | AL9: =SUMIF('Tabla 2 - Ataques detec (Imple)'!$D$3:$D$112,$B9,'Tabla 2 - Ataques detec (Imple)'!AF$3:AF$112) -> 4 | AM9: =AL9 & " (" & AK9 & ")" -> 4 (8) | AN9: =SUMIF('Tabla 2 - Ataques detec (Imple)'!$D$3:$D$112,$B9,'Tabla 2 - Ataques detec (Imple)'!$AG$3:$AG$112) -> 4 | AO9: =AVERAGEIF('Tabla 2 - Ataques detec (Imple)'!$D$3:$D$112,$B9,'Tabla 2 - Ataques detec (Imple)'!$AI$3:$AI$112) -> 1 | AP9: =SUMIF('Tabla 2 - Ataques detec (Imple)'!$D$3:$D$112,$B9,'Tabla 2 - Ataques detec (Imple)'!$AH$3:$AH$112) -> 1 | AQ9: =SUMIF('Tabla 2 - Ataques detec (Imple)'!$D$3:$D$112,$B9,'Tabla 2 - Ataques detec (Imple)'!AJ$3:AJ$112) -> 0 | AR9: =SUMIF('Tabla 2 - Ataques detec (Imple)'!$D$3:$D$112,$B9,'Tabla 2 - Ataques detec (Imple)'!AK$3:AK$112) -> 0 | AS9: =AR9 & " (" & AQ9 & ")" -> 0 (0) | AT9: =SUMIF('Tabla 2 - Ataques detec (Imple)'!$D$3:$D$112,$B9,'Tabla 2 - Ataques detec (Imple)'!$AL$3:$AL$112) -> 0 | AU9: =AVERAGEIF('Tabla 2 - Ataques detec (Imple)'!$D$3:$D$112,$B9,'Tabla 2 - Ataques detec (Imple)'!$AN$3:$AN$112) -> 0 | AV9: =SUMIF('Tabla 2 - Ataques detec (Imple)'!$D$3:$D$112,$B9,'Tabla 2 - Ataques detec (Imple)'!$AM$3:$AM$112) -> 0 | AW9: =SUMIF('Tabla 2 - Ataques detec (Imple)'!$D$3:$D$112,$B9,'Tabla 2 - Ataques detec (Imple)'!AO$3:AO$112) -> 1 | AX9: =SUMIF('Tabla 2 - Ataques detec (Imple)'!$D$3:$D$112,$B9,'Tabla 2 - Ataques detec (Imple)'!AP$3:AP$112) -> 1 | AY9: =AX9 & " (" & AW9 & ")" -> 1 (1) | AZ9: =SUMIF('Tabla 2 - Ataques detec (Imple)'!$D$3:$D$112,$B9,'Tabla 2 - Ataques detec (Imple)'!$AQ$3:$AQ$112) -> 1 | BA9: =AVERAGEIF('Tabla 2 - Ataques detec (Imple)'!$D$3:$D$112,$B9,'Tabla 2 - Ataques detec (Imple)'!$AS$3:$AS$112) -> 1 | BB9: =SUMIF('Tabla 2 - Ataques detec (Imple)'!$D$3:$D$112,$B9,'Tabla 2 - Ataques detec (Imple)'!$AR$3:$AR$112) -> 1 | BC9: =SUMIF('Tabla 2 - Ataques detec (Imple)'!$D$3:$D$112,$B9,'Tabla 2 - Ataques detec (Imple)'!AT$3:AT$112) -> 4 | BD9: =SUMIF('Tabla 2 - Ataques detec (Imple)'!$D$3:$D$112,$B9,'Tabla 2 - Ataques detec (Imple)'!AU$3:AU$112) -> 2 | BE9: =BD9 & " (" & BC9 & ")" -> 2 (4) | BF9: =SUMIF('Tabla 2 - Ataques detec (Imple)'!$D$3:$D$112,$B9,'Tabla 2 - Ataques detec (Imple)'!$AV$3:$AV$112) -> 2 | BG9: =AVERAGEIF('Tabla 2 - Ataques detec (Imple)'!$D$3:$D$112,$B9,'Tabla 2 - Ataques detec (Imple)'!$AX$3:$AX$112) -> 1 | BH9: =SUMIF('Tabla 2 - Ataques detec (Imple)'!$D$3:$D$112,$B9,'Tabla 2 - Ataques detec (Imple)'!$AW$3:$AW$112) -> 1 | BI9: =SUMIF('Tabla 2 - Ataques detec (Imple)'!$D$3:$D$112,$B9,'Tabla 2 - Ataques detec (Imple)'!AY$3:AY$112) -> 1 | BJ9: =SUMIF('Tabla 2 - Ataques detec (Imple)'!$D$3:$D$112,$B9,'Tabla 2 - Ataques detec (Imple)'!AZ$3:AZ$112) -> 1 | BK9: =BJ9 & " (" & BI9 & ")" -> 1 (1) | BL9: =SUMIF('Tabla 2 - Ataques detec (Imple)'!$D$3:$D$112,$B9,'Tabla 2 - Ataques detec (Imple)'!BA$3:BA$112) -> 1 | BM9: =AVERAGEIF('Tabla 2 - Ataques detec (Imple)'!$D$3:$D$112,$B9,'Tabla 2 - Ataques detec (Imple)'!$BC$3:$BC$112) -> 1 | BN9: =SUMIF('Tabla 2 - Ataques detec (Imple)'!$D$3:$D$112,$B9,'Tabla 2 - Ataques detec (Imple)'!$BB$3:$BB$112) -> 1 | BO9: =SUMIF('Tabla 2 - Ataques detec (Imple)'!$D$3:$D$112,$B9,'Tabla 2 - Ataques detec (Imple)'!BD$3:BD$112) -> 2 | BP9: =SUMIF('Tabla 2 - Ataques detec (Imple)'!$D$3:$D$112,$B9,'Tabla 2 - Ataques detec (Imple)'!BE$3:BE$112) -> 2 | BQ9: =BP9 & " (" & BO9 & ")" -> 2 (2) | BR9: =SUMIF('Tabla 2 - Ataques detec (Imple)'!$D$3:$D$112,$B9,'Tabla 2 - Ataques detec (Imple)'!BF$3:BF$112) -> 1 | BS9: =SUMIF('Tabla 2 - Ataques detec (Imple)'!$D$3:$D$112,$B9,'Tabla 2 - Ataques detec (Imple)'!BG$3:BG$112) -> 1 | BT9: =AVERAGEIF('Tabla 2 - Ataques detec (Imple)'!$D$3:$D$112,$B9,'Tabla 2 - Ataques detec (Imple)'!$BI$3:$BI$112) -> 1 | BU9: =SUMIF('Tabla 2 - Ataques detec (Imple)'!$D$3:$D$112,$B9,'Tabla 2 - Ataques detec (Imple)'!$BH$3:$BH$112) -> 1 | BV9: 1 | BW9: 1 | BX9: =BW9 & " (" & BV9 & ")" -> 1 (1) | BY9: 1 | BZ9: 1 | CA9: 1 | CB9: 2 | CC9: 2 | CD9: =CC9 & " (" & CB9 & ")" -> 2 (2) | CE9: 1 | CF9: 1 | CG9: 1 | CH9: 1
A10: =A9+1 -> 8 | B10: =IFERROR(VLOOKUP(A10,'Tabla 2 - Ataques detec (Imple)'!$B$3:$D$112,3,FALSE),"") -> T1029 | C10: =IFERROR(VLOOKUP(B10,Techniques!$B$3:$H$213,2,FALSE),"") -> Scheduled Transfer | D10: =SUMPRODUCT( ('Tabla 2 - Ataques detec (Imple)'!$D$3:$D$112=$B10)* (LEN('Tabla 2 - Ataques detec (Imple)'!$C$3:$C$112)>0) ) -> 1 | E10: =SUMIF('Tabla 2 - Ataques detec (Imple)'!$D$3:$D$112,$B10,'Tabla 2 - Ataques detec (Imple)'!$E$3:$E$112) -> 9 | F10: =D10&" ("&E10&")" -> 1 (9) | G10: =SUMIF('Tabla 2 - Ataques detec (Imple)'!$D$3:$D$112,$B10,'Tabla 2 - Ataques detec (Imple)'!F$3:F$112) -> 5 | H10: =SUMIF('Tabla 2 - Ataques detec (Imple)'!$D$3:$D$112,$B10,'Tabla 2 - Ataques detec (Imple)'!G$3:G$112) -> 2 | I10: =H10 & " (" & G10 & ")" -> 2 (5) | J10: =SUMIF('Tabla 2 - Ataques detec (Imple)'!$D$3:$D$112,$B10,'Tabla 2 - Ataques detec (Imple)'!$H$3:$H$112) -> 2 | K10: =AVERAGEIF('Tabla 2 - Ataques detec (Imple)'!$D$3:$D$112,$B10,'Tabla 2 - Ataques detec (Imple)'!$J$3:$J$112) -> 1 | L10: =SUMIF('Tabla 2 - Ataques detec (Imple)'!$D$3:$D$112,$B10,'Tabla 2 - Ataques detec (Imple)'!$I$3:$I$112) -> 1 | M10: =SUMIF('Tabla 2 - Ataques detec (Imple)'!$D$3:$D$112,$B10,'Tabla 2 - Ataques detec (Imple)'!K$3:K$112) -> 3 | N10: =SUMIF('Tabla 2 - Ataques detec (Imple)'!$D$3:$D$112,$B10,'Tabla 2 - Ataques detec (Imple)'!L$3:L$112) -> 3 | O10: =N10 & " (" & M10 & ")" -> 3 (3) | P10: =SUMIF('Tabla 2 - Ataques detec (Imple)'!$D$3:$D$112,$B10,'Tabla 2 - Ataques detec (Imple)'!$M$3:$M$112) -> 3 | Q10: =AVERAGEIF('Tabla 2 - Ataques detec (Imple)'!$D$3:$D$112,$B10,'Tabla 2 - Ataques detec (Imple)'!$O$3:$O$112) -> 1 | R10: =SUMIF('Tabla 2 - Ataques detec (Imple)'!$D$3:$D$112,$B10,'Tabla 2 - Ataques detec (Imple)'!$N$3:$N$112) -> 1 | S10: =SUMIF('Tabla 2 - Ataques detec (Imple)'!$D$3:$D$112,$B10,'Tabla 2 - Ataques detec (Imple)'!P$3:P$112) -> 8 | T10: =SUMIF('Tabla 2 - Ataques detec (Imple)'!$D$3:$D$112,$B10,'Tabla 2 - Ataques detec (Imple)'!Q$3:Q$112) -> 5 | U10: =T10 & " (" & S10 & ")" -> 5 (8) | V10: =SUMIF('Tabla 2 - Ataques detec (Imple)'!$D$3:$D$112,$B10,'Tabla 2 - Ataques detec (Imple)'!$R$3:$R$112) -> 5 | W10: =AVERAGEIF('Tabla 2 - Ataques detec (Imple)'!$D$3:$D$112,$B10,'Tabla 2 - Ataques detec (Imple)'!$T$3:$T$112) -> 1 | X10: =SUMIF('Tabla 2 - Ataques detec (Imple)'!$D$3:$D$112,$B10,'Tabla 2 - Ataques detec (Imple)'!$S$3:$S$112) -> 2 | Y10: =SUMIF('Tabla 2 - Ataques detec (Imple)'!$D$3:$D$112,$B10,'Tabla 2 - Ataques detec (Imple)'!U$3:U$112) -> 63 | Z10: =SUMIF('Tabla 2 - Ataques detec (Imple)'!$D$3:$D$112,$B10,'Tabla 2 - Ataques detec (Imple)'!V$3:V$112) -> 8 | AA10: =Z10 & " (" & Y10 & ")" -> 8 (63) | AB10: =SUMIF('Tabla 2 - Ataques detec (Imple)'!$D$3:$D$112,$B10,'Tabla 2 - Ataques detec (Imple)'!$R$3:$R$112) -> 5 | AC10: =AVERAGEIF('Tabla 2 - Ataques detec (Imple)'!$D$3:$D$112,$B10,'Tabla 2 - Ataques detec (Imple)'!$Y$3:$Y$112) -> 1 | AD10: =SUMIF('Tabla 2 - Ataques detec (Imple)'!$D$3:$D$112,$B10,'Tabla 2 - Ataques detec (Imple)'!$X$3:$X$112) -> 7 | AE10: =SUMIF('Tabla 2 - Ataques detec (Imple)'!$D$3:$D$112,$B10,'Tabla 2 - Ataques detec (Imple)'!Z$3:Z$112) -> 7 | AF10: =SUMIF('Tabla 2 - Ataques detec (Imple)'!$D$3:$D$112,$B10,'Tabla 2 - Ataques detec (Imple)'!AA$3:AA$112) -> 5 | AG10: =AF10 & " (" & AE10 & ")" -> 5 (7) | AH10: =SUMIF('Tabla 2 - Ataques detec (Imple)'!$D$3:$D$112,$B10,'Tabla 2 - Ataques detec (Imple)'!$AB$3:$AB$112) -> 5 | AI10: =AVERAGEIF('Tabla 2 - Ataques detec (Imple)'!$D$3:$D$112,$B10,'Tabla 2 - Ataques detec (Imple)'!$AD$3:$AD$112) -> 1 | AJ10: =SUMIF('Tabla 2 - Ataques detec (Imple)'!$D$3:$D$112,$B10,'Tabla 2 - Ataques detec (Imple)'!$AC$3:$AC$112) -> 1 | AK10: =SUMIF('Tabla 2 - Ataques detec (Imple)'!$D$3:$D$112,$B10,'Tabla 2 - Ataques detec (Imple)'!AE$3:AE$112) -> 70 | AL10: =SUMIF('Tabla 2 - Ataques detec (Imple)'!$D$3:$D$112,$B10,'Tabla 2 - Ataques detec (Imple)'!AF$3:AF$112) -> 13 | AM10: =AL10 & " (" & AK10 & ")" -> 13 (70) | AN10: =SUMIF('Tabla 2 - Ataques detec (Imple)'!$D$3:$D$112,$B10,'Tabla 2 - Ataques detec (Imple)'!$AG$3:$AG$112) -> 9 | AO10: =AVERAGEIF('Tabla 2 - Ataques detec (Imple)'!$D$3:$D$112,$B10,'Tabla 2 - Ataques detec (Imple)'!$AI$3:$AI$112) -> 1 | AP10: =SUMIF('Tabla 2 - Ataques detec (Imple)'!$D$3:$D$112,$B10,'Tabla 2 - Ataques detec (Imple)'!$AH$3:$AH$112) -> 7 | AQ10: =SUMIF('Tabla 2 - Ataques detec (Imple)'!$D$3:$D$112,$B10,'Tabla 2 - Ataques detec (Imple)'!AJ$3:AJ$112) -> 0 | AR10: =SUMIF('Tabla 2 - Ataques detec (Imple)'!$D$3:$D$112,$B10,'Tabla 2 - Ataques detec (Imple)'!AK$3:AK$112) -> 0 | AS10: =AR10 & " (" & AQ10 & ")" -> 0 (0) | AT10: =SUMIF('Tabla 2 - Ataques detec (Imple)'!$D$3:$D$112,$B10,'Tabla 2 - Ataques detec (Imple)'!$AL$3:$AL$112) -> 0 | AU10: =AVERAGEIF('Tabla 2 - Ataques detec (Imple)'!$D$3:$D$112,$B10,'Tabla 2 - Ataques detec (Imple)'!$AN$3:$AN$112) -> 0 | AV10: =SUMIF('Tabla 2 - Ataques detec (Imple)'!$D$3:$D$112,$B10,'Tabla 2 - Ataques detec (Imple)'!$AM$3:$AM$112) -> 0 | AW10: =SUMIF('Tabla 2 - Ataques detec (Imple)'!$D$3:$D$112,$B10,'Tabla 2 - Ataques detec (Imple)'!AO$3:AO$112) -> 20 | AX10: =SUMIF('Tabla 2 - Ataques detec (Imple)'!$D$3:$D$112,$B10,'Tabla 2 - Ataques detec (Imple)'!AP$3:AP$112) -> 5 | AY10: =AX10 & " (" & AW10 & ")" -> 5 (20) | AZ10: =SUMIF('Tabla 2 - Ataques detec (Imple)'!$D$3:$D$112,$B10,'Tabla 2 - Ataques detec (Imple)'!$AQ$3:$AQ$112) -> 1 | BA10: =AVERAGEIF('Tabla 2 - Ataques detec (Imple)'!$D$3:$D$112,$B10,'Tabla 2 - Ataques detec (Imple)'!$AS$3:$AS$112) -> 1 | BB10: =SUMIF('Tabla 2 - Ataques detec (Imple)'!$D$3:$D$112,$B10,'Tabla 2 - Ataques detec (Imple)'!$AR$3:$AR$112) -> 5 | BC10: =SUMIF('Tabla 2 - Ataques detec (Imple)'!$D$3:$D$112,$B10,'Tabla 2 - Ataques detec (Imple)'!AT$3:AT$112) -> 28 | BD10: =SUMIF('Tabla 2 - Ataques detec (Imple)'!$D$3:$D$112,$B10,'Tabla 2 - Ataques detec (Imple)'!AU$3:AU$112) -> 10 | BE10: =BD10 & " (" & BC10 & ")" -> 10 (28) | BF10: =SUMIF('Tabla 2 - Ataques detec (Imple)'!$D$3:$D$112,$B10,'Tabla 2 - Ataques detec (Imple)'!$AV$3:$AV$112) -> 6 | BG10: =AVERAGEIF('Tabla 2 - Ataques detec (Imple)'!$D$3:$D$112,$B10,'Tabla 2 - Ataques detec (Imple)'!$AX$3:$AX$112) -> 1 | BH10: =SUMIF('Tabla 2 - Ataques detec (Imple)'!$D$3:$D$112,$B10,'Tabla 2 - Ataques detec (Imple)'!$AW$3:$AW$112) -> 7 | BI10: =SUMIF('Tabla 2 - Ataques detec (Imple)'!$D$3:$D$112,$B10,'Tabla 2 - Ataques detec (Imple)'!AY$3:AY$112) -> 4 | BJ10: =SUMIF('Tabla 2 - Ataques detec (Imple)'!$D$3:$D$112,$B10,'Tabla 2 - Ataques detec (Imple)'!AZ$3:AZ$112) -> 3 | BK10: =BJ10 & " (" & BI10 & ")" -> 3 (4) | BL10: =SUMIF('Tabla 2 - Ataques detec (Imple)'!$D$3:$D$112,$B10,'Tabla 2 - Ataques detec (Imple)'!BA$3:BA$112) -> 3 | BM10: =AVERAGEIF('Tabla 2 - Ataques detec (Imple)'!$D$3:$D$112,$B10,'Tabla 2 - Ataques detec (Imple)'!$BC$3:$BC$112) -> 1 | BN10: =SUMIF('Tabla 2 - Ataques detec (Imple)'!$D$3:$D$112,$B10,'Tabla 2 - Ataques detec (Imple)'!$BB$3:$BB$112) -> 2 | BO10: =SUMIF('Tabla 2 - Ataques detec (Imple)'!$D$3:$D$112,$B10,'Tabla 2 - Ataques detec (Imple)'!BD$3:BD$112) -> 11 | BP10: =SUMIF('Tabla 2 - Ataques detec (Imple)'!$D$3:$D$112,$B10,'Tabla 2 - Ataques detec (Imple)'!BE$3:BE$112) -> 10 | BQ10: =BP10 & " (" & BO10 & ")" -> 10 (11) | BR10: =SUMIF('Tabla 2 - Ataques detec (Imple)'!$D$3:$D$112,$B10,'Tabla 2 - Ataques detec (Imple)'!BF$3:BF$112) -> 3 | BS10: =SUMIF('Tabla 2 - Ataques detec (Imple)'!$D$3:$D$112,$B10,'Tabla 2 - Ataques detec (Imple)'!BG$3:BG$112) -> 3 | BT10: =AVERAGEIF('Tabla 2 - Ataques detec (Imple)'!$D$3:$D$112,$B10,'Tabla 2 - Ataques detec (Imple)'!$BI$3:$BI$112) -> 1 | BU10: =SUMIF('Tabla 2 - Ataques detec (Imple)'!$D$3:$D$112,$B10,'Tabla 2 - Ataques detec (Imple)'!$BH$3:$BH$112) -> 7 | BV10: 5 | BW10: 3 | BX10: =BW10 & " (" & BV10 & ")" -> 3 (5) | BY10: 3 | BZ10: 1 | CA10: 2 | CB10: 10 | CC10: 5 | CD10: =CC10 & " (" & CB10 & ")" -> 5 (10) | CE10: 3 | CF10: 2 | CG10: 1 | CH10: 2
A11: =A10+1 -> 9 | B11: =IFERROR(VLOOKUP(A11,'Tabla 2 - Ataques detec (Imple)'!$B$3:$D$112,3,FALSE),"") -> T1030 | C11: =IFERROR(VLOOKUP(B11,Techniques!$B$3:$H$213,2,FALSE),"") -> Data Transfer Size Limits | D11: =SUMPRODUCT( ('Tabla 2 - Ataques detec (Imple)'!$D$3:$D$112=$B11)* (LEN('Tabla 2 - Ataques detec (Imple)'!$C$3:$C$112)>0) ) -> 1 | E11: =SUMIF('Tabla 2 - Ataques detec (Imple)'!$D$3:$D$112,$B11,'Tabla 2 - Ataques detec (Imple)'!$E$3:$E$112) -> 68 | F11: =D11&" ("&E11&")" -> 1 (68) | G11: =SUMIF('Tabla 2 - Ataques detec (Imple)'!$D$3:$D$112,$B11,'Tabla 2 - Ataques detec (Imple)'!F$3:F$112) -> 63 | H11: =SUMIF('Tabla 2 - Ataques detec (Imple)'!$D$3:$D$112,$B11,'Tabla 2 - Ataques detec (Imple)'!G$3:G$112) -> 32 | I11: =H11 & " (" & G11 & ")" -> 32 (63) | J11: =SUMIF('Tabla 2 - Ataques detec (Imple)'!$D$3:$D$112,$B11,'Tabla 2 - Ataques detec (Imple)'!$H$3:$H$112) -> 1 | K11: =AVERAGEIF('Tabla 2 - Ataques detec (Imple)'!$D$3:$D$112,$B11,'Tabla 2 - Ataques detec (Imple)'!$J$3:$J$112) -> 1 | L11: =SUMIF('Tabla 2 - Ataques detec (Imple)'!$D$3:$D$112,$B11,'Tabla 2 - Ataques detec (Imple)'!$I$3:$I$112) -> 32 | M11: =SUMIF('Tabla 2 - Ataques detec (Imple)'!$D$3:$D$112,$B11,'Tabla 2 - Ataques detec (Imple)'!K$3:K$112) -> 1 | N11: =SUMIF('Tabla 2 - Ataques detec (Imple)'!$D$3:$D$112,$B11,'Tabla 2 - Ataques detec (Imple)'!L$3:L$112) -> 1 | O11: =N11 & " (" & M11 & ")" -> 1 (1) | P11: =SUMIF('Tabla 2 - Ataques detec (Imple)'!$D$3:$D$112,$B11,'Tabla 2 - Ataques detec (Imple)'!$M$3:$M$112) -> 1 | Q11: =AVERAGEIF('Tabla 2 - Ataques detec (Imple)'!$D$3:$D$112,$B11,'Tabla 2 - Ataques detec (Imple)'!$O$3:$O$112) -> 1 | R11: =SUMIF('Tabla 2 - Ataques detec (Imple)'!$D$3:$D$112,$B11,'Tabla 2 - Ataques detec (Imple)'!$N$3:$N$112) -> 1 | S11: =SUMIF('Tabla 2 - Ataques detec (Imple)'!$D$3:$D$112,$B11,'Tabla 2 - Ataques detec (Imple)'!P$3:P$112) -> 64 | T11: =SUMIF('Tabla 2 - Ataques detec (Imple)'!$D$3:$D$112,$B11,'Tabla 2 - Ataques detec (Imple)'!Q$3:Q$112) -> 33 | U11: =T11 & " (" & S11 & ")" -> 33 (64) | V11: =SUMIF('Tabla 2 - Ataques detec (Imple)'!$D$3:$D$112,$B11,'Tabla 2 - Ataques detec (Imple)'!$R$3:$R$112) -> 2 | W11: =AVERAGEIF('Tabla 2 - Ataques detec (Imple)'!$D$3:$D$112,$B11,'Tabla 2 - Ataques detec (Imple)'!$T$3:$T$112) -> 1 | X11: =SUMIF('Tabla 2 - Ataques detec (Imple)'!$D$3:$D$112,$B11,'Tabla 2 - Ataques detec (Imple)'!$S$3:$S$112) -> 32 | Y11: =SUMIF('Tabla 2 - Ataques detec (Imple)'!$D$3:$D$112,$B11,'Tabla 2 - Ataques detec (Imple)'!U$3:U$112) -> 63 | Z11: =SUMIF('Tabla 2 - Ataques detec (Imple)'!$D$3:$D$112,$B11,'Tabla 2 - Ataques detec (Imple)'!V$3:V$112) -> 32 | AA11: =Z11 & " (" & Y11 & ")" -> 32 (63) | AB11: =SUMIF('Tabla 2 - Ataques detec (Imple)'!$D$3:$D$112,$B11,'Tabla 2 - Ataques detec (Imple)'!$R$3:$R$112) -> 2 | AC11: =AVERAGEIF('Tabla 2 - Ataques detec (Imple)'!$D$3:$D$112,$B11,'Tabla 2 - Ataques detec (Imple)'!$Y$3:$Y$112) -> 1 | AD11: =SUMIF('Tabla 2 - Ataques detec (Imple)'!$D$3:$D$112,$B11,'Tabla 2 - Ataques detec (Imple)'!$X$3:$X$112) -> 32 | AE11: =SUMIF('Tabla 2 - Ataques detec (Imple)'!$D$3:$D$112,$B11,'Tabla 2 - Ataques detec (Imple)'!Z$3:Z$112) -> 99 | AF11: =SUMIF('Tabla 2 - Ataques detec (Imple)'!$D$3:$D$112,$B11,'Tabla 2 - Ataques detec (Imple)'!AA$3:AA$112) -> 97 | AG11: =AF11 & " (" & AE11 & ")" -> 97 (99) | AH11: =SUMIF('Tabla 2 - Ataques detec (Imple)'!$D$3:$D$112,$B11,'Tabla 2 - Ataques detec (Imple)'!$AB$3:$AB$112) -> 7 | AI11: =AVERAGEIF('Tabla 2 - Ataques detec (Imple)'!$D$3:$D$112,$B11,'Tabla 2 - Ataques detec (Imple)'!$AD$3:$AD$112) -> 1 | AJ11: =SUMIF('Tabla 2 - Ataques detec (Imple)'!$D$3:$D$112,$B11,'Tabla 2 - Ataques detec (Imple)'!$AC$3:$AC$112) -> 34 | AK11: =SUMIF('Tabla 2 - Ataques detec (Imple)'!$D$3:$D$112,$B11,'Tabla 2 - Ataques detec (Imple)'!AE$3:AE$112) -> 162 | AL11: =SUMIF('Tabla 2 - Ataques detec (Imple)'!$D$3:$D$112,$B11,'Tabla 2 - Ataques detec (Imple)'!AF$3:AF$112) -> 129 | AM11: =AL11 & " (" & AK11 & ")" -> 129 (162) | AN11: =SUMIF('Tabla 2 - Ataques detec (Imple)'!$D$3:$D$112,$B11,'Tabla 2 - Ataques detec (Imple)'!$AG$3:$AG$112) -> 8 | AO11: =AVERAGEIF('Tabla 2 - Ataques detec (Imple)'!$D$3:$D$112,$B11,'Tabla 2 - Ataques detec (Imple)'!$AI$3:$AI$112) -> 1 | AP11: =SUMIF('Tabla 2 - Ataques detec (Imple)'!$D$3:$D$112,$B11,'Tabla 2 - Ataques detec (Imple)'!$AH$3:$AH$112) -> 34 | AQ11: =SUMIF('Tabla 2 - Ataques detec (Imple)'!$D$3:$D$112,$B11,'Tabla 2 - Ataques detec (Imple)'!AJ$3:AJ$112) -> 0 | AR11: =SUMIF('Tabla 2 - Ataques detec (Imple)'!$D$3:$D$112,$B11,'Tabla 2 - Ataques detec (Imple)'!AK$3:AK$112) -> 0 | AS11: =AR11 & " (" & AQ11 & ")" -> 0 (0) | AT11: =SUMIF('Tabla 2 - Ataques detec (Imple)'!$D$3:$D$112,$B11,'Tabla 2 - Ataques detec (Imple)'!$AL$3:$AL$112) -> 0 | AU11: =AVERAGEIF('Tabla 2 - Ataques detec (Imple)'!$D$3:$D$112,$B11,'Tabla 2 - Ataques detec (Imple)'!$AN$3:$AN$112) -> 0 | AV11: =SUMIF('Tabla 2 - Ataques detec (Imple)'!$D$3:$D$112,$B11,'Tabla 2 - Ataques detec (Imple)'!$AM$3:$AM$112) -> 0 | AW11: =SUMIF('Tabla 2 - Ataques detec (Imple)'!$D$3:$D$112,$B11,'Tabla 2 - Ataques detec (Imple)'!AO$3:AO$112) -> 0 | AX11: =SUMIF('Tabla 2 - Ataques detec (Imple)'!$D$3:$D$112,$B11,'Tabla 2 - Ataques detec (Imple)'!AP$3:AP$112) -> 0 | AY11: =AX11 & " (" & AW11 & ")" -> 0 (0) | AZ11: =SUMIF('Tabla 2 - Ataques detec (Imple)'!$D$3:$D$112,$B11,'Tabla 2 - Ataques detec (Imple)'!$AQ$3:$AQ$112) -> 0 | BA11: =AVERAGEIF('Tabla 2 - Ataques detec (Imple)'!$D$3:$D$112,$B11,'Tabla 2 - Ataques detec (Imple)'!$AS$3:$AS$112) -> 0 | BB11: =SUMIF('Tabla 2 - Ataques detec (Imple)'!$D$3:$D$112,$B11,'Tabla 2 - Ataques detec (Imple)'!$AR$3:$AR$112) -> 0 | BC11: =SUMIF('Tabla 2 - Ataques detec (Imple)'!$D$3:$D$112,$B11,'Tabla 2 - Ataques detec (Imple)'!AT$3:AT$112) -> 64 | BD11: =SUMIF('Tabla 2 - Ataques detec (Imple)'!$D$3:$D$112,$B11,'Tabla 2 - Ataques detec (Imple)'!AU$3:AU$112) -> 33 | BE11: =BD11 & " (" & BC11 & ")" -> 33 (64) | BF11: =SUMIF('Tabla 2 - Ataques detec (Imple)'!$D$3:$D$112,$B11,'Tabla 2 - Ataques detec (Imple)'!$AV$3:$AV$112) -> 2 | BG11: =AVERAGEIF('Tabla 2 - Ataques detec (Imple)'!$D$3:$D$112,$B11,'Tabla 2 - Ataques detec (Imple)'!$AX$3:$AX$112) -> 1 | BH11: =SUMIF('Tabla 2 - Ataques detec (Imple)'!$D$3:$D$112,$B11,'Tabla 2 - Ataques detec (Imple)'!$AW$3:$AW$112) -> 32 | BI11: =SUMIF('Tabla 2 - Ataques detec (Imple)'!$D$3:$D$112,$B11,'Tabla 2 - Ataques detec (Imple)'!AY$3:AY$112) -> 9 | BJ11: =SUMIF('Tabla 2 - Ataques detec (Imple)'!$D$3:$D$112,$B11,'Tabla 2 - Ataques detec (Imple)'!AZ$3:AZ$112) -> 5 | BK11: =BJ11 & " (" & BI11 & ")" -> 5 (9) | BL11: =SUMIF('Tabla 2 - Ataques detec (Imple)'!$D$3:$D$112,$B11,'Tabla 2 - Ataques detec (Imple)'!BA$3:BA$112) -> 2 | BM11: =AVERAGEIF('Tabla 2 - Ataques detec (Imple)'!$D$3:$D$112,$B11,'Tabla 2 - Ataques detec (Imple)'!$BC$3:$BC$112) -> 1 | BN11: =SUMIF('Tabla 2 - Ataques detec (Imple)'!$D$3:$D$112,$B11,'Tabla 2 - Ataques detec (Imple)'!$BB$3:$BB$112) -> 5 | BO11: =SUMIF('Tabla 2 - Ataques detec (Imple)'!$D$3:$D$112,$B11,'Tabla 2 - Ataques detec (Imple)'!BD$3:BD$112) -> 62 | BP11: =SUMIF('Tabla 2 - Ataques detec (Imple)'!$D$3:$D$112,$B11,'Tabla 2 - Ataques detec (Imple)'!BE$3:BE$112) -> 33 | BQ11: =BP11 & " (" & BO11 & ")" -> 33 (62) | BR11: =SUMIF('Tabla 2 - Ataques detec (Imple)'!$D$3:$D$112,$B11,'Tabla 2 - Ataques detec (Imple)'!BF$3:BF$112) -> 2 | BS11: =SUMIF('Tabla 2 - Ataques detec (Imple)'!$D$3:$D$112,$B11,'Tabla 2 - Ataques detec (Imple)'!BG$3:BG$112) -> 3 | BT11: =AVERAGEIF('Tabla 2 - Ataques detec (Imple)'!$D$3:$D$112,$B11,'Tabla 2 - Ataques detec (Imple)'!$BI$3:$BI$112) -> 1 | BU11: =SUMIF('Tabla 2 - Ataques detec (Imple)'!$D$3:$D$112,$B11,'Tabla 2 - Ataques detec (Imple)'!$BH$3:$BH$112) -> 33 | BV11: 0 | BW11: 0 | BX11: =BW11 & " (" & BV11 & ")" -> 0 (0) | BY11: 0 | BZ11: 0 | CA11: 0 | CB11: 0 | CC11: 0 | CD11: =CC11 & " (" & CB11 & ")" -> 0 (0) | CE11: 0 | CF11: 0 | CG11: 0 | CH11: 0
A12: =A11+1 -> 10 | B12: =IFERROR(VLOOKUP(A12,'Tabla 2 - Ataques detec (Imple)'!$B$3:$D$112,3,FALSE),"") -> T1033 | C12: =IFERROR(VLOOKUP(B12,Techniques!$B$3:$H$213,2,FALSE),"") -> System Owner/User Discovery | D12: =SUMPRODUCT( ('Tabla 2 - Ataques detec (Imple)'!$D$3:$D$112=$B12)* (LEN('Tabla 2 - Ataques detec (Imple)'!$C$3:$C$112)>0) ) -> 1 | E12: =SUMIF('Tabla 2 - Ataques detec (Imple)'!$D$3:$D$112,$B12,'Tabla 2 - Ataques detec (Imple)'!$E$3:$E$112) -> 13 | F12: =D12&" ("&E12&")" -> 1 (13) | G12: =SUMIF('Tabla 2 - Ataques detec (Imple)'!$D$3:$D$112,$B12,'Tabla 2 - Ataques detec (Imple)'!F$3:F$112) -> 0 | H12: =SUMIF('Tabla 2 - Ataques detec (Imple)'!$D$3:$D$112,$B12,'Tabla 2 - Ataques detec (Imple)'!G$3:G$112) -> 0 | I12: =H12 & " (" & G12 & ")" -> 0 (0) | J12: =SUMIF('Tabla 2 - Ataques detec (Imple)'!$D$3:$D$112,$B12,'Tabla 2 - Ataques detec (Imple)'!$H$3:$H$112) -> 0 | K12: =AVERAGEIF('Tabla 2 - Ataques detec (Imple)'!$D$3:$D$112,$B12,'Tabla 2 - Ataques detec (Imple)'!$J$3:$J$112) -> 0 | L12: =SUMIF('Tabla 2 - Ataques detec (Imple)'!$D$3:$D$112,$B12,'Tabla 2 - Ataques detec (Imple)'!$I$3:$I$112) -> 0 | M12: =SUMIF('Tabla 2 - Ataques detec (Imple)'!$D$3:$D$112,$B12,'Tabla 2 - Ataques detec (Imple)'!K$3:K$112) -> 0 | N12: =SUMIF('Tabla 2 - Ataques detec (Imple)'!$D$3:$D$112,$B12,'Tabla 2 - Ataques detec (Imple)'!L$3:L$112) -> 0 | O12: =N12 & " (" & M12 & ")" -> 0 (0) | P12: =SUMIF('Tabla 2 - Ataques detec (Imple)'!$D$3:$D$112,$B12,'Tabla 2 - Ataques detec (Imple)'!$M$3:$M$112) -> 0 | Q12: =AVERAGEIF('Tabla 2 - Ataques detec (Imple)'!$D$3:$D$112,$B12,'Tabla 2 - Ataques detec (Imple)'!$O$3:$O$112) -> 0 | R12: =SUMIF('Tabla 2 - Ataques detec (Imple)'!$D$3:$D$112,$B12,'Tabla 2 - Ataques detec (Imple)'!$N$3:$N$112) -> 0 | S12: =SUMIF('Tabla 2 - Ataques detec (Imple)'!$D$3:$D$112,$B12,'Tabla 2 - Ataques detec (Imple)'!P$3:P$112) -> 0 | T12: =SUMIF('Tabla 2 - Ataques detec (Imple)'!$D$3:$D$112,$B12,'Tabla 2 - Ataques detec (Imple)'!Q$3:Q$112) -> 0 | U12: =T12 & " (" & S12 & ")" -> 0 (0) | V12: =SUMIF('Tabla 2 - Ataques detec (Imple)'!$D$3:$D$112,$B12,'Tabla 2 - Ataques detec (Imple)'!$R$3:$R$112) -> 0 | W12: =AVERAGEIF('Tabla 2 - Ataques detec (Imple)'!$D$3:$D$112,$B12,'Tabla 2 - Ataques detec (Imple)'!$T$3:$T$112) -> 0 | X12: =SUMIF('Tabla 2 - Ataques detec (Imple)'!$D$3:$D$112,$B12,'Tabla 2 - Ataques detec (Imple)'!$S$3:$S$112) -> 0 | Y12: =SUMIF('Tabla 2 - Ataques detec (Imple)'!$D$3:$D$112,$B12,'Tabla 2 - Ataques detec (Imple)'!U$3:U$112) -> 5 | Z12: =SUMIF('Tabla 2 - Ataques detec (Imple)'!$D$3:$D$112,$B12,'Tabla 2 - Ataques detec (Imple)'!V$3:V$112) -> 2 | AA12: =Z12 & " (" & Y12 & ")" -> 2 (5) | AB12: =SUMIF('Tabla 2 - Ataques detec (Imple)'!$D$3:$D$112,$B12,'Tabla 2 - Ataques detec (Imple)'!$R$3:$R$112) -> 0 | AC12: =AVERAGEIF('Tabla 2 - Ataques detec (Imple)'!$D$3:$D$112,$B12,'Tabla 2 - Ataques detec (Imple)'!$Y$3:$Y$112) -> 1 | AD12: =SUMIF('Tabla 2 - Ataques detec (Imple)'!$D$3:$D$112,$B12,'Tabla 2 - Ataques detec (Imple)'!$X$3:$X$112) -> 1 | AE12: =SUMIF('Tabla 2 - Ataques detec (Imple)'!$D$3:$D$112,$B12,'Tabla 2 - Ataques detec (Imple)'!Z$3:Z$112) -> 25 | AF12: =SUMIF('Tabla 2 - Ataques detec (Imple)'!$D$3:$D$112,$B12,'Tabla 2 - Ataques detec (Imple)'!AA$3:AA$112) -> 17 | AG12: =AF12 & " (" & AE12 & ")" -> 17 (25) | AH12: =SUMIF('Tabla 2 - Ataques detec (Imple)'!$D$3:$D$112,$B12,'Tabla 2 - Ataques detec (Imple)'!$AB$3:$AB$112) -> 17 | AI12: =AVERAGEIF('Tabla 2 - Ataques detec (Imple)'!$D$3:$D$112,$B12,'Tabla 2 - Ataques detec (Imple)'!$AD$3:$AD$112) -> 1 | AJ12: =SUMIF('Tabla 2 - Ataques detec (Imple)'!$D$3:$D$112,$B12,'Tabla 2 - Ataques detec (Imple)'!$AC$3:$AC$112) -> 2 | AK12: =SUMIF('Tabla 2 - Ataques detec (Imple)'!$D$3:$D$112,$B12,'Tabla 2 - Ataques detec (Imple)'!AE$3:AE$112) -> 30 | AL12: =SUMIF('Tabla 2 - Ataques detec (Imple)'!$D$3:$D$112,$B12,'Tabla 2 - Ataques detec (Imple)'!AF$3:AF$112) -> 19 | AM12: =AL12 & " (" & AK12 & ")" -> 19 (30) | AN12: =SUMIF('Tabla 2 - Ataques detec (Imple)'!$D$3:$D$112,$B12,'Tabla 2 - Ataques detec (Imple)'!$AG$3:$AG$112) -> 19 | AO12: =AVERAGEIF('Tabla 2 - Ataques detec (Imple)'!$D$3:$D$112,$B12,'Tabla 2 - Ataques detec (Imple)'!$AI$3:$AI$112) -> 1 | AP12: =SUMIF('Tabla 2 - Ataques detec (Imple)'!$D$3:$D$112,$B12,'Tabla 2 - Ataques detec (Imple)'!$AH$3:$AH$112) -> 2 | AQ12: =SUMIF('Tabla 2 - Ataques detec (Imple)'!$D$3:$D$112,$B12,'Tabla 2 - Ataques detec (Imple)'!AJ$3:AJ$112) -> 0 | AR12: =SUMIF('Tabla 2 - Ataques detec (Imple)'!$D$3:$D$112,$B12,'Tabla 2 - Ataques detec (Imple)'!AK$3:AK$112) -> 0 | AS12: =AR12 & " (" & AQ12 & ")" -> 0 (0) | AT12: =SUMIF('Tabla 2 - Ataques detec (Imple)'!$D$3:$D$112,$B12,'Tabla 2 - Ataques detec (Imple)'!$AL$3:$AL$112) -> 0 | AU12: =AVERAGEIF('Tabla 2 - Ataques detec (Imple)'!$D$3:$D$112,$B12,'Tabla 2 - Ataques detec (Imple)'!$AN$3:$AN$112) -> 0 | AV12: =SUMIF('Tabla 2 - Ataques detec (Imple)'!$D$3:$D$112,$B12,'Tabla 2 - Ataques detec (Imple)'!$AM$3:$AM$112) -> 0 | AW12: =SUMIF('Tabla 2 - Ataques detec (Imple)'!$D$3:$D$112,$B12,'Tabla 2 - Ataques detec (Imple)'!AO$3:AO$112) -> 0 | AX12: =SUMIF('Tabla 2 - Ataques detec (Imple)'!$D$3:$D$112,$B12,'Tabla 2 - Ataques detec (Imple)'!AP$3:AP$112) -> 0 | AY12: =AX12 & " (" & AW12 & ")" -> 0 (0) | AZ12: =SUMIF('Tabla 2 - Ataques detec (Imple)'!$D$3:$D$112,$B12,'Tabla 2 - Ataques detec (Imple)'!$AQ$3:$AQ$112) -> 0 | BA12: =AVERAGEIF('Tabla 2 - Ataques detec (Imple)'!$D$3:$D$112,$B12,'Tabla 2 - Ataques detec (Imple)'!$AS$3:$AS$112) -> 0 | BB12: =SUMIF('Tabla 2 - Ataques detec (Imple)'!$D$3:$D$112,$B12,'Tabla 2 - Ataques detec (Imple)'!$AR$3:$AR$112) -> 0 | BC12: =SUMIF('Tabla 2 - Ataques detec (Imple)'!$D$3:$D$112,$B12,'Tabla 2 - Ataques detec (Imple)'!AT$3:AT$112) -> 0 | BD12: =SUMIF('Tabla 2 - Ataques detec (Imple)'!$D$3:$D$112,$B12,'Tabla 2 - Ataques detec (Imple)'!AU$3:AU$112) -> 0 | BE12: =BD12 & " (" & BC12 & ")" -> 0 (0) | BF12: =SUMIF('Tabla 2 - Ataques detec (Imple)'!$D$3:$D$112,$B12,'Tabla 2 - Ataques detec (Imple)'!$AV$3:$AV$112) -> 0 | BG12: =AVERAGEIF('Tabla 2 - Ataques detec (Imple)'!$D$3:$D$112,$B12,'Tabla 2 - Ataques detec (Imple)'!$AX$3:$AX$112) -> 0 | BH12: =SUMIF('Tabla 2 - Ataques detec (Imple)'!$D$3:$D$112,$B12,'Tabla 2 - Ataques detec (Imple)'!$AW$3:$AW$112) -> 0 | BI12: =SUMIF('Tabla 2 - Ataques detec (Imple)'!$D$3:$D$112,$B12,'Tabla 2 - Ataques detec (Imple)'!AY$3:AY$112) -> 0 | BJ12: =SUMIF('Tabla 2 - Ataques detec (Imple)'!$D$3:$D$112,$B12,'Tabla 2 - Ataques detec (Imple)'!AZ$3:AZ$112) -> 0 | BK12: =BJ12 & " (" & BI12 & ")" -> 0 (0) | BL12: =SUMIF('Tabla 2 - Ataques detec (Imple)'!$D$3:$D$112,$B12,'Tabla 2 - Ataques detec (Imple)'!BA$3:BA$112) -> 0 | BM12: =AVERAGEIF('Tabla 2 - Ataques detec (Imple)'!$D$3:$D$112,$B12,'Tabla 2 - Ataques detec (Imple)'!$BC$3:$BC$112) -> 0 | BN12: =SUMIF('Tabla 2 - Ataques detec (Imple)'!$D$3:$D$112,$B12,'Tabla 2 - Ataques detec (Imple)'!$BB$3:$BB$112) -> 0 | BO12: =SUMIF('Tabla 2 - Ataques detec (Imple)'!$D$3:$D$112,$B12,'Tabla 2 - Ataques detec (Imple)'!BD$3:BD$112) -> 10 | BP12: =SUMIF('Tabla 2 - Ataques detec (Imple)'!$D$3:$D$112,$B12,'Tabla 2 - Ataques detec (Imple)'!BE$3:BE$112) -> 9 | BQ12: =BP12 & " (" & BO12 & ")" -> 9 (10) | BR12: =SUMIF('Tabla 2 - Ataques detec (Imple)'!$D$3:$D$112,$B12,'Tabla 2 - Ataques detec (Imple)'!BF$3:BF$112) -> 0 | BS12: =SUMIF('Tabla 2 - Ataques detec (Imple)'!$D$3:$D$112,$B12,'Tabla 2 - Ataques detec (Imple)'!BG$3:BG$112) -> 5 | BT12: =AVERAGEIF('Tabla 2 - Ataques detec (Imple)'!$D$3:$D$112,$B12,'Tabla 2 - Ataques detec (Imple)'!$BI$3:$BI$112) -> 1 | BU12: =SUMIF('Tabla 2 - Ataques detec (Imple)'!$D$3:$D$112,$B12,'Tabla 2 - Ataques detec (Imple)'!$BH$3:$BH$112) -> 7 | BV12: 5 | BW12: 1 | BX12: =BW12 & " (" & BV12 & ")" -> 1 (5) | BY12: 1 | BZ12: 1 | CA12: 1 | CB12: 10 | CC12: 2 | CD12: =CC12 & " (" & CB12 & ")" -> 2 (10) | CE12: 1 | CF12: 1 | CG12: 1 | CH12: 1
A13: =A12+1 -> 11 | B13: =IFERROR(VLOOKUP(A13,'Tabla 2 - Ataques detec (Imple)'!$B$3:$D$112,3,FALSE),"") -> T1039 | C13: =IFERROR(VLOOKUP(B13,Techniques!$B$3:$H$213,2,FALSE),"") -> Data from Network Shared Drive | D13: =SUMPRODUCT( ('Tabla 2 - Ataques detec (Imple)'!$D$3:$D$112=$B13)* (LEN('Tabla 2 - Ataques detec (Imple)'!$C$3:$C$112)>0) ) -> 1 | E13: =SUMIF('Tabla 2 - Ataques detec (Imple)'!$D$3:$D$112,$B13,'Tabla 2 - Ataques detec (Imple)'!$E$3:$E$112) -> 3 | F13: =D13&" ("&E13&")" -> 1 (3) | G13: =SUMIF('Tabla 2 - Ataques detec (Imple)'!$D$3:$D$112,$B13,'Tabla 2 - Ataques detec (Imple)'!F$3:F$112) -> 1 | H13: =SUMIF('Tabla 2 - Ataques detec (Imple)'!$D$3:$D$112,$B13,'Tabla 2 - Ataques detec (Imple)'!G$3:G$112) -> 1 | I13: =H13 & " (" & G13 & ")" -> 1 (1) | J13: =SUMIF('Tabla 2 - Ataques detec (Imple)'!$D$3:$D$112,$B13,'Tabla 2 - Ataques detec (Imple)'!$H$3:$H$112) -> 1 | K13: =AVERAGEIF('Tabla 2 - Ataques detec (Imple)'!$D$3:$D$112,$B13,'Tabla 2 - Ataques detec (Imple)'!$J$3:$J$112) -> 1 | L13: =SUMIF('Tabla 2 - Ataques detec (Imple)'!$D$3:$D$112,$B13,'Tabla 2 - Ataques detec (Imple)'!$I$3:$I$112) -> 1 | M13: =SUMIF('Tabla 2 - Ataques detec (Imple)'!$D$3:$D$112,$B13,'Tabla 2 - Ataques detec (Imple)'!K$3:K$112) -> 0 | N13: =SUMIF('Tabla 2 - Ataques detec (Imple)'!$D$3:$D$112,$B13,'Tabla 2 - Ataques detec (Imple)'!L$3:L$112) -> 0 | O13: =N13 & " (" & M13 & ")" -> 0 (0) | P13: =SUMIF('Tabla 2 - Ataques detec (Imple)'!$D$3:$D$112,$B13,'Tabla 2 - Ataques detec (Imple)'!$M$3:$M$112) -> 0 | Q13: =AVERAGEIF('Tabla 2 - Ataques detec (Imple)'!$D$3:$D$112,$B13,'Tabla 2 - Ataques detec (Imple)'!$O$3:$O$112) -> 0 | R13: =SUMIF('Tabla 2 - Ataques detec (Imple)'!$D$3:$D$112,$B13,'Tabla 2 - Ataques detec (Imple)'!$N$3:$N$112) -> 0 | S13: =SUMIF('Tabla 2 - Ataques detec (Imple)'!$D$3:$D$112,$B13,'Tabla 2 - Ataques detec (Imple)'!P$3:P$112) -> 1 | T13: =SUMIF('Tabla 2 - Ataques detec (Imple)'!$D$3:$D$112,$B13,'Tabla 2 - Ataques detec (Imple)'!Q$3:Q$112) -> 1 | U13: =T13 & " (" & S13 & ")" -> 1 (1) | V13: =SUMIF('Tabla 2 - Ataques detec (Imple)'!$D$3:$D$112,$B13,'Tabla 2 - Ataques detec (Imple)'!$R$3:$R$112) -> 1 | W13: =AVERAGEIF('Tabla 2 - Ataques detec (Imple)'!$D$3:$D$112,$B13,'Tabla 2 - Ataques detec (Imple)'!$T$3:$T$112) -> 1 | X13: =SUMIF('Tabla 2 - Ataques detec (Imple)'!$D$3:$D$112,$B13,'Tabla 2 - Ataques detec (Imple)'!$S$3:$S$112) -> 1 | Y13: =SUMIF('Tabla 2 - Ataques detec (Imple)'!$D$3:$D$112,$B13,'Tabla 2 - Ataques detec (Imple)'!U$3:U$112) -> 2 | Z13: =SUMIF('Tabla 2 - Ataques detec (Imple)'!$D$3:$D$112,$B13,'Tabla 2 - Ataques detec (Imple)'!V$3:V$112) -> 2 | AA13: =Z13 & " (" & Y13 & ")" -> 2 (2) | AB13: =SUMIF('Tabla 2 - Ataques detec (Imple)'!$D$3:$D$112,$B13,'Tabla 2 - Ataques detec (Imple)'!$R$3:$R$112) -> 1 | AC13: =AVERAGEIF('Tabla 2 - Ataques detec (Imple)'!$D$3:$D$112,$B13,'Tabla 2 - Ataques detec (Imple)'!$Y$3:$Y$112) -> 1 | AD13: =SUMIF('Tabla 2 - Ataques detec (Imple)'!$D$3:$D$112,$B13,'Tabla 2 - Ataques detec (Imple)'!$X$3:$X$112) -> 1 | AE13: =SUMIF('Tabla 2 - Ataques detec (Imple)'!$D$3:$D$112,$B13,'Tabla 2 - Ataques detec (Imple)'!Z$3:Z$112) -> 20 | AF13: =SUMIF('Tabla 2 - Ataques detec (Imple)'!$D$3:$D$112,$B13,'Tabla 2 - Ataques detec (Imple)'!AA$3:AA$112) -> 20 | AG13: =AF13 & " (" & AE13 & ")" -> 20 (20) | AH13: =SUMIF('Tabla 2 - Ataques detec (Imple)'!$D$3:$D$112,$B13,'Tabla 2 - Ataques detec (Imple)'!$AB$3:$AB$112) -> 18 | AI13: =AVERAGEIF('Tabla 2 - Ataques detec (Imple)'!$D$3:$D$112,$B13,'Tabla 2 - Ataques detec (Imple)'!$AD$3:$AD$112) -> 1 | AJ13: =SUMIF('Tabla 2 - Ataques detec (Imple)'!$D$3:$D$112,$B13,'Tabla 2 - Ataques detec (Imple)'!$AC$3:$AC$112) -> 3 | AK13: =SUMIF('Tabla 2 - Ataques detec (Imple)'!$D$3:$D$112,$B13,'Tabla 2 - Ataques detec (Imple)'!AE$3:AE$112) -> 22 | AL13: =SUMIF('Tabla 2 - Ataques detec (Imple)'!$D$3:$D$112,$B13,'Tabla 2 - Ataques detec (Imple)'!AF$3:AF$112) -> 22 | AM13: =AL13 & " (" & AK13 & ")" -> 22 (22) | AN13: =SUMIF('Tabla 2 - Ataques detec (Imple)'!$D$3:$D$112,$B13,'Tabla 2 - Ataques detec (Imple)'!$AG$3:$AG$112) -> 20 | AO13: =AVERAGEIF('Tabla 2 - Ataques detec (Imple)'!$D$3:$D$112,$B13,'Tabla 2 - Ataques detec (Imple)'!$AI$3:$AI$112) -> 1 | AP13: =SUMIF('Tabla 2 - Ataques detec (Imple)'!$D$3:$D$112,$B13,'Tabla 2 - Ataques detec (Imple)'!$AH$3:$AH$112) -> 3 | AQ13: =SUMIF('Tabla 2 - Ataques detec (Imple)'!$D$3:$D$112,$B13,'Tabla 2 - Ataques detec (Imple)'!AJ$3:AJ$112) -> 0 | AR13: =SUMIF('Tabla 2 - Ataques detec (Imple)'!$D$3:$D$112,$B13,'Tabla 2 - Ataques detec (Imple)'!AK$3:AK$112) -> 0 | AS13: =AR13 & " (" & AQ13 & ")" -> 0 (0) | AT13: =SUMIF('Tabla 2 - Ataques detec (Imple)'!$D$3:$D$112,$B13,'Tabla 2 - Ataques detec (Imple)'!$AL$3:$AL$112) -> 0 | AU13: =AVERAGEIF('Tabla 2 - Ataques detec (Imple)'!$D$3:$D$112,$B13,'Tabla 2 - Ataques detec (Imple)'!$AN$3:$AN$112) -> 0 | AV13: =SUMIF('Tabla 2 - Ataques detec (Imple)'!$D$3:$D$112,$B13,'Tabla 2 - Ataques detec (Imple)'!$AM$3:$AM$112) -> 0 | AW13: =SUMIF('Tabla 2 - Ataques detec (Imple)'!$D$3:$D$112,$B13,'Tabla 2 - Ataques detec (Imple)'!AO$3:AO$112) -> 0 | AX13: =SUMIF('Tabla 2 - Ataques detec (Imple)'!$D$3:$D$112,$B13,'Tabla 2 - Ataques detec (Imple)'!AP$3:AP$112) -> 0 | AY13: =AX13 & " (" & AW13 & ")" -> 0 (0) | AZ13: =SUMIF('Tabla 2 - Ataques detec (Imple)'!$D$3:$D$112,$B13,'Tabla 2 - Ataques detec (Imple)'!$AQ$3:$AQ$112) -> 0 | BA13: =AVERAGEIF('Tabla 2 - Ataques detec (Imple)'!$D$3:$D$112,$B13,'Tabla 2 - Ataques detec (Imple)'!$AS$3:$AS$112) -> 0 | BB13: =SUMIF('Tabla 2 - Ataques detec (Imple)'!$D$3:$D$112,$B13,'Tabla 2 - Ataques detec (Imple)'!$AR$3:$AR$112) -> 0 | BC13: =SUMIF('Tabla 2 - Ataques detec (Imple)'!$D$3:$D$112,$B13,'Tabla 2 - Ataques detec (Imple)'!AT$3:AT$112) -> 1 | BD13: =SUMIF('Tabla 2 - Ataques detec (Imple)'!$D$3:$D$112,$B13,'Tabla 2 - Ataques detec (Imple)'!AU$3:AU$112) -> 1 | BE13: =BD13 & " (" & BC13 & ")" -> 1 (1) | BF13: =SUMIF('Tabla 2 - Ataques detec (Imple)'!$D$3:$D$112,$B13,'Tabla 2 - Ataques detec (Imple)'!$AV$3:$AV$112) -> 1 | BG13: =AVERAGEIF('Tabla 2 - Ataques detec (Imple)'!$D$3:$D$112,$B13,'Tabla 2 - Ataques detec (Imple)'!$AX$3:$AX$112) -> 1 | BH13: =SUMIF('Tabla 2 - Ataques detec (Imple)'!$D$3:$D$112,$B13,'Tabla 2 - Ataques detec (Imple)'!$AW$3:$AW$112) -> 1 | BI13: =SUMIF('Tabla 2 - Ataques detec (Imple)'!$D$3:$D$112,$B13,'Tabla 2 - Ataques detec (Imple)'!AY$3:AY$112) -> 0 | BJ13: =SUMIF('Tabla 2 - Ataques detec (Imple)'!$D$3:$D$112,$B13,'Tabla 2 - Ataques detec (Imple)'!AZ$3:AZ$112) -> 0 | BK13: =BJ13 & " (" & BI13 & ")" -> 0 (0) | BL13: =SUMIF('Tabla 2 - Ataques detec (Imple)'!$D$3:$D$112,$B13,'Tabla 2 - Ataques detec (Imple)'!BA$3:BA$112) -> 0 | BM13: =AVERAGEIF('Tabla 2 - Ataques detec (Imple)'!$D$3:$D$112,$B13,'Tabla 2 - Ataques detec (Imple)'!$BC$3:$BC$112) -> 0 | BN13: =SUMIF('Tabla 2 - Ataques detec (Imple)'!$D$3:$D$112,$B13,'Tabla 2 - Ataques detec (Imple)'!$BB$3:$BB$112) -> 0 | BO13: =SUMIF('Tabla 2 - Ataques detec (Imple)'!$D$3:$D$112,$B13,'Tabla 2 - Ataques detec (Imple)'!BD$3:BD$112) -> 5 | BP13: =SUMIF('Tabla 2 - Ataques detec (Imple)'!$D$3:$D$112,$B13,'Tabla 2 - Ataques detec (Imple)'!BE$3:BE$112) -> 4 | BQ13: =BP13 & " (" & BO13 & ")" -> 4 (5) | BR13: =SUMIF('Tabla 2 - Ataques detec (Imple)'!$D$3:$D$112,$B13,'Tabla 2 - Ataques detec (Imple)'!BF$3:BF$112) -> 0 | BS13: =SUMIF('Tabla 2 - Ataques detec (Imple)'!$D$3:$D$112,$B13,'Tabla 2 - Ataques detec (Imple)'!BG$3:BG$112) -> 4 | BT13: =AVERAGEIF('Tabla 2 - Ataques detec (Imple)'!$D$3:$D$112,$B13,'Tabla 2 - Ataques detec (Imple)'!$BI$3:$BI$112) -> 1 | BU13: =SUMIF('Tabla 2 - Ataques detec (Imple)'!$D$3:$D$112,$B13,'Tabla 2 - Ataques detec (Imple)'!$BH$3:$BH$112) -> 1 | BV13: 1 | BW13: 1 | BX13: =BW13 & " (" & BV13 & ")" -> 1 (1) | BY13: 1 | BZ13: 1 | CA13: 1 | CB13: 2 | CC13: 2 | CD13: =CC13 & " (" & CB13 & ")" -> 2 (2) | CE13: 1 | CF13: 1 | CG13: 1 | CH13: 1
A14: =A13+1 -> 12 | B14: =IFERROR(VLOOKUP(A14,'Tabla 2 - Ataques detec (Imple)'!$B$3:$D$112,3,FALSE),"") -> T1041 | C14: =IFERROR(VLOOKUP(B14,Techniques!$B$3:$H$213,2,FALSE),"") -> Exfiltration Over C2 Channel | D14: =SUMPRODUCT( ('Tabla 2 - Ataques detec (Imple)'!$D$3:$D$112=$B14)* (LEN('Tabla 2 - Ataques detec (Imple)'!$C$3:$C$112)>0) ) -> 1 | E14: =SUMIF('Tabla 2 - Ataques detec (Imple)'!$D$3:$D$112,$B14,'Tabla 2 - Ataques detec (Imple)'!$E$3:$E$112) -> 2 | F14: =D14&" ("&E14&")" -> 1 (2) | G14: =SUMIF('Tabla 2 - Ataques detec (Imple)'!$D$3:$D$112,$B14,'Tabla 2 - Ataques detec (Imple)'!F$3:F$112) -> 0 | H14: =SUMIF('Tabla 2 - Ataques detec (Imple)'!$D$3:$D$112,$B14,'Tabla 2 - Ataques detec (Imple)'!G$3:G$112) -> 0 | I14: =H14 & " (" & G14 & ")" -> 0 (0) | J14: =SUMIF('Tabla 2 - Ataques detec (Imple)'!$D$3:$D$112,$B14,'Tabla 2 - Ataques detec (Imple)'!$H$3:$H$112) -> 0 | K14: =AVERAGEIF('Tabla 2 - Ataques detec (Imple)'!$D$3:$D$112,$B14,'Tabla 2 - Ataques detec (Imple)'!$J$3:$J$112) -> 0 | L14: =SUMIF('Tabla 2 - Ataques detec (Imple)'!$D$3:$D$112,$B14,'Tabla 2 - Ataques detec (Imple)'!$I$3:$I$112) -> 0 | M14: =SUMIF('Tabla 2 - Ataques detec (Imple)'!$D$3:$D$112,$B14,'Tabla 2 - Ataques detec (Imple)'!K$3:K$112) -> 8 | N14: =SUMIF('Tabla 2 - Ataques detec (Imple)'!$D$3:$D$112,$B14,'Tabla 2 - Ataques detec (Imple)'!L$3:L$112) -> 4 | O14: =N14 & " (" & M14 & ")" -> 4 (8) | P14: =SUMIF('Tabla 2 - Ataques detec (Imple)'!$D$3:$D$112,$B14,'Tabla 2 - Ataques detec (Imple)'!$M$3:$M$112) -> 4 | Q14: =AVERAGEIF('Tabla 2 - Ataques detec (Imple)'!$D$3:$D$112,$B14,'Tabla 2 - Ataques detec (Imple)'!$O$3:$O$112) -> 1 | R14: =SUMIF('Tabla 2 - Ataques detec (Imple)'!$D$3:$D$112,$B14,'Tabla 2 - Ataques detec (Imple)'!$N$3:$N$112) -> 2 | S14: =SUMIF('Tabla 2 - Ataques detec (Imple)'!$D$3:$D$112,$B14,'Tabla 2 - Ataques detec (Imple)'!P$3:P$112) -> 8 | T14: =SUMIF('Tabla 2 - Ataques detec (Imple)'!$D$3:$D$112,$B14,'Tabla 2 - Ataques detec (Imple)'!Q$3:Q$112) -> 4 | U14: =T14 & " (" & S14 & ")" -> 4 (8) | V14: =SUMIF('Tabla 2 - Ataques detec (Imple)'!$D$3:$D$112,$B14,'Tabla 2 - Ataques detec (Imple)'!$R$3:$R$112) -> 4 | W14: =AVERAGEIF('Tabla 2 - Ataques detec (Imple)'!$D$3:$D$112,$B14,'Tabla 2 - Ataques detec (Imple)'!$T$3:$T$112) -> 1 | X14: =SUMIF('Tabla 2 - Ataques detec (Imple)'!$D$3:$D$112,$B14,'Tabla 2 - Ataques detec (Imple)'!$S$3:$S$112) -> 2 | Y14: =SUMIF('Tabla 2 - Ataques detec (Imple)'!$D$3:$D$112,$B14,'Tabla 2 - Ataques detec (Imple)'!U$3:U$112) -> 7 | Z14: =SUMIF('Tabla 2 - Ataques detec (Imple)'!$D$3:$D$112,$B14,'Tabla 2 - Ataques detec (Imple)'!V$3:V$112) -> 3 | AA14: =Z14 & " (" & Y14 & ")" -> 3 (7) | AB14: =SUMIF('Tabla 2 - Ataques detec (Imple)'!$D$3:$D$112,$B14,'Tabla 2 - Ataques detec (Imple)'!$R$3:$R$112) -> 4 | AC14: =AVERAGEIF('Tabla 2 - Ataques detec (Imple)'!$D$3:$D$112,$B14,'Tabla 2 - Ataques detec (Imple)'!$Y$3:$Y$112) -> 1 | AD14: =SUMIF('Tabla 2 - Ataques detec (Imple)'!$D$3:$D$112,$B14,'Tabla 2 - Ataques detec (Imple)'!$X$3:$X$112) -> 2 | AE14: =SUMIF('Tabla 2 - Ataques detec (Imple)'!$D$3:$D$112,$B14,'Tabla 2 - Ataques detec (Imple)'!Z$3:Z$112) -> 25 | AF14: =SUMIF('Tabla 2 - Ataques detec (Imple)'!$D$3:$D$112,$B14,'Tabla 2 - Ataques detec (Imple)'!AA$3:AA$112) -> 11 | AG14: =AF14 & " (" & AE14 & ")" -> 11 (25) | AH14: =SUMIF('Tabla 2 - Ataques detec (Imple)'!$D$3:$D$112,$B14,'Tabla 2 - Ataques detec (Imple)'!$AB$3:$AB$112) -> 10 | AI14: =AVERAGEIF('Tabla 2 - Ataques detec (Imple)'!$D$3:$D$112,$B14,'Tabla 2 - Ataques detec (Imple)'!$AD$3:$AD$112) -> 1 | AJ14: =SUMIF('Tabla 2 - Ataques detec (Imple)'!$D$3:$D$112,$B14,'Tabla 2 - Ataques detec (Imple)'!$AC$3:$AC$112) -> 2 | AK14: =SUMIF('Tabla 2 - Ataques detec (Imple)'!$D$3:$D$112,$B14,'Tabla 2 - Ataques detec (Imple)'!AE$3:AE$112) -> 32 | AL14: =SUMIF('Tabla 2 - Ataques detec (Imple)'!$D$3:$D$112,$B14,'Tabla 2 - Ataques detec (Imple)'!AF$3:AF$112) -> 14 | AM14: =AL14 & " (" & AK14 & ")" -> 14 (32) | AN14: =SUMIF('Tabla 2 - Ataques detec (Imple)'!$D$3:$D$112,$B14,'Tabla 2 - Ataques detec (Imple)'!$AG$3:$AG$112) -> 12 | AO14: =AVERAGEIF('Tabla 2 - Ataques detec (Imple)'!$D$3:$D$112,$B14,'Tabla 2 - Ataques detec (Imple)'!$AI$3:$AI$112) -> 1 | AP14: =SUMIF('Tabla 2 - Ataques detec (Imple)'!$D$3:$D$112,$B14,'Tabla 2 - Ataques detec (Imple)'!$AH$3:$AH$112) -> 2 | AQ14: =SUMIF('Tabla 2 - Ataques detec (Imple)'!$D$3:$D$112,$B14,'Tabla 2 - Ataques detec (Imple)'!AJ$3:AJ$112) -> 0 | AR14: =SUMIF('Tabla 2 - Ataques detec (Imple)'!$D$3:$D$112,$B14,'Tabla 2 - Ataques detec (Imple)'!AK$3:AK$112) -> 0 | AS14: =AR14 & " (" & AQ14 & ")" -> 0 (0) | AT14: =SUMIF('Tabla 2 - Ataques detec (Imple)'!$D$3:$D$112,$B14,'Tabla 2 - Ataques detec (Imple)'!$AL$3:$AL$112) -> 0 | AU14: =AVERAGEIF('Tabla 2 - Ataques detec (Imple)'!$D$3:$D$112,$B14,'Tabla 2 - Ataques detec (Imple)'!$AN$3:$AN$112) -> 0 | AV14: =SUMIF('Tabla 2 - Ataques detec (Imple)'!$D$3:$D$112,$B14,'Tabla 2 - Ataques detec (Imple)'!$AM$3:$AM$112) -> 0 | AW14: =SUMIF('Tabla 2 - Ataques detec (Imple)'!$D$3:$D$112,$B14,'Tabla 2 - Ataques detec (Imple)'!AO$3:AO$112) -> 0 | AX14: =SUMIF('Tabla 2 - Ataques detec (Imple)'!$D$3:$D$112,$B14,'Tabla 2 - Ataques detec (Imple)'!AP$3:AP$112) -> 0 | AY14: =AX14 & " (" & AW14 & ")" -> 0 (0) | AZ14: =SUMIF('Tabla 2 - Ataques detec (Imple)'!$D$3:$D$112,$B14,'Tabla 2 - Ataques detec (Imple)'!$AQ$3:$AQ$112) -> 0 | BA14: =AVERAGEIF('Tabla 2 - Ataques detec (Imple)'!$D$3:$D$112,$B14,'Tabla 2 - Ataques detec (Imple)'!$AS$3:$AS$112) -> 0 | BB14: =SUMIF('Tabla 2 - Ataques detec (Imple)'!$D$3:$D$112,$B14,'Tabla 2 - Ataques detec (Imple)'!$AR$3:$AR$112) -> 0 | BC14: =SUMIF('Tabla 2 - Ataques detec (Imple)'!$D$3:$D$112,$B14,'Tabla 2 - Ataques detec (Imple)'!AT$3:AT$112) -> 8 | BD14: =SUMIF('Tabla 2 - Ataques detec (Imple)'!$D$3:$D$112,$B14,'Tabla 2 - Ataques detec (Imple)'!AU$3:AU$112) -> 4 | BE14: =BD14 & " (" & BC14 & ")" -> 4 (8) | BF14: =SUMIF('Tabla 2 - Ataques detec (Imple)'!$D$3:$D$112,$B14,'Tabla 2 - Ataques detec (Imple)'!$AV$3:$AV$112) -> 4 | BG14: =AVERAGEIF('Tabla 2 - Ataques detec (Imple)'!$D$3:$D$112,$B14,'Tabla 2 - Ataques detec (Imple)'!$AX$3:$AX$112) -> 1 | BH14: =SUMIF('Tabla 2 - Ataques detec (Imple)'!$D$3:$D$112,$B14,'Tabla 2 - Ataques detec (Imple)'!$AW$3:$AW$112) -> 2 | BI14: =SUMIF('Tabla 2 - Ataques detec (Imple)'!$D$3:$D$112,$B14,'Tabla 2 - Ataques detec (Imple)'!AY$3:AY$112) -> 0 | BJ14: =SUMIF('Tabla 2 - Ataques detec (Imple)'!$D$3:$D$112,$B14,'Tabla 2 - Ataques detec (Imple)'!AZ$3:AZ$112) -> 0 | BK14: =BJ14 & " (" & BI14 & ")" -> 0 (0) | BL14: =SUMIF('Tabla 2 - Ataques detec (Imple)'!$D$3:$D$112,$B14,'Tabla 2 - Ataques detec (Imple)'!BA$3:BA$112) -> 0 | BM14: =AVERAGEIF('Tabla 2 - Ataques detec (Imple)'!$D$3:$D$112,$B14,'Tabla 2 - Ataques detec (Imple)'!$BC$3:$BC$112) -> 0 | BN14: =SUMIF('Tabla 2 - Ataques detec (Imple)'!$D$3:$D$112,$B14,'Tabla 2 - Ataques detec (Imple)'!$BB$3:$BB$112) -> 0 | BO14: =SUMIF('Tabla 2 - Ataques detec (Imple)'!$D$3:$D$112,$B14,'Tabla 2 - Ataques detec (Imple)'!BD$3:BD$112) -> 2 | BP14: =SUMIF('Tabla 2 - Ataques detec (Imple)'!$D$3:$D$112,$B14,'Tabla 2 - Ataques detec (Imple)'!BE$3:BE$112) -> 2 | BQ14: =BP14 & " (" & BO14 & ")" -> 2 (2) | BR14: =SUMIF('Tabla 2 - Ataques detec (Imple)'!$D$3:$D$112,$B14,'Tabla 2 - Ataques detec (Imple)'!BF$3:BF$112) -> 0 | BS14: =SUMIF('Tabla 2 - Ataques detec (Imple)'!$D$3:$D$112,$B14,'Tabla 2 - Ataques detec (Imple)'!BG$3:BG$112) -> 2 | BT14: =AVERAGEIF('Tabla 2 - Ataques detec (Imple)'!$D$3:$D$112,$B14,'Tabla 2 - Ataques detec (Imple)'!$BI$3:$BI$112) -> 1 | BU14: =SUMIF('Tabla 2 - Ataques detec (Imple)'!$D$3:$D$112,$B14,'Tabla 2 - Ataques detec (Imple)'!$BH$3:$BH$112) -> 1 | BV14: 0 | BW14: 0 | BX14: =BW14 & " (" & BV14 & ")" -> 0 (0) | BY14: 0 | BZ14: 0 | CA14: 0 | CB14: 0 | CC14: 0 | CD14: =CC14 & " (" & CB14 & ")" -> 0 (0) | CE14: 0 | CF14: 0 | CG14: 0 | CH14: 0
A15: =A14+1 -> 13 | B15: =IFERROR(VLOOKUP(A15,'Tabla 2 - Ataques detec (Imple)'!$B$3:$D$112,3,FALSE),"") -> T1046 | C15: =IFERROR(VLOOKUP(B15,Techniques!$B$3:$H$213,2,FALSE),"") -> Network Service Discovery | D15: =SUMPRODUCT( ('Tabla 2 - Ataques detec (Imple)'!$D$3:$D$112=$B15)* (LEN('Tabla 2 - Ataques detec (Imple)'!$C$3:$C$112)>0) ) -> 3 | E15: =SUMIF('Tabla 2 - Ataques detec (Imple)'!$D$3:$D$112,$B15,'Tabla 2 - Ataques detec (Imple)'!$E$3:$E$112) -> 65846 | F15: =D15&" ("&E15&")" -> 3 (65846) | G15: =SUMIF('Tabla 2 - Ataques detec (Imple)'!$D$3:$D$112,$B15,'Tabla 2 - Ataques detec (Imple)'!F$3:F$112) -> 276 | H15: =SUMIF('Tabla 2 - Ataques detec (Imple)'!$D$3:$D$112,$B15,'Tabla 2 - Ataques detec (Imple)'!G$3:G$112) -> 107 | I15: =H15 & " (" & G15 & ")" -> 107 (276) | J15: =SUMIF('Tabla 2 - Ataques detec (Imple)'!$D$3:$D$112,$B15,'Tabla 2 - Ataques detec (Imple)'!$H$3:$H$112) -> 13 | K15: =AVERAGEIF('Tabla 2 - Ataques detec (Imple)'!$D$3:$D$112,$B15,'Tabla 2 - Ataques detec (Imple)'!$J$3:$J$112) -> 0.66666667 | L15: =SUMIF('Tabla 2 - Ataques detec (Imple)'!$D$3:$D$112,$B15,'Tabla 2 - Ataques detec (Imple)'!$I$3:$I$112) -> 87 | M15: =SUMIF('Tabla 2 - Ataques detec (Imple)'!$D$3:$D$112,$B15,'Tabla 2 - Ataques detec (Imple)'!K$3:K$112) -> 858 | N15: =SUMIF('Tabla 2 - Ataques detec (Imple)'!$D$3:$D$112,$B15,'Tabla 2 - Ataques detec (Imple)'!L$3:L$112) -> 305 | O15: =N15 & " (" & M15 & ")" -> 305 (858) | P15: =SUMIF('Tabla 2 - Ataques detec (Imple)'!$D$3:$D$112,$B15,'Tabla 2 - Ataques detec (Imple)'!$M$3:$M$112) -> 123 | Q15: =AVERAGEIF('Tabla 2 - Ataques detec (Imple)'!$D$3:$D$112,$B15,'Tabla 2 - Ataques detec (Imple)'!$O$3:$O$112) -> 1 | R15: =SUMIF('Tabla 2 - Ataques detec (Imple)'!$D$3:$D$112,$B15,'Tabla 2 - Ataques detec (Imple)'!$N$3:$N$112) -> 116 | S15: =SUMIF('Tabla 2 - Ataques detec (Imple)'!$D$3:$D$112,$B15,'Tabla 2 - Ataques detec (Imple)'!P$3:P$112) -> 1134 | T15: =SUMIF('Tabla 2 - Ataques detec (Imple)'!$D$3:$D$112,$B15,'Tabla 2 - Ataques detec (Imple)'!Q$3:Q$112) -> 412 | U15: =T15 & " (" & S15 & ")" -> 412 (1134) | V15: =SUMIF('Tabla 2 - Ataques detec (Imple)'!$D$3:$D$112,$B15,'Tabla 2 - Ataques detec (Imple)'!$R$3:$R$112) -> 136 | W15: =AVERAGEIF('Tabla 2 - Ataques detec (Imple)'!$D$3:$D$112,$B15,'Tabla 2 - Ataques detec (Imple)'!$T$3:$T$112) -> 1 | X15: =SUMIF('Tabla 2 - Ataques detec (Imple)'!$D$3:$D$112,$B15,'Tabla 2 - Ataques detec (Imple)'!$S$3:$S$112) -> 136 | Y15: =SUMIF('Tabla 2 - Ataques detec (Imple)'!$D$3:$D$112,$B15,'Tabla 2 - Ataques detec (Imple)'!U$3:U$112) -> 15728 | Z15: =SUMIF('Tabla 2 - Ataques detec (Imple)'!$D$3:$D$112,$B15,'Tabla 2 - Ataques detec (Imple)'!V$3:V$112) -> 1260 | AA15: =Z15 & " (" & Y15 & ")" -> 1260 (15728) | AB15: =SUMIF('Tabla 2 - Ataques detec (Imple)'!$D$3:$D$112,$B15,'Tabla 2 - Ataques detec (Imple)'!$R$3:$R$112) -> 136 | AC15: =AVERAGEIF('Tabla 2 - Ataques detec (Imple)'!$D$3:$D$112,$B15,'Tabla 2 - Ataques detec (Imple)'!$Y$3:$Y$112) -> 1 | AD15: =SUMIF('Tabla 2 - Ataques detec (Imple)'!$D$3:$D$112,$B15,'Tabla 2 - Ataques detec (Imple)'!$X$3:$X$112) -> 170 | AE15: =SUMIF('Tabla 2 - Ataques detec (Imple)'!$D$3:$D$112,$B15,'Tabla 2 - Ataques detec (Imple)'!Z$3:Z$112) -> 4184 | AF15: =SUMIF('Tabla 2 - Ataques detec (Imple)'!$D$3:$D$112,$B15,'Tabla 2 - Ataques detec (Imple)'!AA$3:AA$112) -> 822 | AG15: =AF15 & " (" & AE15 & ")" -> 822 (4184) | AH15: =SUMIF('Tabla 2 - Ataques detec (Imple)'!$D$3:$D$112,$B15,'Tabla 2 - Ataques detec (Imple)'!$AB$3:$AB$112) -> 341 | AI15: =AVERAGEIF('Tabla 2 - Ataques detec (Imple)'!$D$3:$D$112,$B15,'Tabla 2 - Ataques detec (Imple)'!$AD$3:$AD$112) -> 1 | AJ15: =SUMIF('Tabla 2 - Ataques detec (Imple)'!$D$3:$D$112,$B15,'Tabla 2 - Ataques detec (Imple)'!$AC$3:$AC$112) -> 142 | AK15: =SUMIF('Tabla 2 - Ataques detec (Imple)'!$D$3:$D$112,$B15,'Tabla 2 - Ataques detec (Imple)'!AE$3:AE$112) -> 19912 | AL15: =SUMIF('Tabla 2 - Ataques detec (Imple)'!$D$3:$D$112,$B15,'Tabla 2 - Ataques detec (Imple)'!AF$3:AF$112) -> 2082 | AM15: =AL15 & " (" & AK15 & ")" -> 2082 (19912) | AN15: =SUMIF('Tabla 2 - Ataques detec (Imple)'!$D$3:$D$112,$B15,'Tabla 2 - Ataques detec (Imple)'!$AG$3:$AG$112) -> 793 | AO15: =AVERAGEIF('Tabla 2 - Ataques detec (Imple)'!$D$3:$D$112,$B15,'Tabla 2 - Ataques detec (Imple)'!$AI$3:$AI$112) -> 1 | AP15: =SUMIF('Tabla 2 - Ataques detec (Imple)'!$D$3:$D$112,$B15,'Tabla 2 - Ataques detec (Imple)'!$AH$3:$AH$112) -> 178 | AQ15: =SUMIF('Tabla 2 - Ataques detec (Imple)'!$D$3:$D$112,$B15,'Tabla 2 - Ataques detec (Imple)'!AJ$3:AJ$112) -> 0 | AR15: =SUMIF('Tabla 2 - Ataques detec (Imple)'!$D$3:$D$112,$B15,'Tabla 2 - Ataques detec (Imple)'!AK$3:AK$112) -> 0 | AS15: =AR15 & " (" & AQ15 & ")" -> 0 (0) | AT15: =SUMIF('Tabla 2 - Ataques detec (Imple)'!$D$3:$D$112,$B15,'Tabla 2 - Ataques detec (Imple)'!$AL$3:$AL$112) -> 0 | AU15: =AVERAGEIF('Tabla 2 - Ataques detec (Imple)'!$D$3:$D$112,$B15,'Tabla 2 - Ataques detec (Imple)'!$AN$3:$AN$112) -> 0 | AV15: =SUMIF('Tabla 2 - Ataques detec (Imple)'!$D$3:$D$112,$B15,'Tabla 2 - Ataques detec (Imple)'!$AM$3:$AM$112) -> 0 | AW15: =SUMIF('Tabla 2 - Ataques detec (Imple)'!$D$3:$D$112,$B15,'Tabla 2 - Ataques detec (Imple)'!AO$3:AO$112) -> 1815 | AX15: =SUMIF('Tabla 2 - Ataques detec (Imple)'!$D$3:$D$112,$B15,'Tabla 2 - Ataques detec (Imple)'!AP$3:AP$112) -> 629 | AY15: =AX15 & " (" & AW15 & ")" -> 629 (1815) | AZ15: =SUMIF('Tabla 2 - Ataques detec (Imple)'!$D$3:$D$112,$B15,'Tabla 2 - Ataques detec (Imple)'!$AQ$3:$AQ$112) -> 346 | BA15: =AVERAGEIF('Tabla 2 - Ataques detec (Imple)'!$D$3:$D$112,$B15,'Tabla 2 - Ataques detec (Imple)'!$AS$3:$AS$112) -> 0.66666667 | BB15: =SUMIF('Tabla 2 - Ataques detec (Imple)'!$D$3:$D$112,$B15,'Tabla 2 - Ataques detec (Imple)'!$AR$3:$AR$112) -> 128 | BC15: =SUMIF('Tabla 2 - Ataques detec (Imple)'!$D$3:$D$112,$B15,'Tabla 2 - Ataques detec (Imple)'!AT$3:AT$112) -> 2949 | BD15: =SUMIF('Tabla 2 - Ataques detec (Imple)'!$D$3:$D$112,$B15,'Tabla 2 - Ataques detec (Imple)'!AU$3:AU$112) -> 1041 | BE15: =BD15 & " (" & BC15 & ")" -> 1041 (2949) | BF15: =SUMIF('Tabla 2 - Ataques detec (Imple)'!$D$3:$D$112,$B15,'Tabla 2 - Ataques detec (Imple)'!$AV$3:$AV$112) -> 482 | BG15: =AVERAGEIF('Tabla 2 - Ataques detec (Imple)'!$D$3:$D$112,$B15,'Tabla 2 - Ataques detec (Imple)'!$AX$3:$AX$112) -> 1 | BH15: =SUMIF('Tabla 2 - Ataques detec (Imple)'!$D$3:$D$112,$B15,'Tabla 2 - Ataques detec (Imple)'!$AW$3:$AW$112) -> 152 | BI15: =SUMIF('Tabla 2 - Ataques detec (Imple)'!$D$3:$D$112,$B15,'Tabla 2 - Ataques detec (Imple)'!AY$3:AY$112) -> 702 | BJ15: =SUMIF('Tabla 2 - Ataques detec (Imple)'!$D$3:$D$112,$B15,'Tabla 2 - Ataques detec (Imple)'!AZ$3:AZ$112) -> 468 | BK15: =BJ15 & " (" & BI15 & ")" -> 468 (702) | BL15: =SUMIF('Tabla 2 - Ataques detec (Imple)'!$D$3:$D$112,$B15,'Tabla 2 - Ataques detec (Imple)'!BA$3:BA$112) -> 110 | BM15: =AVERAGEIF('Tabla 2 - Ataques detec (Imple)'!$D$3:$D$112,$B15,'Tabla 2 - Ataques detec (Imple)'!$BC$3:$BC$112) -> 1 | BN15: =SUMIF('Tabla 2 - Ataques detec (Imple)'!$D$3:$D$112,$B15,'Tabla 2 - Ataques detec (Imple)'!$BB$3:$BB$112) -> 171 | BO15: =SUMIF('Tabla 2 - Ataques detec (Imple)'!$D$3:$D$112,$B15,'Tabla 2 - Ataques detec (Imple)'!BD$3:BD$112) -> 881 | BP15: =SUMIF('Tabla 2 - Ataques detec (Imple)'!$D$3:$D$112,$B15,'Tabla 2 - Ataques detec (Imple)'!BE$3:BE$112) -> 647 | BQ15: =BP15 & " (" & BO15 & ")" -> 647 (881) | BR15: =SUMIF('Tabla 2 - Ataques detec (Imple)'!$D$3:$D$112,$B15,'Tabla 2 - Ataques detec (Imple)'!BF$3:BF$112) -> 110 | BS15: =SUMIF('Tabla 2 - Ataques detec (Imple)'!$D$3:$D$112,$B15,'Tabla 2 - Ataques detec (Imple)'!BG$3:BG$112) -> 11 | BT15: =AVERAGEIF('Tabla 2 - Ataques detec (Imple)'!$D$3:$D$112,$B15,'Tabla 2 - Ataques detec (Imple)'!$BI$3:$BI$112) -> 1 | BU15: =SUMIF('Tabla 2 - Ataques detec (Imple)'!$D$3:$D$112,$B15,'Tabla 2 - Ataques detec (Imple)'!$BH$3:$BH$112) -> 186 | BV15: 5560 | BW15: 252 | BX15: =BW15 & " (" & BV15 & ")" -> 252 (5560) | BY15: 51 | BZ15: 1 | CA15: 168 | CB15: 11120 | CC15: 421 | CD15: =CC15 & " (" & CB15 & ")" -> 421 (11120) | CE15: 51 | CF15: 6 | CG15: 1 | CH15: 168
... A17: =A16+1 -> 15 | B17: =IFERROR(VLOOKUP(A17,'Tabla 2 - Ataques detec (Imple)'!$B$3:$D$112,3,FALSE),"") -> T1048 | C17: =IFERROR(VLOOKUP(B17,Techniques!$B$3:$H$213,2,FALSE),"") -> Exfiltration Over Alternative Protocol | D17: =SUMPRODUCT( ('Tabla 2 - Ataques detec (Imple)'!$D$3:$D$112=$B17)* (LEN('Tabla 2 - Ataques detec (Imple)'!$C$3:$C$112)>0) ) -> 2 | E17: =SUMIF('Tabla 2 - Ataques detec (Imple)'!$D$3:$D$112,$B17,'Tabla 2 - Ataques detec (Imple)'!$E$3:$E$112) -> 12 | F17: =D17&" ("&E17&")" -> 2 (12) | G17: =SUMIF('Tabla 2 - Ataques detec (Imple)'!$D$3:$D$112,$B17,'Tabla 2 - Ataques detec (Imple)'!F$3:F$112) -> 2 | H17: =SUMIF('Tabla 2 - Ataques detec (Imple)'!$D$3:$D$112,$B17,'Tabla 2 - Ataques detec (Imple)'!G$3:G$112) -> 1 | I17: =H17 & " (" & G17 & ")" -> 1 (2) | J17: =SUMIF('Tabla 2 - Ataques detec (Imple)'!$D$3:$D$112,$B17,'Tabla 2 - Ataques detec (Imple)'!$H$3:$H$112) -> 1 | K17: =AVERAGEIF('Tabla 2 - Ataques detec (Imple)'!$D$3:$D$112,$B17,'Tabla 2 - Ataques detec (Imple)'!$J$3:$J$112) -> 0.5 | L17: =SUMIF('Tabla 2 - Ataques detec (Imple)'!$D$3:$D$112,$B17,'Tabla 2 - Ataques detec (Imple)'!$I$3:$I$112) -> 1 | M17: =SUMIF('Tabla 2 - Ataques detec (Imple)'!$D$3:$D$112,$B17,'Tabla 2 - Ataques detec (Imple)'!K$3:K$112) -> 0 | N17: =SUMIF('Tabla 2 - Ataques detec (Imple)'!$D$3:$D$112,$B17,'Tabla 2 - Ataques detec (Imple)'!L$3:L$112) -> 0 | O17: =N17 & " (" & M17 & ")" -> 0 (0) | P17: =SUMIF('Tabla 2 - Ataques detec (Imple)'!$D$3:$D$112,$B17,'Tabla 2 - Ataques detec (Imple)'!$M$3:$M$112) -> 0 | Q17: =AVERAGEIF('Tabla 2 - Ataques detec (Imple)'!$D$3:$D$112,$B17,'Tabla 2 - Ataques detec (Imple)'!$O$3:$O$112) -> 0 | R17: =SUMIF('Tabla 2 - Ataques detec (Imple)'!$D$3:$D$112,$B17,'Tabla 2 - Ataques detec (Imple)'!$N$3:$N$112) -> 0 | S17: =SUMIF('Tabla 2 - Ataques detec (Imple)'!$D$3:$D$112,$B17,'Tabla 2 - Ataques detec (Imple)'!P$3:P$112) -> 2 | T17: =SUMIF('Tabla 2 - Ataques detec (Imple)'!$D$3:$D$112,$B17,'Tabla 2 - Ataques detec (Imple)'!Q$3:Q$112) -> 1 | U17: =T17 & " (" & S17 & ")" -> 1 (2) | V17: =SUMIF('Tabla 2 - Ataques detec (Imple)'!$D$3:$D$112,$B17,'Tabla 2 - Ataques detec (Imple)'!$R$3:$R$112) -> 1 | W17: =AVERAGEIF('Tabla 2 - Ataques detec (Imple)'!$D$3:$D$112,$B17,'Tabla 2 - Ataques detec (Imple)'!$T$3:$T$112) -> 0.5 | X17: =SUMIF('Tabla 2 - Ataques detec (Imple)'!$D$3:$D$112,$B17,'Tabla 2 - Ataques detec (Imple)'!$S$3:$S$112) -> 1 | Y17: =SUMIF('Tabla 2 - Ataques detec (Imple)'!$D$3:$D$112,$B17,'Tabla 2 - Ataques detec (Imple)'!U$3:U$112) -> 66 | Z17: =SUMIF('Tabla 2 - Ataques detec (Imple)'!$D$3:$D$112,$B17,'Tabla 2 - Ataques detec (Imple)'!V$3:V$112) -> 5 | AA17: =Z17 & " (" & Y17 & ")" -> 5 (66) | AB17: =SUMIF('Tabla 2 - Ataques detec (Imple)'!$D$3:$D$112,$B17,'Tabla 2 - Ataques detec (Imple)'!$R$3:$R$112) -> 1 | AC17: =AVERAGEIF('Tabla 2 - Ataques detec (Imple)'!$D$3:$D$112,$B17,'Tabla 2 - Ataques detec (Imple)'!$Y$3:$Y$112) -> 1 | AD17: =SUMIF('Tabla 2 - Ataques detec (Imple)'!$D$3:$D$112,$B17,'Tabla 2 - Ataques detec (Imple)'!$X$3:$X$112) -> 2 | AE17: =SUMIF('Tabla 2 - Ataques detec (Imple)'!$D$3:$D$112,$B17,'Tabla 2 - Ataques detec (Imple)'!Z$3:Z$112) -> 51 | AF17: =SUMIF('Tabla 2 - Ataques detec (Imple)'!$D$3:$D$112,$B17,'Tabla 2 - Ataques detec (Imple)'!AA$3:AA$112) -> 12 | AG17: =AF17 & " (" & AE17 & ")" -> 12 (51) | AH17: =SUMIF('Tabla 2 - Ataques detec (Imple)'!$D$3:$D$112,$B17,'Tabla 2 - Ataques detec (Imple)'!$AB$3:$AB$112) -> 10 | AI17: =AVERAGEIF('Tabla 2 - Ataques detec (Imple)'!$D$3:$D$112,$B17,'Tabla 2 - Ataques detec (Imple)'!$AD$3:$AD$112) -> 1 | AJ17: =SUMIF('Tabla 2 - Ataques detec (Imple)'!$D$3:$D$112,$B17,'Tabla 2 - Ataques detec (Imple)'!$AC$3:$AC$112) -> 3 | AK17: =SUMIF('Tabla 2 - Ataques detec (Imple)'!$D$3:$D$112,$B17,'Tabla 2 - Ataques detec (Imple)'!AE$3:AE$112) -> 117 | AL17: =SUMIF('Tabla 2 - Ataques detec (Imple)'!$D$3:$D$112,$B17,'Tabla 2 - Ataques detec (Imple)'!AF$3:AF$112) -> 17 | AM17: =AL17 & " (" & AK17 & ")" -> 17 (117) | AN17: =SUMIF('Tabla 2 - Ataques detec (Imple)'!$D$3:$D$112,$B17,'Tabla 2 - Ataques detec (Imple)'!$AG$3:$AG$112) -> 15 | AO17: =AVERAGEIF('Tabla 2 - Ataques detec (Imple)'!$D$3:$D$112,$B17,'Tabla 2 - Ataques detec (Imple)'!$AI$3:$AI$112) -> 1 | AP17: =SUMIF('Tabla 2 - Ataques detec (Imple)'!$D$3:$D$112,$B17,'Tabla 2 - Ataques detec (Imple)'!$AH$3:$AH$112) -> 3 | AQ17: =SUMIF('Tabla 2 - Ataques detec (Imple)'!$D$3:$D$112,$B17,'Tabla 2 - Ataques detec (Imple)'!AJ$3:AJ$112) -> 0 | AR17: =SUMIF('Tabla 2 - Ataques detec (Imple)'!$D$3:$D$112,$B17,'Tabla 2 - Ataques detec (Imple)'!AK$3:AK$112) -> 0 | AS17: =AR17 & " (" & AQ17 & ")" -> 0 (0) | AT17: =SUMIF('Tabla 2 - Ataques detec (Imple)'!$D$3:$D$112,$B17,'Tabla 2 - Ataques detec (Imple)'!$AL$3:$AL$112) -> 0 | AU17: =AVERAGEIF('Tabla 2 - Ataques detec (Imple)'!$D$3:$D$112,$B17,'Tabla 2 - Ataques detec (Imple)'!$AN$3:$AN$112) -> 0 | AV17: =SUMIF('Tabla 2 - Ataques detec (Imple)'!$D$3:$D$112,$B17,'Tabla 2 - Ataques detec (Imple)'!$AM$3:$AM$112) -> 0 | AW17: =SUMIF('Tabla 2 - Ataques detec (Imple)'!$D$3:$D$112,$B17,'Tabla 2 - Ataques detec (Imple)'!AO$3:AO$112) -> 48 | AX17: =SUMIF('Tabla 2 - Ataques detec (Imple)'!$D$3:$D$112,$B17,'Tabla 2 - Ataques detec (Imple)'!AP$3:AP$112) -> 3 | AY17: =AX17 & " (" & AW17 & ")" -> 3 (48) | AZ17: =SUMIF('Tabla 2 - Ataques detec (Imple)'!$D$3:$D$112,$B17,'Tabla 2 - Ataques detec (Imple)'!$AQ$3:$AQ$112) -> 3 | BA17: =AVERAGEIF('Tabla 2 - Ataques detec (Imple)'!$D$3:$D$112,$B17,'Tabla 2 - Ataques detec (Imple)'!$AS$3:$AS$112) -> 0.5 | BB17: =SUMIF('Tabla 2 - Ataques detec (Imple)'!$D$3:$D$112,$B17,'Tabla 2 - Ataques detec (Imple)'!$AR$3:$AR$112) -> 1 | BC17: =SUMIF('Tabla 2 - Ataques detec (Imple)'!$D$3:$D$112,$B17,'Tabla 2 - Ataques detec (Imple)'!AT$3:AT$112) -> 50 | BD17: =SUMIF('Tabla 2 - Ataques detec (Imple)'!$D$3:$D$112,$B17,'Tabla 2 - Ataques detec (Imple)'!AU$3:AU$112) -> 4 | BE17: =BD17 & " (" & BC17 & ")" -> 4 (50) | BF17: =SUMIF('Tabla 2 - Ataques detec (Imple)'!$D$3:$D$112,$B17,'Tabla 2 - Ataques detec (Imple)'!$AV$3:$AV$112) -> 4 | BG17: =AVERAGEIF('Tabla 2 - Ataques detec (Imple)'!$D$3:$D$112,$B17,'Tabla 2 - Ataques detec (Imple)'!$AX$3:$AX$112) -> 1 | BH17: =SUMIF('Tabla 2 - Ataques detec (Imple)'!$D$3:$D$112,$B17,'Tabla 2 - Ataques detec (Imple)'!$AW$3:$AW$112) -> 2 | BI17: =SUMIF('Tabla 2 - Ataques detec (Imple)'!$D$3:$D$112,$B17,'Tabla 2 - Ataques detec (Imple)'!AY$3:AY$112) -> 0 | BJ17: =SUMIF('Tabla 2 - Ataques detec (Imple)'!$D$3:$D$112,$B17,'Tabla 2 - Ataques detec (Imple)'!AZ$3:AZ$112) -> 0 | BK17: =BJ17 & " (" & BI17 & ")" -> 0 (0) | BL17: =SUMIF('Tabla 2 - Ataques detec (Imple)'!$D$3:$D$112,$B17,'Tabla 2 - Ataques detec (Imple)'!BA$3:BA$112) -> 0 | BM17: =AVERAGEIF('Tabla 2 - Ataques detec (Imple)'!$D$3:$D$112,$B17,'Tabla 2 - Ataques detec (Imple)'!$BC$3:$BC$112) -> 0 | BN17: =SUMIF('Tabla 2 - Ataques detec (Imple)'!$D$3:$D$112,$B17,'Tabla 2 - Ataques detec (Imple)'!$BB$3:$BB$112) -> 0 | BO17: =SUMIF('Tabla 2 - Ataques detec (Imple)'!$D$3:$D$112,$B17,'Tabla 2 - Ataques detec (Imple)'!BD$3:BD$112) -> 9 | BP17: =SUMIF('Tabla 2 - Ataques detec (Imple)'!$D$3:$D$112,$B17,'Tabla 2 - Ataques detec (Imple)'!BE$3:BE$112) -> 3 | BQ17: =BP17 & " (" & BO17 & ")" -> 3 (9) | BR17: =SUMIF('Tabla 2 - Ataques detec (Imple)'!$D$3:$D$112,$B17,'Tabla 2 - Ataques detec (Imple)'!BF$3:BF$112) -> 0 | BS17: =SUMIF('Tabla 2 - Ataques detec (Imple)'!$D$3:$D$112,$B17,'Tabla 2 - Ataques detec (Imple)'!BG$3:BG$112) -> 3 | BT17: =AVERAGEIF('Tabla 2 - Ataques detec (Imple)'!$D$3:$D$112,$B17,'Tabla 2 - Ataques detec (Imple)'!$BI$3:$BI$112) -> 1 | BU17: =SUMIF('Tabla 2 - Ataques detec (Imple)'!$D$3:$D$112,$B17,'Tabla 2 - Ataques detec (Imple)'!$BH$3:$BH$112) -> 3 | BV17: 0 | BW17: 0 | BX17: =BW17 & " (" & BV17 & ")" -> 0 (0) | BY17: 0 | BZ17: 0 | CA17: 0 | CB17: 0 | CC17: 0 | CD17: =CC17 & " (" & CB17 & ")" -> 0 (0) | CE17: 0 | CF17: 0 | CG17: 0 | CH17: 0
A18: =A17+1 -> 16 | B18: =IFERROR(VLOOKUP(A18,'Tabla 2 - Ataques detec (Imple)'!$B$3:$D$112,3,FALSE),"") -> T1053 | C18: =IFERROR(VLOOKUP(B18,Techniques!$B$3:$H$213,2,FALSE),"") -> Scheduled Task/Job | D18: =SUMPRODUCT( ('Tabla 2 - Ataques detec (Imple)'!$D$3:$D$112=$B18)* (LEN('Tabla 2 - Ataques detec (Imple)'!$C$3:$C$112)>0) ) -> 1 | E18: =SUMIF('Tabla 2 - Ataques detec (Imple)'!$D$3:$D$112,$B18,'Tabla 2 - Ataques detec (Imple)'!$E$3:$E$112) -> 2 | F18: =D18&" ("&E18&")" -> 1 (2) | G18: =SUMIF('Tabla 2 - Ataques detec (Imple)'!$D$3:$D$112,$B18,'Tabla 2 - Ataques detec (Imple)'!F$3:F$112) -> 1 | H18: =SUMIF('Tabla 2 - Ataques detec (Imple)'!$D$3:$D$112,$B18,'Tabla 2 - Ataques detec (Imple)'!G$3:G$112) -> 1 | I18: =H18 & " (" & G18 & ")" -> 1 (1) | J18: =SUMIF('Tabla 2 - Ataques detec (Imple)'!$D$3:$D$112,$B18,'Tabla 2 - Ataques detec (Imple)'!$H$3:$H$112) -> 1 | K18: =AVERAGEIF('Tabla 2 - Ataques detec (Imple)'!$D$3:$D$112,$B18,'Tabla 2 - Ataques detec (Imple)'!$J$3:$J$112) -> 1 | L18: =SUMIF('Tabla 2 - Ataques detec (Imple)'!$D$3:$D$112,$B18,'Tabla 2 - Ataques detec (Imple)'!$I$3:$I$112) -> 1 | M18: =SUMIF('Tabla 2 - Ataques detec (Imple)'!$D$3:$D$112,$B18,'Tabla 2 - Ataques detec (Imple)'!K$3:K$112) -> 14 | N18: =SUMIF('Tabla 2 - Ataques detec (Imple)'!$D$3:$D$112,$B18,'Tabla 2 - Ataques detec (Imple)'!L$3:L$112) -> 4 | O18: =N18 & " (" & M18 & ")" -> 4 (14) | P18: =SUMIF('Tabla 2 - Ataques detec (Imple)'!$D$3:$D$112,$B18,'Tabla 2 - Ataques detec (Imple)'!$M$3:$M$112) -> 4 | Q18: =AVERAGEIF('Tabla 2 - Ataques detec (Imple)'!$D$3:$D$112,$B18,'Tabla 2 - Ataques detec (Imple)'!$O$3:$O$112) -> 1 | R18: =SUMIF('Tabla 2 - Ataques detec (Imple)'!$D$3:$D$112,$B18,'Tabla 2 - Ataques detec (Imple)'!$N$3:$N$112) -> 2 | S18: =SUMIF('Tabla 2 - Ataques detec (Imple)'!$D$3:$D$112,$B18,'Tabla 2 - Ataques detec (Imple)'!P$3:P$112) -> 15 | T18: =SUMIF('Tabla 2 - Ataques detec (Imple)'!$D$3:$D$112,$B18,'Tabla 2 - Ataques detec (Imple)'!Q$3:Q$112) -> 5 | U18: =T18 & " (" & S18 & ")" -> 5 (15) | V18: =SUMIF('Tabla 2 - Ataques detec (Imple)'!$D$3:$D$112,$B18,'Tabla 2 - Ataques detec (Imple)'!$R$3:$R$112) -> 5 | W18: =AVERAGEIF('Tabla 2 - Ataques detec (Imple)'!$D$3:$D$112,$B18,'Tabla 2 - Ataques detec (Imple)'!$T$3:$T$112) -> 1 | X18: =SUMIF('Tabla 2 - Ataques detec (Imple)'!$D$3:$D$112,$B18,'Tabla 2 - Ataques detec (Imple)'!$S$3:$S$112) -> 2 | Y18: =SUMIF('Tabla 2 - Ataques detec (Imple)'!$D$3:$D$112,$B18,'Tabla 2 - Ataques detec (Imple)'!U$3:U$112) -> 25 | Z18: =SUMIF('Tabla 2 - Ataques detec (Imple)'!$D$3:$D$112,$B18,'Tabla 2 - Ataques detec (Imple)'!V$3:V$112) -> 8 | AA18: =Z18 & " (" & Y18 & ")" -> 8 (25) | AB18: =SUMIF('Tabla 2 - Ataques detec (Imple)'!$D$3:$D$112,$B18,'Tabla 2 - Ataques detec (Imple)'!$R$3:$R$112) -> 5 | AC18: =AVERAGEIF('Tabla 2 - Ataques detec (Imple)'!$D$3:$D$112,$B18,'Tabla 2 - Ataques detec (Imple)'!$Y$3:$Y$112) -> 1 | AD18: =SUMIF('Tabla 2 - Ataques detec (Imple)'!$D$3:$D$112,$B18,'Tabla 2 - Ataques detec (Imple)'!$X$3:$X$112) -> 2 | AE18: =SUMIF('Tabla 2 - Ataques detec (Imple)'!$D$3:$D$112,$B18,'Tabla 2 - Ataques detec (Imple)'!Z$3:Z$112) -> 52 | AF18: =SUMIF('Tabla 2 - Ataques detec (Imple)'!$D$3:$D$112,$B18,'Tabla 2 - Ataques detec (Imple)'!AA$3:AA$112) -> 15 | AG18: =AF18 & " (" & AE18 & ")" -> 15 (52) | AH18: =SUMIF('Tabla 2 - Ataques detec (Imple)'!$D$3:$D$112,$B18,'Tabla 2 - Ataques detec (Imple)'!$AB$3:$AB$112) -> 12 | AI18: =AVERAGEIF('Tabla 2 - Ataques detec (Imple)'!$D$3:$D$112,$B18,'Tabla 2 - Ataques detec (Imple)'!$AD$3:$AD$112) -> 1 | AJ18: =SUMIF('Tabla 2 - Ataques detec (Imple)'!$D$3:$D$112,$B18,'Tabla 2 - Ataques detec (Imple)'!$AC$3:$AC$112) -> 2 | AK18: =SUMIF('Tabla 2 - Ataques detec (Imple)'!$D$3:$D$112,$B18,'Tabla 2 - Ataques detec (Imple)'!AE$3:AE$112) -> 77 | AL18: =SUMIF('Tabla 2 - Ataques detec (Imple)'!$D$3:$D$112,$B18,'Tabla 2 - Ataques detec (Imple)'!AF$3:AF$112) -> 23 | AM18: =AL18 & " (" & AK18 & ")" -> 23 (77) | AN18: =SUMIF('Tabla 2 - Ataques detec (Imple)'!$D$3:$D$112,$B18,'Tabla 2 - Ataques detec (Imple)'!$AG$3:$AG$112) -> 19 | AO18: =AVERAGEIF('Tabla 2 - Ataques detec (Imple)'!$D$3:$D$112,$B18,'Tabla 2 - Ataques detec (Imple)'!$AI$3:$AI$112) -> 1 | AP18: =SUMIF('Tabla 2 - Ataques detec (Imple)'!$D$3:$D$112,$B18,'Tabla 2 - Ataques detec (Imple)'!$AH$3:$AH$112) -> 2 | AQ18: =SUMIF('Tabla 2 - Ataques detec (Imple)'!$D$3:$D$112,$B18,'Tabla 2 - Ataques detec (Imple)'!AJ$3:AJ$112) -> 0 | AR18: =SUMIF('Tabla 2 - Ataques detec (Imple)'!$D$3:$D$112,$B18,'Tabla 2 - Ataques detec (Imple)'!AK$3:AK$112) -> 0 | AS18: =AR18 & " (" & AQ18 & ")" -> 0 (0) | AT18: =SUMIF('Tabla 2 - Ataques detec (Imple)'!$D$3:$D$112,$B18,'Tabla 2 - Ataques detec (Imple)'!$AL$3:$AL$112) -> 0 | AU18: =AVERAGEIF('Tabla 2 - Ataques detec (Imple)'!$D$3:$D$112,$B18,'Tabla 2 - Ataques detec (Imple)'!$AN$3:$AN$112) -> 0 | AV18: =SUMIF('Tabla 2 - Ataques detec (Imple)'!$D$3:$D$112,$B18,'Tabla 2 - Ataques detec (Imple)'!$AM$3:$AM$112) -> 0 | AW18: =SUMIF('Tabla 2 - Ataques detec (Imple)'!$D$3:$D$112,$B18,'Tabla 2 - Ataques detec (Imple)'!AO$3:AO$112) -> 5 | AX18: =SUMIF('Tabla 2 - Ataques detec (Imple)'!$D$3:$D$112,$B18,'Tabla 2 - Ataques detec (Imple)'!AP$3:AP$112) -> 3 | AY18: =AX18 & " (" & AW18 & ")" -> 3 (5) | AZ18: =SUMIF('Tabla 2 - Ataques detec (Imple)'!$D$3:$D$112,$B18,'Tabla 2 - Ataques detec (Imple)'!$AQ$3:$AQ$112) -> 3 | BA18: =AVERAGEIF('Tabla 2 - Ataques detec (Imple)'!$D$3:$D$112,$B18,'Tabla 2 - Ataques detec (Imple)'!$AS$3:$AS$112) -> 1 | BB18: =SUMIF('Tabla 2 - Ataques detec (Imple)'!$D$3:$D$112,$B18,'Tabla 2 - Ataques detec (Imple)'!$AR$3:$AR$112) -> 1 | BC18: =SUMIF('Tabla 2 - Ataques detec (Imple)'!$D$3:$D$112,$B18,'Tabla 2 - Ataques detec (Imple)'!AT$3:AT$112) -> 20 | BD18: =SUMIF('Tabla 2 - Ataques detec (Imple)'!$D$3:$D$112,$B18,'Tabla 2 - Ataques detec (Imple)'!AU$3:AU$112) -> 8 | BE18: =BD18 & " (" & BC18 & ")" -> 8 (20) | BF18: =SUMIF('Tabla 2 - Ataques detec (Imple)'!$D$3:$D$112,$B18,'Tabla 2 - Ataques detec (Imple)'!$AV$3:$AV$112) -> 8 | BG18: =AVERAGEIF('Tabla 2 - Ataques detec (Imple)'!$D$3:$D$112,$B18,'Tabla 2 - Ataques detec (Imple)'!$AX$3:$AX$112) -> 1 | BH18: =SUMIF('Tabla 2 - Ataques detec (Imple)'!$D$3:$D$112,$B18,'Tabla 2 - Ataques detec (Imple)'!$AW$3:$AW$112) -> 2 | BI18: =SUMIF('Tabla 2 - Ataques detec (Imple)'!$D$3:$D$112,$B18,'Tabla 2 - Ataques detec (Imple)'!AY$3:AY$112) -> 4 | BJ18: =SUMIF('Tabla 2 - Ataques detec (Imple)'!$D$3:$D$112,$B18,'Tabla 2 - Ataques detec (Imple)'!AZ$3:AZ$112) -> 3 | BK18: =BJ18 & " (" & BI18 & ")" -> 3 (4) | BL18: =SUMIF('Tabla 2 - Ataques detec (Imple)'!$D$3:$D$112,$B18,'Tabla 2 - Ataques detec (Imple)'!BA$3:BA$112) -> 2 | BM18: =AVERAGEIF('Tabla 2 - Ataques detec (Imple)'!$D$3:$D$112,$B18,'Tabla 2 - Ataques detec (Imple)'!$BC$3:$BC$112) -> 1 | BN18: 2 | BO18: =SUMIF('Tabla 2 - Ataques detec (Imple)'!$D$3:$D$112,$B18,'Tabla 2 - Ataques detec (Imple)'!BD$3:BD$112) -> 6 | BP18: =SUMIF('Tabla 2 - Ataques detec (Imple)'!$D$3:$D$112,$B18,'Tabla 2 - Ataques detec (Imple)'!BE$3:BE$112) -> 5 | BQ18: =BP18 & " (" & BO18 & ")" -> 5 (6) | BR18: =SUMIF('Tabla 2 - Ataques detec (Imple)'!$D$3:$D$112,$B18,'Tabla 2 - Ataques detec (Imple)'!BF$3:BF$112) -> 2 | BS18: =SUMIF('Tabla 2 - Ataques detec (Imple)'!$D$3:$D$112,$B18,'Tabla 2 - Ataques detec (Imple)'!BG$3:BG$112) -> 1 | BT18: =AVERAGEIF('Tabla 2 - Ataques detec (Imple)'!$D$3:$D$112,$B18,'Tabla 2 - Ataques detec (Imple)'!$BI$3:$BI$112) -> 1 | BU18: 2 | BV18: 12 | BW18: 2 | BX18: =BW18 & " (" & BV18 & ")" -> 2 (12) | BY18: 2 | BZ18: 1 | CA18: 1 | CB18: 24 | CC18: 3 | CD18: =CC18 & " (" & CB18 & ")" -> 3 (24) | CE18: 2 | CF18: 1 | CG18: 1 | CH18: 1
A19: =A18+1 -> 17 | B19: =IFERROR(VLOOKUP(A19,'Tabla 2 - Ataques detec (Imple)'!$B$3:$D$112,3,FALSE),"") -> T1070 | C19: =IFERROR(VLOOKUP(B19,Techniques!$B$3:$H$213,2,FALSE),"") -> Indicator Removal | D19: =SUMPRODUCT( ('Tabla 2 - Ataques detec (Imple)'!$D$3:$D$112=$B19)* (LEN('Tabla 2 - Ataques detec (Imple)'!$C$3:$C$112)>0) ) -> 1 | E19: =SUMIF('Tabla 2 - Ataques detec (Imple)'!$D$3:$D$112,$B19,'Tabla 2 - Ataques detec (Imple)'!$E$3:$E$112) -> 1 | F19: =D19&" ("&E19&")" -> 1 (1) | G19: =SUMIF('Tabla 2 - Ataques detec (Imple)'!$D$3:$D$112,$B19,'Tabla 2 - Ataques detec (Imple)'!F$3:F$112) -> 0 | H19: =SUMIF('Tabla 2 - Ataques detec (Imple)'!$D$3:$D$112,$B19,'Tabla 2 - Ataques detec (Imple)'!G$3:G$112) -> 0 | I19: =H19 & " (" & G19 & ")" -> 0 (0) | J19: =SUMIF('Tabla 2 - Ataques detec (Imple)'!$D$3:$D$112,$B19,'Tabla 2 - Ataques detec (Imple)'!$H$3:$H$112) -> 0 | K19: =AVERAGEIF('Tabla 2 - Ataques detec (Imple)'!$D$3:$D$112,$B19,'Tabla 2 - Ataques detec (Imple)'!$J$3:$J$112) -> 0 | L19: =SUMIF('Tabla 2 - Ataques detec (Imple)'!$D$3:$D$112,$B19,'Tabla 2 - Ataques detec (Imple)'!$I$3:$I$112) -> 0 | M19: =SUMIF('Tabla 2 - Ataques detec (Imple)'!$D$3:$D$112,$B19,'Tabla 2 - Ataques detec (Imple)'!K$3:K$112) -> 0 | N19: =SUMIF('Tabla 2 - Ataques detec (Imple)'!$D$3:$D$112,$B19,'Tabla 2 - Ataques detec (Imple)'!L$3:L$112) -> 0 | O19: =N19 & " (" & M19 & ")" -> 0 (0) | P19: =SUMIF('Tabla 2 - Ataques detec (Imple)'!$D$3:$D$112,$B19,'Tabla 2 - Ataques detec (Imple)'!$M$3:$M$112) -> 0 | Q19: =AVERAGEIF('Tabla 2 - Ataques detec (Imple)'!$D$3:$D$112,$B19,'Tabla 2 - Ataques detec (Imple)'!$O$3:$O$112) -> 0 | R19: =SUMIF('Tabla 2 - Ataques detec (Imple)'!$D$3:$D$112,$B19,'Tabla 2 - Ataques detec (Imple)'!$N$3:$N$112) -> 0 | S19: =SUMIF('Tabla 2 - Ataques detec (Imple)'!$D$3:$D$112,$B19,'Tabla 2 - Ataques detec (Imple)'!P$3:P$112) -> 0 | T19: =SUMIF('Tabla 2 - Ataques detec (Imple)'!$D$3:$D$112,$B19,'Tabla 2 - Ataques detec (Imple)'!Q$3:Q$112) -> 0 | U19: =T19 & " (" & S19 & ")" -> 0 (0) | V19: =SUMIF('Tabla 2 - Ataques detec (Imple)'!$D$3:$D$112,$B19,'Tabla 2 - Ataques detec (Imple)'!$R$3:$R$112) -> 0 | W19: =AVERAGEIF('Tabla 2 - Ataques detec (Imple)'!$D$3:$D$112,$B19,'Tabla 2 - Ataques detec (Imple)'!$T$3:$T$112) -> 0 | X19: =SUMIF('Tabla 2 - Ataques detec (Imple)'!$D$3:$D$112,$B19,'Tabla 2 - Ataques detec (Imple)'!$S$3:$S$112) -> 0 | Y19: =SUMIF('Tabla 2 - Ataques detec (Imple)'!$D$3:$D$112,$B19,'Tabla 2 - Ataques detec (Imple)'!U$3:U$112) -> 0 | Z19: =SUMIF('Tabla 2 - Ataques detec (Imple)'!$D$3:$D$112,$B19,'Tabla 2 - Ataques detec (Imple)'!V$3:V$112) -> 0 | AA19: =Z19 & " (" & Y19 & ")" -> 0 (0) | AB19: =SUMIF('Tabla 2 - Ataques detec (Imple)'!$D$3:$D$112,$B19,'Tabla 2 - Ataques detec (Imple)'!$R$3:$R$112) -> 0 | AC19: =AVERAGEIF('Tabla 2 - Ataques detec (Imple)'!$D$3:$D$112,$B19,'Tabla 2 - Ataques detec (Imple)'!$Y$3:$Y$112) -> 0 | AD19: =SUMIF('Tabla 2 - Ataques detec (Imple)'!$D$3:$D$112,$B19,'Tabla 2 - Ataques detec (Imple)'!$X$3:$X$112) -> 0 | AE19: =SUMIF('Tabla 2 - Ataques detec (Imple)'!$D$3:$D$112,$B19,'Tabla 2 - Ataques detec (Imple)'!Z$3:Z$112) -> 11 | AF19: =SUMIF('Tabla 2 - Ataques detec (Imple)'!$D$3:$D$112,$B19,'Tabla 2 - Ataques detec (Imple)'!AA$3:AA$112) -> 11 | AG19: =AF19 & " (" & AE19 & ")" -> 11 (11) | AH19: =SUMIF('Tabla 2 - Ataques detec (Imple)'!$D$3:$D$112,$B19,'Tabla 2 - Ataques detec (Imple)'!$AB$3:$AB$112) -> 11 | AI19: =AVERAGEIF('Tabla 2 - Ataques detec (Imple)'!$D$3:$D$112,$B19,'Tabla 2 - Ataques detec (Imple)'!$AD$3:$AD$112) -> 1 | AJ19: =SUMIF('Tabla 2 - Ataques detec (Imple)'!$D$3:$D$112,$B19,'Tabla 2 - Ataques detec (Imple)'!$AC$3:$AC$112) -> 1 | AK19: =SUMIF('Tabla 2 - Ataques detec (Imple)'!$D$3:$D$112,$B19,'Tabla 2 - Ataques detec (Imple)'!AE$3:AE$112) -> 11 | AL19: =SUMIF('Tabla 2 - Ataques detec (Imple)'!$D$3:$D$112,$B19,'Tabla 2 - Ataques detec (Imple)'!AF$3:AF$112) -> 11 | AM19: =AL19 & " (" & AK19 & ")" -> 11 (11) | AN19: =SUMIF('Tabla 2 - Ataques detec (Imple)'!$D$3:$D$112,$B19,'Tabla 2 - Ataques detec (Imple)'!$AG$3:$AG$112) -> 11 | AO19: =AVERAGEIF('Tabla 2 - Ataques detec (Imple)'!$D$3:$D$112,$B19,'Tabla 2 - Ataques detec (Imple)'!$AI$3:$AI$112) -> 1 | AP19: =SUMIF('Tabla 2 - Ataques detec (Imple)'!$D$3:$D$112,$B19,'Tabla 2 - Ataques detec (Imple)'!$AH$3:$AH$112) -> 1 | AQ19: =SUMIF('Tabla 2 - Ataques detec (Imple)'!$D$3:$D$112,$B19,'Tabla 2 - Ataques detec (Imple)'!AJ$3:AJ$112) -> 0 | AR19: =SUMIF('Tabla 2 - Ataques detec (Imple)'!$D$3:$D$112,$B19,'Tabla 2 - Ataques detec (Imple)'!AK$3:AK$112) -> 0 | AS19: =AR19 & " (" & AQ19 & ")" -> 0 (0) | AT19: =SUMIF('Tabla 2 - Ataques detec (Imple)'!$D$3:$D$112,$B19,'Tabla 2 - Ataques detec (Imple)'!$AL$3:$AL$112) -> 0 | AU19: =AVERAGEIF('Tabla 2 - Ataques detec (Imple)'!$D$3:$D$112,$B19,'Tabla 2 - Ataques detec (Imple)'!$AN$3:$AN$112) -> 0 | AV19: =SUMIF('Tabla 2 - Ataques detec (Imple)'!$D$3:$D$112,$B19,'Tabla 2 - Ataques detec (Imple)'!$AM$3:$AM$112) -> 0 | AW19: =SUMIF('Tabla 2 - Ataques detec (Imple)'!$D$3:$D$112,$B19,'Tabla 2 - Ataques detec (Imple)'!AO$3:AO$112) -> 0 | AX19: =SUMIF('Tabla 2 - Ataques detec (Imple)'!$D$3:$D$112,$B19,'Tabla 2 - Ataques detec (Imple)'!AP$3:AP$112) -> 0 | AY19: =AX19 & " (" & AW19 & ")" -> 0 (0) | AZ19: =SUMIF('Tabla 2 - Ataques detec (Imple)'!$D$3:$D$112,$B19,'Tabla 2 - Ataques detec (Imple)'!$AQ$3:$AQ$112) -> 0 | BA19: =AVERAGEIF('Tabla 2 - Ataques detec (Imple)'!$D$3:$D$112,$B19,'Tabla 2 - Ataques detec (Imple)'!$AS$3:$AS$112) -> 0 | BB19: =SUMIF('Tabla 2 - Ataques detec (Imple)'!$D$3:$D$112,$B19,'Tabla 2 - Ataques detec (Imple)'!$AR$3:$AR$112) -> 0 | BC19: =SUMIF('Tabla 2 - Ataques detec (Imple)'!$D$3:$D$112,$B19,'Tabla 2 - Ataques detec (Imple)'!AT$3:AT$112) -> 0 | BD19: =SUMIF('Tabla 2 - Ataques detec (Imple)'!$D$3:$D$112,$B19,'Tabla 2 - Ataques detec (Imple)'!AU$3:AU$112) -> 0 | BE19: =BD19 & " (" & BC19 & ")" -> 0 (0) | BF19: =SUMIF('Tabla 2 - Ataques detec (Imple)'!$D$3:$D$112,$B19,'Tabla 2 - Ataques detec (Imple)'!$AV$3:$AV$112) -> 0 | BG19: =AVERAGEIF('Tabla 2 - Ataques detec (Imple)'!$D$3:$D$112,$B19,'Tabla 2 - Ataques detec (Imple)'!$AX$3:$AX$112) -> 0 | BH19: =SUMIF('Tabla 2 - Ataques detec (Imple)'!$D$3:$D$112,$B19,'Tabla 2 - Ataques detec (Imple)'!$AW$3:$AW$112) -> 0 | BI19: =SUMIF('Tabla 2 - Ataques detec (Imple)'!$D$3:$D$112,$B19,'Tabla 2 - Ataques detec (Imple)'!AY$3:AY$112) -> 0 | BJ19: =SUMIF('Tabla 2 - Ataques detec (Imple)'!$D$3:$D$112,$B19,'Tabla 2 - Ataques detec (Imple)'!AZ$3:AZ$112) -> 0 | BK19: =BJ19 & " (" & BI19 & ")" -> 0 (0) | BL19: =SUMIF('Tabla 2 - Ataques detec (Imple)'!$D$3:$D$112,$B19,'Tabla 2 - Ataques detec (Imple)'!BA$3:BA$112) -> 0 | BM19: =AVERAGEIF('Tabla 2 - Ataques detec (Imple)'!$D$3:$D$112,$B19,'Tabla 2 - Ataques detec (Imple)'!$BC$3:$BC$112) -> 0 | BN19: =SUMIF('Tabla 2 - Ataques detec (Imple)'!$D$3:$D$112,$B19,'Tabla 2 - Ataques detec (Imple)'!$BB$3:$BB$112) -> 0 | BO19: =SUMIF('Tabla 2 - Ataques detec (Imple)'!$D$3:$D$112,$B19,'Tabla 2 - Ataques detec (Imple)'!BD$3:BD$112) -> 5 | BP19: =SUMIF('Tabla 2 - Ataques detec (Imple)'!$D$3:$D$112,$B19,'Tabla 2 - Ataques detec (Imple)'!BE$3:BE$112) -> 4 | BQ19: =BP19 & " (" & BO19 & ")" -> 4 (5) | BR19: =SUMIF('Tabla 2 - Ataques detec (Imple)'!$D$3:$D$112,$B19,'Tabla 2 - Ataques detec (Imple)'!BF$3:BF$112) -> 0 | BS19: =SUMIF('Tabla 2 - Ataques detec (Imple)'!$D$3:$D$112,$B19,'Tabla 2 - Ataques detec (Imple)'!BG$3:BG$112) -> 4 | BT19: =AVERAGEIF('Tabla 2 - Ataques detec (Imple)'!$D$3:$D$112,$B19,'Tabla 2 - Ataques detec (Imple)'!$BI$3:$BI$112) -> 1 | BU19: =SUMIF('Tabla 2 - Ataques detec (Imple)'!$D$3:$D$112,$B19,'Tabla 2 - Ataques detec (Imple)'!$BH$3:$BH$112) -> 1 | BV19: 1 | BW19: 1 | BX19: =BW19 & " (" & BV19 & ")" -> 1 (1) | BY19: 1 | BZ19: 1 | CA19: 1 | CB19: 2 | CC19: 2 | CD19: =CC19 & " (" & CB19 & ")" -> 2 (2) | CE19: 1 | CF19: 1 | CG19: 1 | CH19: 1
A20: =A19+1 -> 18 | B20: =IFERROR(VLOOKUP(A20,'Tabla 2 - Ataques detec (Imple)'!$B$3:$D$112,3,FALSE),"") -> T1071 | C20: =IFERROR(VLOOKUP(B20,Techniques!$B$3:$H$213,2,FALSE),"") -> Application Layer Protocol | D20: =SUMPRODUCT( ('Tabla 2 - Ataques detec (Imple)'!$D$3:$D$112=$B20)* (LEN('Tabla 2 - Ataques detec (Imple)'!$C$3:$C$112)>0) ) -> 1 | E20: =SUMIF('Tabla 2 - Ataques detec (Imple)'!$D$3:$D$112,$B20,'Tabla 2 - Ataques detec (Imple)'!$E$3:$E$112) -> 198 | F20: =D20&" ("&E20&")" -> 1 (198) | G20: =SUMIF('Tabla 2 - Ataques detec (Imple)'!$D$3:$D$112,$B20,'Tabla 2 - Ataques detec (Imple)'!F$3:F$112) -> 204 | H20: =SUMIF('Tabla 2 - Ataques detec (Imple)'!$D$3:$D$112,$B20,'Tabla 2 - Ataques detec (Imple)'!G$3:G$112) -> 10 | I20: =H20 & " (" & G20 & ")" -> 10 (204) | J20: =SUMIF('Tabla 2 - Ataques detec (Imple)'!$D$3:$D$112,$B20,'Tabla 2 - Ataques detec (Imple)'!$H$3:$H$112) -> 1 | K20: =AVERAGEIF('Tabla 2 - Ataques detec (Imple)'!$D$3:$D$112,$B20,'Tabla 2 - Ataques detec (Imple)'!$J$3:$J$112) -> 1 | L20: =SUMIF('Tabla 2 - Ataques detec (Imple)'!$D$3:$D$112,$B20,'Tabla 2 - Ataques detec (Imple)'!$I$3:$I$112) -> 10 | M20: =SUMIF('Tabla 2 - Ataques detec (Imple)'!$D$3:$D$112,$B20,'Tabla 2 - Ataques detec (Imple)'!K$3:K$112) -> 0 | N20: =SUMIF('Tabla 2 - Ataques detec (Imple)'!$D$3:$D$112,$B20,'Tabla 2 - Ataques detec (Imple)'!L$3:L$112) -> 0 | O20: =N20 & " (" & M20 & ")" -> 0 (0) | P20: =SUMIF('Tabla 2 - Ataques detec (Imple)'!$D$3:$D$112,$B20,'Tabla 2 - Ataques detec (Imple)'!$M$3:$M$112) -> 0 | Q20: =AVERAGEIF('Tabla 2 - Ataques detec (Imple)'!$D$3:$D$112,$B20,'Tabla 2 - Ataques detec (Imple)'!$O$3:$O$112) -> 0 | R20: =SUMIF('Tabla 2 - Ataques detec (Imple)'!$D$3:$D$112,$B20,'Tabla 2 - Ataques detec (Imple)'!$N$3:$N$112) -> 0 | S20: =SUMIF('Tabla 2 - Ataques detec (Imple)'!$D$3:$D$112,$B20,'Tabla 2 - Ataques detec (Imple)'!P$3:P$112) -> 204 | T20: =SUMIF('Tabla 2 - Ataques detec (Imple)'!$D$3:$D$112,$B20,'Tabla 2 - Ataques detec (Imple)'!Q$3:Q$112) -> 10 | U20: =T20 & " (" & S20 & ")" -> 10 (204) | V20: =SUMIF('Tabla 2 - Ataques detec (Imple)'!$D$3:$D$112,$B20,'Tabla 2 - Ataques detec (Imple)'!$R$3:$R$112) -> 1 | W20: =AVERAGEIF('Tabla 2 - Ataques detec (Imple)'!$D$3:$D$112,$B20,'Tabla 2 - Ataques detec (Imple)'!$T$3:$T$112) -> 1 | X20: =SUMIF('Tabla 2 - Ataques detec (Imple)'!$D$3:$D$112,$B20,'Tabla 2 - Ataques detec (Imple)'!$S$3:$S$112) -> 10 | Y20: =SUMIF('Tabla 2 - Ataques detec (Imple)'!$D$3:$D$112,$B20,'Tabla 2 - Ataques detec (Imple)'!U$3:U$112) -> 205 | Z20: =SUMIF('Tabla 2 - Ataques detec (Imple)'!$D$3:$D$112,$B20,'Tabla 2 - Ataques detec (Imple)'!V$3:V$112) -> 11 | AA20: =Z20 & " (" & Y20 & ")" -> 11 (205) | AB20: =SUMIF('Tabla 2 - Ataques detec (Imple)'!$D$3:$D$112,$B20,'Tabla 2 - Ataques detec (Imple)'!$R$3:$R$112) -> 1 | AC20: =AVERAGEIF('Tabla 2 - Ataques detec (Imple)'!$D$3:$D$112,$B20,'Tabla 2 - Ataques detec (Imple)'!$Y$3:$Y$112) -> 1 | AD20: =SUMIF('Tabla 2 - Ataques detec (Imple)'!$D$3:$D$112,$B20,'Tabla 2 - Ataques detec (Imple)'!$X$3:$X$112) -> 11 | AE20: =SUMIF('Tabla 2 - Ataques detec (Imple)'!$D$3:$D$112,$B20,'Tabla 2 - Ataques detec (Imple)'!Z$3:Z$112) -> 106 | AF20: =SUMIF('Tabla 2 - Ataques detec (Imple)'!$D$3:$D$112,$B20,'Tabla 2 - Ataques detec (Imple)'!AA$3:AA$112) -> 105 | AG20: =AF20 & " (" & AE20 & ")" -> 105 (106) | AH20: =SUMIF('Tabla 2 - Ataques detec (Imple)'!$D$3:$D$112,$B20,'Tabla 2 - Ataques detec (Imple)'!$AB$3:$AB$112) -> 5 | AI20: =AVERAGEIF('Tabla 2 - Ataques detec (Imple)'!$D$3:$D$112,$B20,'Tabla 2 - Ataques detec (Imple)'!$AD$3:$AD$112) -> 1 | AJ20: =SUMIF('Tabla 2 - Ataques detec (Imple)'!$D$3:$D$112,$B20,'Tabla 2 - Ataques detec (Imple)'!$AC$3:$AC$112) -> 100 | AK20: =SUMIF('Tabla 2 - Ataques detec (Imple)'!$D$3:$D$112,$B20,'Tabla 2 - Ataques detec (Imple)'!AE$3:AE$112) -> 311 | AL20: =SUMIF('Tabla 2 - Ataques detec (Imple)'!$D$3:$D$112,$B20,'Tabla 2 - Ataques detec (Imple)'!AF$3:AF$112) -> 116 | AM20: =AL20 & " (" & AK20 & ")" -> 116 (311) | AN20: =SUMIF('Tabla 2 - Ataques detec (Imple)'!$D$3:$D$112,$B20,'Tabla 2 - Ataques detec (Imple)'!$AG$3:$AG$112) -> 7 | AO20: =AVERAGEIF('Tabla 2 - Ataques detec (Imple)'!$D$3:$D$112,$B20,'Tabla 2 - Ataques detec (Imple)'!$AI$3:$AI$112) -> 1 | AP20: =SUMIF('Tabla 2 - Ataques detec (Imple)'!$D$3:$D$112,$B20,'Tabla 2 - Ataques detec (Imple)'!$AH$3:$AH$112) -> 107 | AQ20: =SUMIF('Tabla 2 - Ataques detec (Imple)'!$D$3:$D$112,$B20,'Tabla 2 - Ataques detec (Imple)'!AJ$3:AJ$112) -> 0 | AR20: =SUMIF('Tabla 2 - Ataques detec (Imple)'!$D$3:$D$112,$B20,'Tabla 2 - Ataques detec (Imple)'!AK$3:AK$112) -> 0 | AS20: =AR20 & " (" & AQ20 & ")" -> 0 (0) | AT20: =SUMIF('Tabla 2 - Ataques detec (Imple)'!$D$3:$D$112,$B20,'Tabla 2 - Ataques detec (Imple)'!$AL$3:$AL$112) -> 0 | AU20: =AVERAGEIF('Tabla 2 - Ataques detec (Imple)'!$D$3:$D$112,$B20,'Tabla 2 - Ataques detec (Imple)'!$AN$3:$AN$112) -> 0 | AV20: =SUMIF('Tabla 2 - Ataques detec (Imple)'!$D$3:$D$112,$B20,'Tabla 2 - Ataques detec (Imple)'!$AM$3:$AM$112) -> 0 | AW20: =SUMIF('Tabla 2 - Ataques detec (Imple)'!$D$3:$D$112,$B20,'Tabla 2 - Ataques detec (Imple)'!AO$3:AO$112) -> 0 | AX20: =SUMIF('Tabla 2 - Ataques detec (Imple)'!$D$3:$D$112,$B20,'Tabla 2 - Ataques detec (Imple)'!AP$3:AP$112) -> 0 | AY20: =AX20 & " (" & AW20 & ")" -> 0 (0) | AZ20: =SUMIF('Tabla 2 - Ataques detec (Imple)'!$D$3:$D$112,$B20,'Tabla 2 - Ataques detec (Imple)'!$AQ$3:$AQ$112) -> 0 | BA20: =AVERAGEIF('Tabla 2 - Ataques detec (Imple)'!$D$3:$D$112,$B20,'Tabla 2 - Ataques detec (Imple)'!$AS$3:$AS$112) -> 0 | BB20: =SUMIF('Tabla 2 - Ataques detec (Imple)'!$D$3:$D$112,$B20,'Tabla 2 - Ataques detec (Imple)'!$AR$3:$AR$112) -> 0 | BC20: =SUMIF('Tabla 2 - Ataques detec (Imple)'!$D$3:$D$112,$B20,'Tabla 2 - Ataques detec (Imple)'!AT$3:AT$112) -> 204 | BD20: =SUMIF('Tabla 2 - Ataques detec (Imple)'!$D$3:$D$112,$B20,'Tabla 2 - Ataques detec (Imple)'!AU$3:AU$112) -> 10 | BE20: =BD20 & " (" & BC20 & ")" -> 10 (204) | BF20: =SUMIF('Tabla 2 - Ataques detec (Imple)'!$D$3:$D$112,$B20,'Tabla 2 - Ataques detec (Imple)'!$AV$3:$AV$112) -> 1 | BG20: =AVERAGEIF('Tabla 2 - Ataques detec (Imple)'!$D$3:$D$112,$B20,'Tabla 2 - Ataques detec (Imple)'!$AX$3:$AX$112) -> 1 | BH20: =SUMIF('Tabla 2 - Ataques detec (Imple)'!$D$3:$D$112,$B20,'Tabla 2 - Ataques detec (Imple)'!$AW$3:$AW$112) -> 10 | BI20: =SUMIF('Tabla 2 - Ataques detec (Imple)'!$D$3:$D$112,$B20,'Tabla 2 - Ataques detec (Imple)'!AY$3:AY$112) -> 20 | BJ20: =SUMIF('Tabla 2 - Ataques detec (Imple)'!$D$3:$D$112,$B20,'Tabla 2 - Ataques detec (Imple)'!AZ$3:AZ$112) -> 10 | BK20: =BJ20 & " (" & BI20 & ")" -> 10 (20) | BL20: =SUMIF('Tabla 2 - Ataques detec (Imple)'!$D$3:$D$112,$B20,'Tabla 2 - Ataques detec (Imple)'!BA$3:BA$112) -> 1 | BM20: =AVERAGEIF('Tabla 2 - Ataques detec (Imple)'!$D$3:$D$112,$B20,'Tabla 2 - Ataques detec (Imple)'!$BC$3:$BC$112) -> 1 | BN20: =SUMIF('Tabla 2 - Ataques detec (Imple)'!$D$3:$D$112,$B20,'Tabla 2 - Ataques detec (Imple)'!$BB$3:$BB$112) -> 10 | BO20: =SUMIF('Tabla 2 - Ataques detec (Imple)'!$D$3:$D$112,$B20,'Tabla 2 - Ataques detec (Imple)'!BD$3:BD$112) -> 218 | BP20: =SUMIF('Tabla 2 - Ataques detec (Imple)'!$D$3:$D$112,$B20,'Tabla 2 - Ataques detec (Imple)'!BE$3:BE$112) -> 208 | BQ20: =BP20 & " (" & BO20 & ")" -> 208 (218) | BR20: =SUMIF('Tabla 2 - Ataques detec (Imple)'!$D$3:$D$112,$B20,'Tabla 2 - Ataques detec (Imple)'!BF$3:BF$112) -> 1 | BS20: =SUMIF('Tabla 2 - Ataques detec (Imple)'!$D$3:$D$112,$B20,'Tabla 2 - Ataques detec (Imple)'!BG$3:BG$112) -> 2 | BT20: =AVERAGEIF('Tabla 2 - Ataques detec (Imple)'!$D$3:$D$112,$B20,'Tabla 2 - Ataques detec (Imple)'!$BI$3:$BI$112) -> 1 | BU20: =SUMIF('Tabla 2 - Ataques detec (Imple)'!$D$3:$D$112,$B20,'Tabla 2 - Ataques detec (Imple)'!$BH$3:$BH$112) -> 198 | BV20: 5 | BW20: 5 | BX20: =BW20 & " (" & BV20 & ")" -> 5 (5) | BY20: 1 | BZ20: 1 | CA20: 5 | CB20: 10 | CC20: 10 | CD20: =CC20 & " (" & CB20 & ")" -> 10 (10) | CE20: 1 | CF20: 1 | CG20: 1 | CH20: 5
A21: =A20+1 -> 19 | B21: =IFERROR(VLOOKUP(A21,'Tabla 2 - Ataques detec (Imple)'!$B$3:$D$112,3,FALSE),"") -> T1087 | C21: =IFERROR(VLOOKUP(B21,Techniques!$B$3:$H$213,2,FALSE),"") -> Account Discovery | D21: =SUMPRODUCT( ('Tabla 2 - Ataques detec (Imple)'!$D$3:$D$112=$B21)* (LEN('Tabla 2 - Ataques detec (Imple)'!$C$3:$C$112)>0) ) -> 1 | E21: =SUMIF('Tabla 2 - Ataques detec (Imple)'!$D$3:$D$112,$B21,'Tabla 2 - Ataques detec (Imple)'!$E$3:$E$112) -> 2 | F21: =D21&" ("&E21&")" -> 1 (2) | G21: =SUMIF('Tabla 2 - Ataques detec (Imple)'!$D$3:$D$112,$B21,'Tabla 2 - Ataques detec (Imple)'!F$3:F$112) -> 24 | H21: =SUMIF('Tabla 2 - Ataques detec (Imple)'!$D$3:$D$112,$B21,'Tabla 2 - Ataques detec (Imple)'!G$3:G$112) -> 2 | I21: =H21 & " (" & G21 & ")" -> 2 (24) | J21: =SUMIF('Tabla 2 - Ataques detec (Imple)'!$D$3:$D$112,$B21,'Tabla 2 - Ataques detec (Imple)'!$H$3:$H$112) -> 2 | K21: =AVERAGEIF('Tabla 2 - Ataques detec (Imple)'!$D$3:$D$112,$B21,'Tabla 2 - Ataques detec (Imple)'!$J$3:$J$112) -> 1 | L21: =SUMIF('Tabla 2 - Ataques detec (Imple)'!$D$3:$D$112,$B21,'Tabla 2 - Ataques detec (Imple)'!$I$3:$I$112) -> 1 | M21: =SUMIF('Tabla 2 - Ataques detec (Imple)'!$D$3:$D$112,$B21,'Tabla 2 - Ataques detec (Imple)'!K$3:K$112) -> 11 | N21: =SUMIF('Tabla 2 - Ataques detec (Imple)'!$D$3:$D$112,$B21,'Tabla 2 - Ataques detec (Imple)'!L$3:L$112) -> 4 | O21: =N21 & " (" & M21 & ")" -> 4 (11) | P21: =SUMIF('Tabla 2 - Ataques detec (Imple)'!$D$3:$D$112,$B21,'Tabla 2 - Ataques detec (Imple)'!$M$3:$M$112) -> 4 | Q21: =AVERAGEIF('Tabla 2 - Ataques detec (Imple)'!$D$3:$D$112,$B21,'Tabla 2 - Ataques detec (Imple)'!$O$3:$O$112) -> 1 | R21: =SUMIF('Tabla 2 - Ataques detec (Imple)'!$D$3:$D$112,$B21,'Tabla 2 - Ataques detec (Imple)'!$N$3:$N$112) -> 2 | S21: =SUMIF('Tabla 2 - Ataques detec (Imple)'!$D$3:$D$112,$B21,'Tabla 2 - Ataques detec (Imple)'!P$3:P$112) -> 35 | T21: =SUMIF('Tabla 2 - Ataques detec (Imple)'!$D$3:$D$112,$B21,'Tabla 2 - Ataques detec (Imple)'!Q$3:Q$112) -> 6 | U21: =T21 & " (" & S21 & ")" -> 6 (35) | V21: =SUMIF('Tabla 2 - Ataques detec (Imple)'!$D$3:$D$112,$B21,'Tabla 2 - Ataques detec (Imple)'!$R$3:$R$112) -> 6 | W21: =AVERAGEIF('Tabla 2 - Ataques detec (Imple)'!$D$3:$D$112,$B21,'Tabla 2 - Ataques detec (Imple)'!$T$3:$T$112) -> 1 | X21: =SUMIF('Tabla 2 - Ataques detec (Imple)'!$D$3:$D$112,$B21,'Tabla 2 - Ataques detec (Imple)'!$S$3:$S$112) -> 2 | Y21: =SUMIF('Tabla 2 - Ataques detec (Imple)'!$D$3:$D$112,$B21,'Tabla 2 - Ataques detec (Imple)'!U$3:U$112) -> 42 | Z21: =SUMIF('Tabla 2 - Ataques detec (Imple)'!$D$3:$D$112,$B21,'Tabla 2 - Ataques detec (Imple)'!V$3:V$112) -> 10 | AA21: =Z21 & " (" & Y21 & ")" -> 10 (42) | AB21: =SUMIF('Tabla 2 - Ataques detec (Imple)'!$D$3:$D$112,$B21,'Tabla 2 - Ataques detec (Imple)'!$R$3:$R$112) -> 6 | AC21: =AVERAGEIF('Tabla 2 - Ataques detec (Imple)'!$D$3:$D$112,$B21,'Tabla 2 - Ataques detec (Imple)'!$Y$3:$Y$112) -> 1 | AD21: =SUMIF('Tabla 2 - Ataques detec (Imple)'!$D$3:$D$112,$B21,'Tabla 2 - Ataques detec (Imple)'!$X$3:$X$112) -> 2 | AE21: =SUMIF('Tabla 2 - Ataques detec (Imple)'!$D$3:$D$112,$B21,'Tabla 2 - Ataques detec (Imple)'!Z$3:Z$112) -> 36 | AF21: =SUMIF('Tabla 2 - Ataques detec (Imple)'!$D$3:$D$112,$B21,'Tabla 2 - Ataques detec (Imple)'!AA$3:AA$112) -> 13 | AG21: =AF21 & " (" & AE21 & ")" -> 13 (36) | AH21: =SUMIF('Tabla 2 - Ataques detec (Imple)'!$D$3:$D$112,$B21,'Tabla 2 - Ataques detec (Imple)'!$AB$3:$AB$112) -> 13 | AI21: =AVERAGEIF('Tabla 2 - Ataques detec (Imple)'!$D$3:$D$112,$B21,'Tabla 2 - Ataques detec (Imple)'!$AD$3:$AD$112) -> 1 | AJ21: =SUMIF('Tabla 2 - Ataques detec (Imple)'!$D$3:$D$112,$B21,'Tabla 2 - Ataques detec (Imple)'!$AC$3:$AC$112) -> 2 | AK21: =SUMIF('Tabla 2 - Ataques detec (Imple)'!$D$3:$D$112,$B21,'Tabla 2 - Ataques detec (Imple)'!AE$3:AE$112) -> 78 | AL21: =SUMIF('Tabla 2 - Ataques detec (Imple)'!$D$3:$D$112,$B21,'Tabla 2 - Ataques detec (Imple)'!AF$3:AF$112) -> 23 | AM21: =AL21 & " (" & AK21 & ")" -> 23 (78) | AN21: =SUMIF('Tabla 2 - Ataques detec (Imple)'!$D$3:$D$112,$B21,'Tabla 2 - Ataques detec (Imple)'!$AG$3:$AG$112) -> 22 | AO21: =AVERAGEIF('Tabla 2 - Ataques detec (Imple)'!$D$3:$D$112,$B21,'Tabla 2 - Ataques detec (Imple)'!$AI$3:$AI$112) -> 1 | AP21: =SUMIF('Tabla 2 - Ataques detec (Imple)'!$D$3:$D$112,$B21,'Tabla 2 - Ataques detec (Imple)'!$AH$3:$AH$112) -> 2 | AQ21: =SUMIF('Tabla 2 - Ataques detec (Imple)'!$D$3:$D$112,$B21,'Tabla 2 - Ataques detec (Imple)'!AJ$3:AJ$112) -> 0 | AR21: =SUMIF('Tabla 2 - Ataques detec (Imple)'!$D$3:$D$112,$B21,'Tabla 2 - Ataques detec (Imple)'!AK$3:AK$112) -> 0 | AS21: =AR21 & " (" & AQ21 & ")" -> 0 (0) | AT21: =SUMIF('Tabla 2 - Ataques detec (Imple)'!$D$3:$D$112,$B21,'Tabla 2 - Ataques detec (Imple)'!$AL$3:$AL$112) -> 0 | AU21: =AVERAGEIF('Tabla 2 - Ataques detec (Imple)'!$D$3:$D$112,$B21,'Tabla 2 - Ataques detec (Imple)'!$AN$3:$AN$112) -> 0 | AV21: =SUMIF('Tabla 2 - Ataques detec (Imple)'!$D$3:$D$112,$B21,'Tabla 2 - Ataques detec (Imple)'!$AM$3:$AM$112) -> 0 | AW21: =SUMIF('Tabla 2 - Ataques detec (Imple)'!$D$3:$D$112,$B21,'Tabla 2 - Ataques detec (Imple)'!AO$3:AO$112) -> 4 | AX21: =SUMIF('Tabla 2 - Ataques detec (Imple)'!$D$3:$D$112,$B21,'Tabla 2 - Ataques detec (Imple)'!AP$3:AP$112) -> 3 | AY21: =AX21 & " (" & AW21 & ")" -> 3 (4) | AZ21: =SUMIF('Tabla 2 - Ataques detec (Imple)'!$D$3:$D$112,$B21,'Tabla 2 - Ataques detec (Imple)'!$AQ$3:$AQ$112) -> 3 | BA21: =AVERAGEIF('Tabla 2 - Ataques detec (Imple)'!$D$3:$D$112,$B21,'Tabla 2 - Ataques detec (Imple)'!$AS$3:$AS$112) -> 1 | BB21: =SUMIF('Tabla 2 - Ataques detec (Imple)'!$D$3:$D$112,$B21,'Tabla 2 - Ataques detec (Imple)'!$AR$3:$AR$112) -> 1 | BC21: =SUMIF('Tabla 2 - Ataques detec (Imple)'!$D$3:$D$112,$B21,'Tabla 2 - Ataques detec (Imple)'!AT$3:AT$112) -> 39 | BD21: =SUMIF('Tabla 2 - Ataques detec (Imple)'!$D$3:$D$112,$B21,'Tabla 2 - Ataques detec (Imple)'!AU$3:AU$112) -> 9 | BE21: =BD21 & " (" & BC21 & ")" -> 9 (39) | BF21: =SUMIF('Tabla 2 - Ataques detec (Imple)'!$D$3:$D$112,$B21,'Tabla 2 - Ataques detec (Imple)'!$AV$3:$AV$112) -> 9 | BG21: =AVERAGEIF('Tabla 2 - Ataques detec (Imple)'!$D$3:$D$112,$B21,'Tabla 2 - Ataques detec (Imple)'!$AX$3:$AX$112) -> 1 | BH21: =SUMIF('Tabla 2 - Ataques detec (Imple)'!$D$3:$D$112,$B21,'Tabla 2 - Ataques detec (Imple)'!$AW$3:$AW$112) -> 2 | BI21: =SUMIF('Tabla 2 - Ataques detec (Imple)'!$D$3:$D$112,$B21,'Tabla 2 - Ataques detec (Imple)'!AY$3:AY$112) -> 4 | BJ21: =SUMIF('Tabla 2 - Ataques detec (Imple)'!$D$3:$D$112,$B21,'Tabla 2 - Ataques detec (Imple)'!AZ$3:AZ$112) -> 4 | BK21: =BJ21 & " (" & BI21 & ")" -> 4 (4) | BL21: =SUMIF('Tabla 2 - Ataques detec (Imple)'!$D$3:$D$112,$B21,'Tabla 2 - Ataques detec (Imple)'!BA$3:BA$112) -> 2 | BM21: =AVERAGEIF('Tabla 2 - Ataques detec (Imple)'!$D$3:$D$112,$B21,'Tabla 2 - Ataques detec (Imple)'!$BC$3:$BC$112) -> 1 | BN21: =SUMIF('Tabla 2 - Ataques detec (Imple)'!$D$3:$D$112,$B21,'Tabla 2 - Ataques detec (Imple)'!$BB$3:$BB$112) -> 2 | BO21: =SUMIF('Tabla 2 - Ataques detec (Imple)'!$D$3:$D$112,$B21,'Tabla 2 - Ataques detec (Imple)'!BD$3:BD$112) -> 4 | BP21: =SUMIF('Tabla 2 - Ataques detec (Imple)'!$D$3:$D$112,$B21,'Tabla 2 - Ataques detec (Imple)'!BE$3:BE$112) -> 4 | BQ21: =BP21 & " (" & BO21 & ")" -> 4 (4) | BR21: =SUMIF('Tabla 2 - Ataques detec (Imple)'!$D$3:$D$112,$B21,'Tabla 2 - Ataques detec (Imple)'!BF$3:BF$112) -> 2 | BS21: =SUMIF('Tabla 2 - Ataques detec (Imple)'!$D$3:$D$112,$B21,'Tabla 2 - Ataques detec (Imple)'!BG$3:BG$112) -> 0 | BT21: =AVERAGEIF('Tabla 2 - Ataques detec (Imple)'!$D$3:$D$112,$B21,'Tabla 2 - Ataques detec (Imple)'!$BI$3:$BI$112) -> 1 | BU21: =SUMIF('Tabla 2 - Ataques detec (Imple)'!$D$3:$D$112,$B21,'Tabla 2 - Ataques detec (Imple)'!$BH$3:$BH$112) -> 2 | BV21: 0 | BW21: 0 | BX21: =BW21 & " (" & BV21 & ")" -> 0 (0) | BY21: 0 | BZ21: 0 | CA21: 0 | CB21: 0 | CC21: 0 | CD21: =CC21 & " (" & CB21 & ")" -> 0 (0) | CE21: 0 | CF21: 0 | CG21: 0 | CH21: 0
A22: =A21+1 -> 20 | B22: =IFERROR(VLOOKUP(A22,'Tabla 2 - Ataques detec (Imple)'!$B$3:$D$112,3,FALSE),"") -> T1090 | C22: =IFERROR(VLOOKUP(B22,Techniques!$B$3:$H$213,2,FALSE),"") -> Proxy | D22: =SUMPRODUCT( ('Tabla 2 - Ataques detec (Imple)'!$D$3:$D$112=$B22)* (LEN('Tabla 2 - Ataques detec (Imple)'!$C$3:$C$112)>0) ) -> 1 | E22: =SUMIF('Tabla 2 - Ataques detec (Imple)'!$D$3:$D$112,$B22,'Tabla 2 - Ataques detec (Imple)'!$E$3:$E$112) -> 23 | F22: =D22&" ("&E22&")" -> 1 (23) | G22: =SUMIF('Tabla 2 - Ataques detec (Imple)'!$D$3:$D$112,$B22,'Tabla 2 - Ataques detec (Imple)'!F$3:F$112) -> 4 | H22: =SUMIF('Tabla 2 - Ataques detec (Imple)'!$D$3:$D$112,$B22,'Tabla 2 - Ataques detec (Imple)'!G$3:G$112) -> 4 | I22: =H22 & " (" & G22 & ")" -> 4 (4) | J22: =SUMIF('Tabla 2 - Ataques detec (Imple)'!$D$3:$D$112,$B22,'Tabla 2 - Ataques detec (Imple)'!$H$3:$H$112) -> 2 | K22: =AVERAGEIF('Tabla 2 - Ataques detec (Imple)'!$D$3:$D$112,$B22,'Tabla 2 - Ataques detec (Imple)'!$J$3:$J$112) -> 1 | L22: =SUMIF('Tabla 2 - Ataques detec (Imple)'!$D$3:$D$112,$B22,'Tabla 2 - Ataques detec (Imple)'!$I$3:$I$112) -> 2 | M22: =SUMIF('Tabla 2 - Ataques detec (Imple)'!$D$3:$D$112,$B22,'Tabla 2 - Ataques detec (Imple)'!K$3:K$112) -> 6 | N22: =SUMIF('Tabla 2 - Ataques detec (Imple)'!$D$3:$D$112,$B22,'Tabla 2 - Ataques detec (Imple)'!L$3:L$112) -> 6 | O22: =N22 & " (" & M22 & ")" -> 6 (6) | P22: =SUMIF('Tabla 2 - Ataques detec (Imple)'!$D$3:$D$112,$B22,'Tabla 2 - Ataques detec (Imple)'!$M$3:$M$112) -> 3 | Q22: =AVERAGEIF('Tabla 2 - Ataques detec (Imple)'!$D$3:$D$112,$B22,'Tabla 2 - Ataques detec (Imple)'!$O$3:$O$112) -> 1 | R22: =SUMIF('Tabla 2 - Ataques detec (Imple)'!$D$3:$D$112,$B22,'Tabla 2 - Ataques detec (Imple)'!$N$3:$N$112) -> 2 | S22: =SUMIF('Tabla 2 - Ataques detec (Imple)'!$D$3:$D$112,$B22,'Tabla 2 - Ataques detec (Imple)'!P$3:P$112) -> 10 | T22: =SUMIF('Tabla 2 - Ataques detec (Imple)'!$D$3:$D$112,$B22,'Tabla 2 - Ataques detec (Imple)'!Q$3:Q$112) -> 10 | U22: =T22 & " (" & S22 & ")" -> 10 (10) | V22: =SUMIF('Tabla 2 - Ataques detec (Imple)'!$D$3:$D$112,$B22,'Tabla 2 - Ataques detec (Imple)'!$R$3:$R$112) -> 5 | W22: =AVERAGEIF('Tabla 2 - Ataques detec (Imple)'!$D$3:$D$112,$B22,'Tabla 2 - Ataques detec (Imple)'!$T$3:$T$112) -> 1 | X22: =SUMIF('Tabla 2 - Ataques detec (Imple)'!$D$3:$D$112,$B22,'Tabla 2 - Ataques detec (Imple)'!$S$3:$S$112) -> 3 | Y22: =SUMIF('Tabla 2 - Ataques detec (Imple)'!$D$3:$D$112,$B22,'Tabla 2 - Ataques detec (Imple)'!U$3:U$112) -> 57 | Z22: =SUMIF('Tabla 2 - Ataques detec (Imple)'!$D$3:$D$112,$B22,'Tabla 2 - Ataques detec (Imple)'!V$3:V$112) -> 21 | AA22: =Z22 & " (" & Y22 & ")" -> 21 (57) | AB22: =SUMIF('Tabla 2 - Ataques detec (Imple)'!$D$3:$D$112,$B22,'Tabla 2 - Ataques detec (Imple)'!$R$3:$R$112) -> 5 | AC22: =AVERAGEIF('Tabla 2 - Ataques detec (Imple)'!$D$3:$D$112,$B22,'Tabla 2 - Ataques detec (Imple)'!$Y$3:$Y$112) -> 1 | AD22: =SUMIF('Tabla 2 - Ataques detec (Imple)'!$D$3:$D$112,$B22,'Tabla 2 - Ataques detec (Imple)'!$X$3:$X$112) -> 17 | AE22: =SUMIF('Tabla 2 - Ataques detec (Imple)'!$D$3:$D$112,$B22,'Tabla 2 - Ataques detec (Imple)'!Z$3:Z$112) -> 42 | AF22: =SUMIF('Tabla 2 - Ataques detec (Imple)'!$D$3:$D$112,$B22,'Tabla 2 - Ataques detec (Imple)'!AA$3:AA$112) -> 12 | AG22: =AF22 & " (" & AE22 & ")" -> 12 (42) | AH22: =SUMIF('Tabla 2 - Ataques detec (Imple)'!$D$3:$D$112,$B22,'Tabla 2 - Ataques detec (Imple)'!$AB$3:$AB$112) -> 6 | AI22: =AVERAGEIF('Tabla 2 - Ataques detec (Imple)'!$D$3:$D$112,$B22,'Tabla 2 - Ataques detec (Imple)'!$AD$3:$AD$112) -> 1 | AJ22: =SUMIF('Tabla 2 - Ataques detec (Imple)'!$D$3:$D$112,$B22,'Tabla 2 - Ataques detec (Imple)'!$AC$3:$AC$112) -> 5 | AK22: =SUMIF('Tabla 2 - Ataques detec (Imple)'!$D$3:$D$112,$B22,'Tabla 2 - Ataques detec (Imple)'!AE$3:AE$112) -> 99 | AL22: =SUMIF('Tabla 2 - Ataques detec (Imple)'!$D$3:$D$112,$B22,'Tabla 2 - Ataques detec (Imple)'!AF$3:AF$112) -> 33 | AM22: =AL22 & " (" & AK22 & ")" -> 33 (99) | AN22: =SUMIF('Tabla 2 - Ataques detec (Imple)'!$D$3:$D$112,$B22,'Tabla 2 - Ataques detec (Imple)'!$AG$3:$AG$112) -> 10 | AO22: =AVERAGEIF('Tabla 2 - Ataques detec (Imple)'!$D$3:$D$112,$B22,'Tabla 2 - Ataques detec (Imple)'!$AI$3:$AI$112) -> 1 | AP22: =SUMIF('Tabla 2 - Ataques detec (Imple)'!$D$3:$D$112,$B22,'Tabla 2 - Ataques detec (Imple)'!$AH$3:$AH$112) -> 17 | AQ22: =SUMIF('Tabla 2 - Ataques detec (Imple)'!$D$3:$D$112,$B22,'Tabla 2 - Ataques detec (Imple)'!AJ$3:AJ$112) -> 0 | AR22: =SUMIF('Tabla 2 - Ataques detec (Imple)'!$D$3:$D$112,$B22,'Tabla 2 - Ataques detec (Imple)'!AK$3:AK$112) -> 0 | AS22: =AR22 & " (" & AQ22 & ")" -> 0 (0) | AT22: =SUMIF('Tabla 2 - Ataques detec (Imple)'!$D$3:$D$112,$B22,'Tabla 2 - Ataques detec (Imple)'!$AL$3:$AL$112) -> 0 | AU22: =AVERAGEIF('Tabla 2 - Ataques detec (Imple)'!$D$3:$D$112,$B22,'Tabla 2 - Ataques detec (Imple)'!$AN$3:$AN$112) -> 0 | AV22: =SUMIF('Tabla 2 - Ataques detec (Imple)'!$D$3:$D$112,$B22,'Tabla 2 - Ataques detec (Imple)'!$AM$3:$AM$112) -> 0 | AW22: =SUMIF('Tabla 2 - Ataques detec (Imple)'!$D$3:$D$112,$B22,'Tabla 2 - Ataques detec (Imple)'!AO$3:AO$112) -> 0 | AX22: =SUMIF('Tabla 2 - Ataques detec (Imple)'!$D$3:$D$112,$B22,'Tabla 2 - Ataques detec (Imple)'!AP$3:AP$112) -> 0 | AY22: =AX22 & " (" & AW22 & ")" -> 0 (0) | AZ22: =SUMIF('Tabla 2 - Ataques detec (Imple)'!$D$3:$D$112,$B22,'Tabla 2 - Ataques detec (Imple)'!$AQ$3:$AQ$112) -> 0 | BA22: =AVERAGEIF('Tabla 2 - Ataques detec (Imple)'!$D$3:$D$112,$B22,'Tabla 2 - Ataques detec (Imple)'!$AS$3:$AS$112) -> 0 | BB22: =SUMIF('Tabla 2 - Ataques detec (Imple)'!$D$3:$D$112,$B22,'Tabla 2 - Ataques detec (Imple)'!$AR$3:$AR$112) -> 0 | BC22: =SUMIF('Tabla 2 - Ataques detec (Imple)'!$D$3:$D$112,$B22,'Tabla 2 - Ataques detec (Imple)'!AT$3:AT$112) -> 10 | BD22: =SUMIF('Tabla 2 - Ataques detec (Imple)'!$D$3:$D$112,$B22,'Tabla 2 - Ataques detec (Imple)'!AU$3:AU$112) -> 10 | BE22: =BD22 & " (" & BC22 & ")" -> 10 (10) | BF22: =SUMIF('Tabla 2 - Ataques detec (Imple)'!$D$3:$D$112,$B22,'Tabla 2 - Ataques detec (Imple)'!$AV$3:$AV$112) -> 5 | BG22: =AVERAGEIF('Tabla 2 - Ataques detec (Imple)'!$D$3:$D$112,$B22,'Tabla 2 - Ataques detec (Imple)'!$AX$3:$AX$112) -> 1 | BH22: =SUMIF('Tabla 2 - Ataques detec (Imple)'!$D$3:$D$112,$B22,'Tabla 2 - Ataques detec (Imple)'!$AW$3:$AW$112) -> 3 | BI22: =SUMIF('Tabla 2 - Ataques detec (Imple)'!$D$3:$D$112,$B22,'Tabla 2 - Ataques detec (Imple)'!AY$3:AY$112) -> 7 | BJ22: =SUMIF('Tabla 2 - Ataques detec (Imple)'!$D$3:$D$112,$B22,'Tabla 2 - Ataques detec (Imple)'!AZ$3:AZ$112) -> 4 | BK22: =BJ22 & " (" & BI22 & ")" -> 4 (7) | BL22: =SUMIF('Tabla 2 - Ataques detec (Imple)'!$D$3:$D$112,$B22,'Tabla 2 - Ataques detec (Imple)'!BA$3:BA$112) -> 1 | BM22: =AVERAGEIF('Tabla 2 - Ataques detec (Imple)'!$D$3:$D$112,$B22,'Tabla 2 - Ataques detec (Imple)'!$BC$3:$BC$112) -> 1 | BN22: =SUMIF('Tabla 2 - Ataques detec (Imple)'!$D$3:$D$112,$B22,'Tabla 2 - Ataques detec (Imple)'!$BB$3:$BB$112) -> 4 | BO22: =SUMIF('Tabla 2 - Ataques detec (Imple)'!$D$3:$D$112,$B22,'Tabla 2 - Ataques detec (Imple)'!BD$3:BD$112) -> 61 | BP22: =SUMIF('Tabla 2 - Ataques detec (Imple)'!$D$3:$D$112,$B22,'Tabla 2 - Ataques detec (Imple)'!BE$3:BE$112) -> 29 | BQ22: =BP22 & " (" & BO22 & ")" -> 29 (61) | BR22: =SUMIF('Tabla 2 - Ataques detec (Imple)'!$D$3:$D$112,$B22,'Tabla 2 - Ataques detec (Imple)'!BF$3:BF$112) -> 1 | BS22: =SUMIF('Tabla 2 - Ataques detec (Imple)'!$D$3:$D$112,$B22,'Tabla 2 - Ataques detec (Imple)'!BG$3:BG$112) -> 5 | BT22: =AVERAGEIF('Tabla 2 - Ataques detec (Imple)'!$D$3:$D$112,$B22,'Tabla 2 - Ataques detec (Imple)'!$BI$3:$BI$112) -> 1 | BU22: =SUMIF('Tabla 2 - Ataques detec (Imple)'!$D$3:$D$112,$B22,'Tabla 2 - Ataques detec (Imple)'!$BH$3:$BH$112) -> 20 | BV22: 47 | BW22: 19 | BX22: =BW22 & " (" & BV22 & ")" -> 19 (47) | BY22: 2 | BZ22: 1 | CA22: 15 | CB22: 94 | CC22: 34 | CD22: =CC22 & " (" & CB22 & ")" -> 34 (94) | CE22: 2 | CF22: 1 | CG22: 1 | CH22: 15
A23: =A22+1 -> 21 | B23: =IFERROR(VLOOKUP(A23,'Tabla 2 - Ataques detec (Imple)'!$B$3:$D$112,3,FALSE),"") -> T1095 | C23: =IFERROR(VLOOKUP(B23,Techniques!$B$3:$H$213,2,FALSE),"") -> Non-Application Layer Protocol | D23: =SUMPRODUCT( ('Tabla 2 - Ataques detec (Imple)'!$D$3:$D$112=$B23)* (LEN('Tabla 2 - Ataques detec (Imple)'!$C$3:$C$112)>0) ) -> 1 | E23: =SUMIF('Tabla 2 - Ataques detec (Imple)'!$D$3:$D$112,$B23,'Tabla 2 - Ataques detec (Imple)'!$E$3:$E$112) -> 2 | F23: =D23&" ("&E23&")" -> 1 (2) | G23: =SUMIF('Tabla 2 - Ataques detec (Imple)'!$D$3:$D$112,$B23,'Tabla 2 - Ataques detec (Imple)'!F$3:F$112) -> 3 | H23: =SUMIF('Tabla 2 - Ataques detec (Imple)'!$D$3:$D$112,$B23,'Tabla 2 - Ataques detec (Imple)'!G$3:G$112) -> 2 | I23: =H23 & " (" & G23 & ")" -> 2 (3) | J23: =SUMIF('Tabla 2 - Ataques detec (Imple)'!$D$3:$D$112,$B23,'Tabla 2 - Ataques detec (Imple)'!$H$3:$H$112) -> 2 | K23: =AVERAGEIF('Tabla 2 - Ataques detec (Imple)'!$D$3:$D$112,$B23,'Tabla 2 - Ataques detec (Imple)'!$J$3:$J$112) -> 1 | L23: =SUMIF('Tabla 2 - Ataques detec (Imple)'!$D$3:$D$112,$B23,'Tabla 2 - Ataques detec (Imple)'!$I$3:$I$112) -> 2 | M23: =SUMIF('Tabla 2 - Ataques detec (Imple)'!$D$3:$D$112,$B23,'Tabla 2 - Ataques detec (Imple)'!K$3:K$112) -> 4 | N23: =SUMIF('Tabla 2 - Ataques detec (Imple)'!$D$3:$D$112,$B23,'Tabla 2 - Ataques detec (Imple)'!L$3:L$112) -> 4 | O23: =N23 & " (" & M23 & ")" -> 4 (4) | P23: =SUMIF('Tabla 2 - Ataques detec (Imple)'!$D$3:$D$112,$B23,'Tabla 2 - Ataques detec (Imple)'!$M$3:$M$112) -> 4 | Q23: =AVERAGEIF('Tabla 2 - Ataques detec (Imple)'!$D$3:$D$112,$B23,'Tabla 2 - Ataques detec (Imple)'!$O$3:$O$112) -> 1 | R23: =SUMIF('Tabla 2 - Ataques detec (Imple)'!$D$3:$D$112,$B23,'Tabla 2 - Ataques detec (Imple)'!$N$3:$N$112) -> 2 | S23: =SUMIF('Tabla 2 - Ataques detec (Imple)'!$D$3:$D$112,$B23,'Tabla 2 - Ataques detec (Imple)'!P$3:P$112) -> 7 | T23: =SUMIF('Tabla 2 - Ataques detec (Imple)'!$D$3:$D$112,$B23,'Tabla 2 - Ataques detec (Imple)'!Q$3:Q$112) -> 6 | U23: =T23 & " (" & S23 & ")" -> 6 (7) | V23: =SUMIF('Tabla 2 - Ataques detec (Imple)'!$D$3:$D$112,$B23,'Tabla 2 - Ataques detec (Imple)'!$R$3:$R$112) -> 6 | W23: =AVERAGEIF('Tabla 2 - Ataques detec (Imple)'!$D$3:$D$112,$B23,'Tabla 2 - Ataques detec (Imple)'!$T$3:$T$112) -> 1 | X23: =SUMIF('Tabla 2 - Ataques detec (Imple)'!$D$3:$D$112,$B23,'Tabla 2 - Ataques detec (Imple)'!$S$3:$S$112) -> 2 | Y23: =SUMIF('Tabla 2 - Ataques detec (Imple)'!$D$3:$D$112,$B23,'Tabla 2 - Ataques detec (Imple)'!U$3:U$112) -> 18 | Z23: =SUMIF('Tabla 2 - Ataques detec (Imple)'!$D$3:$D$112,$B23,'Tabla 2 - Ataques detec (Imple)'!V$3:V$112) -> 8 | AA23: =Z23 & " (" & Y23 & ")" -> 8 (18) | AB23: =SUMIF('Tabla 2 - Ataques detec (Imple)'!$D$3:$D$112,$B23,'Tabla 2 - Ataques detec (Imple)'!$R$3:$R$112) -> 6 | AC23: =AVERAGEIF('Tabla 2 - Ataques detec (Imple)'!$D$3:$D$112,$B23,'Tabla 2 - Ataques detec (Imple)'!$Y$3:$Y$112) -> 1 | AD23: =SUMIF('Tabla 2 - Ataques detec (Imple)'!$D$3:$D$112,$B23,'Tabla 2 - Ataques detec (Imple)'!$X$3:$X$112) -> 2 | AE23: =SUMIF('Tabla 2 - Ataques detec (Imple)'!$D$3:$D$112,$B23,'Tabla 2 - Ataques detec (Imple)'!Z$3:Z$112) -> 12 | AF23: =SUMIF('Tabla 2 - Ataques detec (Imple)'!$D$3:$D$112,$B23,'Tabla 2 - Ataques detec (Imple)'!AA$3:AA$112) -> 9 | AG23: =AF23 & " (" & AE23 & ")" -> 9 (12) | AH23: =SUMIF('Tabla 2 - Ataques detec (Imple)'!$D$3:$D$112,$B23,'Tabla 2 - Ataques detec (Imple)'!$AB$3:$AB$112) -> 9 | AI23: =AVERAGEIF('Tabla 2 - Ataques detec (Imple)'!$D$3:$D$112,$B23,'Tabla 2 - Ataques detec (Imple)'!$AD$3:$AD$112) -> 1 | AJ23: =SUMIF('Tabla 2 - Ataques detec (Imple)'!$D$3:$D$112,$B23,'Tabla 2 - Ataques detec (Imple)'!$AC$3:$AC$112) -> 2 | AK23: =SUMIF('Tabla 2 - Ataques detec (Imple)'!$D$3:$D$112,$B23,'Tabla 2 - Ataques detec (Imple)'!AE$3:AE$112) -> 30 | AL23: =SUMIF('Tabla 2 - Ataques detec (Imple)'!$D$3:$D$112,$B23,'Tabla 2 - Ataques detec (Imple)'!AF$3:AF$112) -> 17 | AM23: =AL23 & " (" & AK23 & ")" -> 17 (30) | AN23: =SUMIF('Tabla 2 - Ataques detec (Imple)'!$D$3:$D$112,$B23,'Tabla 2 - Ataques detec (Imple)'!$AG$3:$AG$112) -> 17 | AO23: =AVERAGEIF('Tabla 2 - Ataques detec (Imple)'!$D$3:$D$112,$B23,'Tabla 2 - Ataques detec (Imple)'!$AI$3:$AI$112) -> 1 | AP23: =SUMIF('Tabla 2 - Ataques detec (Imple)'!$D$3:$D$112,$B23,'Tabla 2 - Ataques detec (Imple)'!$AH$3:$AH$112) -> 2 | AQ23: =SUMIF('Tabla 2 - Ataques detec (Imple)'!$D$3:$D$112,$B23,'Tabla 2 - Ataques detec (Imple)'!AJ$3:AJ$112) -> 0 | AR23: =SUMIF('Tabla 2 - Ataques detec (Imple)'!$D$3:$D$112,$B23,'Tabla 2 - Ataques detec (Imple)'!AK$3:AK$112) -> 0 | AS23: =AR23 & " (" & AQ23 & ")" -> 0 (0) | AT23: =SUMIF('Tabla 2 - Ataques detec (Imple)'!$D$3:$D$112,$B23,'Tabla 2 - Ataques detec (Imple)'!$AL$3:$AL$112) -> 0 | AU23: =AVERAGEIF('Tabla 2 - Ataques detec (Imple)'!$D$3:$D$112,$B23,'Tabla 2 - Ataques detec (Imple)'!$AN$3:$AN$112) -> 0 | AV23: =SUMIF('Tabla 2 - Ataques detec (Imple)'!$D$3:$D$112,$B23,'Tabla 2 - Ataques detec (Imple)'!$AM$3:$AM$112) -> 0 | AW23: =SUMIF('Tabla 2 - Ataques detec (Imple)'!$D$3:$D$112,$B23,'Tabla 2 - Ataques detec (Imple)'!AO$3:AO$112) -> 3 | AX23: =SUMIF('Tabla 2 - Ataques detec (Imple)'!$D$3:$D$112,$B23,'Tabla 2 - Ataques detec (Imple)'!AP$3:AP$112) -> 2 | AY23: =AX23 & " (" & AW23 & ")" -> 2 (3) | AZ23: =SUMIF('Tabla 2 - Ataques detec (Imple)'!$D$3:$D$112,$B23,'Tabla 2 - Ataques detec (Imple)'!$AQ$3:$AQ$112) -> 2 | BA23: =AVERAGEIF('Tabla 2 - Ataques detec (Imple)'!$D$3:$D$112,$B23,'Tabla 2 - Ataques detec (Imple)'!$AS$3:$AS$112) -> 1 | BB23: =SUMIF('Tabla 2 - Ataques detec (Imple)'!$D$3:$D$112,$B23,'Tabla 2 - Ataques detec (Imple)'!$AR$3:$AR$112) -> 1 | BC23: =SUMIF('Tabla 2 - Ataques detec (Imple)'!$D$3:$D$112,$B23,'Tabla 2 - Ataques detec (Imple)'!AT$3:AT$112) -> 10 | BD23: =SUMIF('Tabla 2 - Ataques detec (Imple)'!$D$3:$D$112,$B23,'Tabla 2 - Ataques detec (Imple)'!AU$3:AU$112) -> 8 | BE23: =BD23 & " (" & BC23 & ")" -> 8 (10) | BF23: =SUMIF('Tabla 2 - Ataques detec (Imple)'!$D$3:$D$112,$B23,'Tabla 2 - Ataques detec (Imple)'!$AV$3:$AV$112) -> 8 | BG23: =AVERAGEIF('Tabla 2 - Ataques detec (Imple)'!$D$3:$D$112,$B23,'Tabla 2 - Ataques detec (Imple)'!$AX$3:$AX$112) -> 1 | BH23: =SUMIF('Tabla 2 - Ataques detec (Imple)'!$D$3:$D$112,$B23,'Tabla 2 - Ataques detec (Imple)'!$AW$3:$AW$112) -> 2 | BI23: =SUMIF('Tabla 2 - Ataques detec (Imple)'!$D$3:$D$112,$B23,'Tabla 2 - Ataques detec (Imple)'!AY$3:AY$112) -> 3 | BJ23: =SUMIF('Tabla 2 - Ataques detec (Imple)'!$D$3:$D$112,$B23,'Tabla 2 - Ataques detec (Imple)'!AZ$3:AZ$112) -> 2 | BK23: =BJ23 & " (" & BI23 & ")" -> 2 (3) | BL23: =SUMIF('Tabla 2 - Ataques detec (Imple)'!$D$3:$D$112,$B23,'Tabla 2 - Ataques detec (Imple)'!BA$3:BA$112) -> 1 | BM23: =AVERAGEIF('Tabla 2 - Ataques detec (Imple)'!$D$3:$D$112,$B23,'Tabla 2 - Ataques detec (Imple)'!$BC$3:$BC$112) -> 1 | BN23: =SUMIF('Tabla 2 - Ataques detec (Imple)'!$D$3:$D$112,$B23,'Tabla 2 - Ataques detec (Imple)'!$BB$3:$BB$112) -> 2 | BO23: =SUMIF('Tabla 2 - Ataques detec (Imple)'!$D$3:$D$112,$B23,'Tabla 2 - Ataques detec (Imple)'!BD$3:BD$112) -> 4 | BP23: =SUMIF('Tabla 2 - Ataques detec (Imple)'!$D$3:$D$112,$B23,'Tabla 2 - Ataques detec (Imple)'!BE$3:BE$112) -> 3 | BQ23: =BP23 & " (" & BO23 & ")" -> 3 (4) | BR23: =SUMIF('Tabla 2 - Ataques detec (Imple)'!$D$3:$D$112,$B23,'Tabla 2 - Ataques detec (Imple)'!BF$3:BF$112) -> 1 | BS23: =SUMIF('Tabla 2 - Ataques detec (Imple)'!$D$3:$D$112,$B23,'Tabla 2 - Ataques detec (Imple)'!BG$3:BG$112) -> 1 | BT23: =AVERAGEIF('Tabla 2 - Ataques detec (Imple)'!$D$3:$D$112,$B23,'Tabla 2 - Ataques detec (Imple)'!$BI$3:$BI$112) -> 1 | BU23: =SUMIF('Tabla 2 - Ataques detec (Imple)'!$D$3:$D$112,$B23,'Tabla 2 - Ataques detec (Imple)'!$BH$3:$BH$112) -> 2 | BV23: 2 | BW23: 2 | BX23: =BW23 & " (" & BV23 & ")" -> 2 (2) | BY23: 1 | BZ23: 1 | CA23: 2 | CB23: 4 | CC23: 4 | CD23: =CC23 & " (" & CB23 & ")" -> 4 (4) | CE23: 1 | CF23: 2 | CG23: 1 | CH23: 2
A24: =A23+1 -> 22 | B24: =IFERROR(VLOOKUP(A24,'Tabla 2 - Ataques detec (Imple)'!$B$3:$D$112,3,FALSE),"") -> T1102 | C24: =IFERROR(VLOOKUP(B24,Techniques!$B$3:$H$213,2,FALSE),"") -> Web Service | D24: =SUMPRODUCT( ('Tabla 2 - Ataques detec (Imple)'!$D$3:$D$112=$B24)* (LEN('Tabla 2 - Ataques detec (Imple)'!$C$3:$C$112)>0) ) -> 1 | E24: =SUMIF('Tabla 2 - Ataques detec (Imple)'!$D$3:$D$112,$B24,'Tabla 2 - Ataques detec (Imple)'!$E$3:$E$112) -> 2 | F24: =D24&" ("&E24&")" -> 1 (2) | G24: =SUMIF('Tabla 2 - Ataques detec (Imple)'!$D$3:$D$112,$B24,'Tabla 2 - Ataques detec (Imple)'!F$3:F$112) -> 3 | H24: =SUMIF('Tabla 2 - Ataques detec (Imple)'!$D$3:$D$112,$B24,'Tabla 2 - Ataques detec (Imple)'!G$3:G$112) -> 3 | I24: =H24 & " (" & G24 & ")" -> 3 (3) | J24: =SUMIF('Tabla 2 - Ataques detec (Imple)'!$D$3:$D$112,$B24,'Tabla 2 - Ataques detec (Imple)'!$H$3:$H$112) -> 3 | K24: =AVERAGEIF('Tabla 2 - Ataques detec (Imple)'!$D$3:$D$112,$B24,'Tabla 2 - Ataques detec (Imple)'!$J$3:$J$112) -> 1 | L24: =SUMIF('Tabla 2 - Ataques detec (Imple)'!$D$3:$D$112,$B24,'Tabla 2 - Ataques detec (Imple)'!$I$3:$I$112) -> 1 | M24: =SUMIF('Tabla 2 - Ataques detec (Imple)'!$D$3:$D$112,$B24,'Tabla 2 - Ataques detec (Imple)'!K$3:K$112) -> 3 | N24: =SUMIF('Tabla 2 - Ataques detec (Imple)'!$D$3:$D$112,$B24,'Tabla 2 - Ataques detec (Imple)'!L$3:L$112) -> 3 | O24: =N24 & " (" & M24 & ")" -> 3 (3) | P24: =SUMIF('Tabla 2 - Ataques detec (Imple)'!$D$3:$D$112,$B24,'Tabla 2 - Ataques detec (Imple)'!$M$3:$M$112) -> 3 | Q24: =AVERAGEIF('Tabla 2 - Ataques detec (Imple)'!$D$3:$D$112,$B24,'Tabla 2 - Ataques detec (Imple)'!$O$3:$O$112) -> 1 | R24: =SUMIF('Tabla 2 - Ataques detec (Imple)'!$D$3:$D$112,$B24,'Tabla 2 - Ataques detec (Imple)'!$N$3:$N$112) -> 1 | S24: =SUMIF('Tabla 2 - Ataques detec (Imple)'!$D$3:$D$112,$B24,'Tabla 2 - Ataques detec (Imple)'!P$3:P$112) -> 6 | T24: =SUMIF('Tabla 2 - Ataques detec (Imple)'!$D$3:$D$112,$B24,'Tabla 2 - Ataques detec (Imple)'!Q$3:Q$112) -> 6 | U24: =T24 & " (" & S24 & ")" -> 6 (6) | V24: =SUMIF('Tabla 2 - Ataques detec (Imple)'!$D$3:$D$112,$B24,'Tabla 2 - Ataques detec (Imple)'!$R$3:$R$112) -> 6 | W24: =AVERAGEIF('Tabla 2 - Ataques detec (Imple)'!$D$3:$D$112,$B24,'Tabla 2 - Ataques detec (Imple)'!$T$3:$T$112) -> 1 | X24: =SUMIF('Tabla 2 - Ataques detec (Imple)'!$D$3:$D$112,$B24,'Tabla 2 - Ataques detec (Imple)'!$S$3:$S$112) -> 2 | Y24: =SUMIF('Tabla 2 - Ataques detec (Imple)'!$D$3:$D$112,$B24,'Tabla 2 - Ataques detec (Imple)'!U$3:U$112) -> 17 | Z24: =SUMIF('Tabla 2 - Ataques detec (Imple)'!$D$3:$D$112,$B24,'Tabla 2 - Ataques detec (Imple)'!V$3:V$112) -> 4 | AA24: =Z24 & " (" & Y24 & ")" -> 4 (17) | AB24: =SUMIF('Tabla 2 - Ataques detec (Imple)'!$D$3:$D$112,$B24,'Tabla 2 - Ataques detec (Imple)'!$R$3:$R$112) -> 6 | AC24: =AVERAGEIF('Tabla 2 - Ataques detec (Imple)'!$D$3:$D$112,$B24,'Tabla 2 - Ataques detec (Imple)'!$Y$3:$Y$112) -> 1 | AD24: =SUMIF('Tabla 2 - Ataques detec (Imple)'!$D$3:$D$112,$B24,'Tabla 2 - Ataques detec (Imple)'!$X$3:$X$112) -> 2 | AE24: =SUMIF('Tabla 2 - Ataques detec (Imple)'!$D$3:$D$112,$B24,'Tabla 2 - Ataques detec (Imple)'!Z$3:Z$112) -> 8 | AF24: =SUMIF('Tabla 2 - Ataques detec (Imple)'!$D$3:$D$112,$B24,'Tabla 2 - Ataques detec (Imple)'!AA$3:AA$112) -> 6 | AG24: =AF24 & " (" & AE24 & ")" -> 6 (8) | AH24: =SUMIF('Tabla 2 - Ataques detec (Imple)'!$D$3:$D$112,$B24,'Tabla 2 - Ataques detec (Imple)'!$AB$3:$AB$112) -> 5 | AI24: =AVERAGEIF('Tabla 2 - Ataques detec (Imple)'!$D$3:$D$112,$B24,'Tabla 2 - Ataques detec (Imple)'!$AD$3:$AD$112) -> 1 | AJ24: =SUMIF('Tabla 2 - Ataques detec (Imple)'!$D$3:$D$112,$B24,'Tabla 2 - Ataques detec (Imple)'!$AC$3:$AC$112) -> 2 | AK24: =SUMIF('Tabla 2 - Ataques detec (Imple)'!$D$3:$D$112,$B24,'Tabla 2 - Ataques detec (Imple)'!AE$3:AE$112) -> 25 | AL24: =SUMIF('Tabla 2 - Ataques detec (Imple)'!$D$3:$D$112,$B24,'Tabla 2 - Ataques detec (Imple)'!AF$3:AF$112) -> 10 | AM24: =AL24 & " (" & AK24 & ")" -> 10 (25) | AN24: =SUMIF('Tabla 2 - Ataques detec (Imple)'!$D$3:$D$112,$B24,'Tabla 2 - Ataques detec (Imple)'!$AG$3:$AG$112) -> 9 | AO24: =AVERAGEIF('Tabla 2 - Ataques detec (Imple)'!$D$3:$D$112,$B24,'Tabla 2 - Ataques detec (Imple)'!$AI$3:$AI$112) -> 1 | AP24: =SUMIF('Tabla 2 - Ataques detec (Imple)'!$D$3:$D$112,$B24,'Tabla 2 - Ataques detec (Imple)'!$AH$3:$AH$112) -> 2 | AQ24: =SUMIF('Tabla 2 - Ataques detec (Imple)'!$D$3:$D$112,$B24,'Tabla 2 - Ataques detec (Imple)'!AJ$3:AJ$112) -> 0 | AR24: =SUMIF('Tabla 2 - Ataques detec (Imple)'!$D$3:$D$112,$B24,'Tabla 2 - Ataques detec (Imple)'!AK$3:AK$112) -> 0 | AS24: =AR24 & " (" & AQ24 & ")" -> 0 (0) | AT24: =SUMIF('Tabla 2 - Ataques detec (Imple)'!$D$3:$D$112,$B24,'Tabla 2 - Ataques detec (Imple)'!$AL$3:$AL$112) -> 0 | AU24: =AVERAGEIF('Tabla 2 - Ataques detec (Imple)'!$D$3:$D$112,$B24,'Tabla 2 - Ataques detec (Imple)'!$AN$3:$AN$112) -> 0 | AV24: =SUMIF('Tabla 2 - Ataques detec (Imple)'!$D$3:$D$112,$B24,'Tabla 2 - Ataques detec (Imple)'!$AM$3:$AM$112) -> 0 | AW24: =SUMIF('Tabla 2 - Ataques detec (Imple)'!$D$3:$D$112,$B24,'Tabla 2 - Ataques detec (Imple)'!AO$3:AO$112) -> 0 | AX24: =SUMIF('Tabla 2 - Ataques detec (Imple)'!$D$3:$D$112,$B24,'Tabla 2 - Ataques detec (Imple)'!AP$3:AP$112) -> 0 | AY24: =AX24 & " (" & AW24 & ")" -> 0 (0) | AZ24: =SUMIF('Tabla 2 - Ataques detec (Imple)'!$D$3:$D$112,$B24,'Tabla 2 - Ataques detec (Imple)'!$AQ$3:$AQ$112) -> 0 | BA24: =AVERAGEIF('Tabla 2 - Ataques detec (Imple)'!$D$3:$D$112,$B24,'Tabla 2 - Ataques detec (Imple)'!$AS$3:$AS$112) -> 0 | BB24: =SUMIF('Tabla 2 - Ataques detec (Imple)'!$D$3:$D$112,$B24,'Tabla 2 - Ataques detec (Imple)'!$AR$3:$AR$112) -> 0 | BC24: =SUMIF('Tabla 2 - Ataques detec (Imple)'!$D$3:$D$112,$B24,'Tabla 2 - Ataques detec (Imple)'!AT$3:AT$112) -> 6 | BD24: =SUMIF('Tabla 2 - Ataques detec (Imple)'!$D$3:$D$112,$B24,'Tabla 2 - Ataques detec (Imple)'!AU$3:AU$112) -> 6 | BE24: =BD24 & " (" & BC24 & ")" -> 6 (6) | BF24: =SUMIF('Tabla 2 - Ataques detec (Imple)'!$D$3:$D$112,$B24,'Tabla 2 - Ataques detec (Imple)'!$AV$3:$AV$112) -> 6 | BG24: =AVERAGEIF('Tabla 2 - Ataques detec (Imple)'!$D$3:$D$112,$B24,'Tabla 2 - Ataques detec (Imple)'!$AX$3:$AX$112) -> 1 | BH24: =SUMIF('Tabla 2 - Ataques detec (Imple)'!$D$3:$D$112,$B24,'Tabla 2 - Ataques detec (Imple)'!$AW$3:$AW$112) -> 2 | BI24: =SUMIF('Tabla 2 - Ataques detec (Imple)'!$D$3:$D$112,$B24,'Tabla 2 - Ataques detec (Imple)'!AY$3:AY$112) -> 4 | BJ24: =SUMIF('Tabla 2 - Ataques detec (Imple)'!$D$3:$D$112,$B24,'Tabla 2 - Ataques detec (Imple)'!AZ$3:AZ$112) -> 3 | BK24: =BJ24 & " (" & BI24 & ")" -> 3 (4) | BL24: =SUMIF('Tabla 2 - Ataques detec (Imple)'!$D$3:$D$112,$B24,'Tabla 2 - Ataques detec (Imple)'!BA$3:BA$112) -> 3 | BM24: =AVERAGEIF('Tabla 2 - Ataques detec (Imple)'!$D$3:$D$112,$B24,'Tabla 2 - Ataques detec (Imple)'!$BC$3:$BC$112) -> 1 | BN24: =SUMIF('Tabla 2 - Ataques detec (Imple)'!$D$3:$D$112,$B24,'Tabla 2 - Ataques detec (Imple)'!$BB$3:$BB$112) -> 2 | BO24: =SUMIF('Tabla 2 - Ataques detec (Imple)'!$D$3:$D$112,$B24,'Tabla 2 - Ataques detec (Imple)'!BD$3:BD$112) -> 6 | BP24: =SUMIF('Tabla 2 - Ataques detec (Imple)'!$D$3:$D$112,$B24,'Tabla 2 - Ataques detec (Imple)'!BE$3:BE$112) -> 5 | BQ24: =BP24 & " (" & BO24 & ")" -> 5 (6) | BR24: =SUMIF('Tabla 2 - Ataques detec (Imple)'!$D$3:$D$112,$B24,'Tabla 2 - Ataques detec (Imple)'!BF$3:BF$112) -> 3 | BS24: =SUMIF('Tabla 2 - Ataques detec (Imple)'!$D$3:$D$112,$B24,'Tabla 2 - Ataques detec (Imple)'!BG$3:BG$112) -> 2 | BT24: =AVERAGEIF('Tabla 2 - Ataques detec (Imple)'!$D$3:$D$112,$B24,'Tabla 2 - Ataques detec (Imple)'!$BI$3:$BI$112) -> 1 | BU24: =SUMIF('Tabla 2 - Ataques detec (Imple)'!$D$3:$D$112,$B24,'Tabla 2 - Ataques detec (Imple)'!$BH$3:$BH$112) -> 2 | BV24: 6 | BW24: 3 | BX24: =BW24 & " (" & BV24 & ")" -> 3 (6) | BY24: 3 | BZ24: 1 | CA24: 2 | CB24: 12 | CC24: 5 | CD24: =CC24 & " (" & CB24 & ")" -> 5 (12) | CE24: 3 | CF24: 2 | CG24: 1 | CH24: 2
A25: =A24+1 -> 23 | B25: =IFERROR(VLOOKUP(A25,'Tabla 2 - Ataques detec (Imple)'!$B$3:$D$112,3,FALSE),"") -> T1104 | C25: =IFERROR(VLOOKUP(B25,Techniques!$B$3:$H$213,2,FALSE),"") -> Multi-Stage Channels | D25: =SUMPRODUCT( ('Tabla 2 - Ataques detec (Imple)'!$D$3:$D$112=$B25)* (LEN('Tabla 2 - Ataques detec (Imple)'!$C$3:$C$112)>0) ) -> 1 | E25: =SUMIF('Tabla 2 - Ataques detec (Imple)'!$D$3:$D$112,$B25,'Tabla 2 - Ataques detec (Imple)'!$E$3:$E$112) -> 1 | F25: =D25&" ("&E25&")" -> 1 (1) | G25: =SUMIF('Tabla 2 - Ataques detec (Imple)'!$D$3:$D$112,$B25,'Tabla 2 - Ataques detec (Imple)'!F$3:F$112) -> 0 | H25: =SUMIF('Tabla 2 - Ataques detec (Imple)'!$D$3:$D$112,$B25,'Tabla 2 - Ataques detec (Imple)'!G$3:G$112) -> 0 | I25: =H25 & " (" & G25 & ")" -> 0 (0) | J25: =SUMIF('Tabla 2 - Ataques detec (Imple)'!$D$3:$D$112,$B25,'Tabla 2 - Ataques detec (Imple)'!$H$3:$H$112) -> 0 | K25: =AVERAGEIF('Tabla 2 - Ataques detec (Imple)'!$D$3:$D$112,$B25,'Tabla 2 - Ataques detec (Imple)'!$J$3:$J$112) -> 0 | L25: =SUMIF('Tabla 2 - Ataques detec (Imple)'!$D$3:$D$112,$B25,'Tabla 2 - Ataques detec (Imple)'!$I$3:$I$112) -> 0 | M25: =SUMIF('Tabla 2 - Ataques detec (Imple)'!$D$3:$D$112,$B25,'Tabla 2 - Ataques detec (Imple)'!K$3:K$112) -> 3 | N25: =SUMIF('Tabla 2 - Ataques detec (Imple)'!$D$3:$D$112,$B25,'Tabla 2 - Ataques detec (Imple)'!L$3:L$112) -> 3 | O25: =N25 & " (" & M25 & ")" -> 3 (3) | P25: =SUMIF('Tabla 2 - Ataques detec (Imple)'!$D$3:$D$112,$B25,'Tabla 2 - Ataques detec (Imple)'!$M$3:$M$112) -> 3 | Q25: =AVERAGEIF('Tabla 2 - Ataques detec (Imple)'!$D$3:$D$112,$B25,'Tabla 2 - Ataques detec (Imple)'!$O$3:$O$112) -> 1 | R25: =SUMIF('Tabla 2 - Ataques detec (Imple)'!$D$3:$D$112,$B25,'Tabla 2 - Ataques detec (Imple)'!$N$3:$N$112) -> 1 | S25: =SUMIF('Tabla 2 - Ataques detec (Imple)'!$D$3:$D$112,$B25,'Tabla 2 - Ataques detec (Imple)'!P$3:P$112) -> 3 | T25: =SUMIF('Tabla 2 - Ataques detec (Imple)'!$D$3:$D$112,$B25,'Tabla 2 - Ataques detec (Imple)'!Q$3:Q$112) -> 3 | U25: =T25 & " (" & S25 & ")" -> 3 (3) | V25: =SUMIF('Tabla 2 - Ataques detec (Imple)'!$D$3:$D$112,$B25,'Tabla 2 - Ataques detec (Imple)'!$R$3:$R$112) -> 3 | W25: =AVERAGEIF('Tabla 2 - Ataques detec (Imple)'!$D$3:$D$112,$B25,'Tabla 2 - Ataques detec (Imple)'!$T$3:$T$112) -> 1 | X25: =SUMIF('Tabla 2 - Ataques detec (Imple)'!$D$3:$D$112,$B25,'Tabla 2 - Ataques detec (Imple)'!$S$3:$S$112) -> 1 | Y25: =SUMIF('Tabla 2 - Ataques detec (Imple)'!$D$3:$D$112,$B25,'Tabla 2 - Ataques detec (Imple)'!U$3:U$112) -> 19 | Z25: =SUMIF('Tabla 2 - Ataques detec (Imple)'!$D$3:$D$112,$B25,'Tabla 2 - Ataques detec (Imple)'!V$3:V$112) -> 1 | AA25: =Z25 & " (" & Y25 & ")" -> 1 (19) | AB25: =SUMIF('Tabla 2 - Ataques detec (Imple)'!$D$3:$D$112,$B25,'Tabla 2 - Ataques detec (Imple)'!$R$3:$R$112) -> 3 | AC25: =AVERAGEIF('Tabla 2 - Ataques detec (Imple)'!$D$3:$D$112,$B25,'Tabla 2 - Ataques detec (Imple)'!$Y$3:$Y$112) -> 1 | AD25: =SUMIF('Tabla 2 - Ataques detec (Imple)'!$D$3:$D$112,$B25,'Tabla 2 - Ataques detec (Imple)'!$X$3:$X$112) -> 1 | AE25: =SUMIF('Tabla 2 - Ataques detec (Imple)'!$D$3:$D$112,$B25,'Tabla 2 - Ataques detec (Imple)'!Z$3:Z$112) -> 7 | AF25: =SUMIF('Tabla 2 - Ataques detec (Imple)'!$D$3:$D$112,$B25,'Tabla 2 - Ataques detec (Imple)'!AA$3:AA$112) -> 5 | AG25: =AF25 & " (" & AE25 & ")" -> 5 (7) | AH25: =SUMIF('Tabla 2 - Ataques detec (Imple)'!$D$3:$D$112,$B25,'Tabla 2 - Ataques detec (Imple)'!$AB$3:$AB$112) -> 5 | AI25: =AVERAGEIF('Tabla 2 - Ataques detec (Imple)'!$D$3:$D$112,$B25,'Tabla 2 - Ataques detec (Imple)'!$AD$3:$AD$112) -> 1 | AJ25: =SUMIF('Tabla 2 - Ataques detec (Imple)'!$D$3:$D$112,$B25,'Tabla 2 - Ataques detec (Imple)'!$AC$3:$AC$112) -> 1 | AK25: =SUMIF('Tabla 2 - Ataques detec (Imple)'!$D$3:$D$112,$B25,'Tabla 2 - Ataques detec (Imple)'!AE$3:AE$112) -> 26 | AL25: =SUMIF('Tabla 2 - Ataques detec (Imple)'!$D$3:$D$112,$B25,'Tabla 2 - Ataques detec (Imple)'!AF$3:AF$112) -> 6 | AM25: =AL25 & " (" & AK25 & ")" -> 6 (26) | AN25: =SUMIF('Tabla 2 - Ataques detec (Imple)'!$D$3:$D$112,$B25,'Tabla 2 - Ataques detec (Imple)'!$AG$3:$AG$112) -> 6 | AO25: =AVERAGEIF('Tabla 2 - Ataques detec (Imple)'!$D$3:$D$112,$B25,'Tabla 2 - Ataques detec (Imple)'!$AI$3:$AI$112) -> 1 | AP25: =SUMIF('Tabla 2 - Ataques detec (Imple)'!$D$3:$D$112,$B25,'Tabla 2 - Ataques detec (Imple)'!$AH$3:$AH$112) -> 1 | AQ25: =SUMIF('Tabla 2 - Ataques detec (Imple)'!$D$3:$D$112,$B25,'Tabla 2 - Ataques detec (Imple)'!AJ$3:AJ$112) -> 0 | AR25: =SUMIF('Tabla 2 - Ataques detec (Imple)'!$D$3:$D$112,$B25,'Tabla 2 - Ataques detec (Imple)'!AK$3:AK$112) -> 0 | AS25: =AR25 & " (" & AQ25 & ")" -> 0 (0) | AT25: =SUMIF('Tabla 2 - Ataques detec (Imple)'!$D$3:$D$112,$B25,'Tabla 2 - Ataques detec (Imple)'!$AL$3:$AL$112) -> 0 | AU25: =AVERAGEIF('Tabla 2 - Ataques detec (Imple)'!$D$3:$D$112,$B25,'Tabla 2 - Ataques detec (Imple)'!$AN$3:$AN$112) -> 0 | AV25: =SUMIF('Tabla 2 - Ataques detec (Imple)'!$D$3:$D$112,$B25,'Tabla 2 - Ataques detec (Imple)'!$AM$3:$AM$112) -> 0 | AW25: =SUMIF('Tabla 2 - Ataques detec (Imple)'!$D$3:$D$112,$B25,'Tabla 2 - Ataques detec (Imple)'!AO$3:AO$112) -> 0 | AX25: =SUMIF('Tabla 2 - Ataques detec (Imple)'!$D$3:$D$112,$B25,'Tabla 2 - Ataques detec (Imple)'!AP$3:AP$112) -> 0 | AY25: =AX25 & " (" & AW25 & ")" -> 0 (0) | AZ25: =SUMIF('Tabla 2 - Ataques detec (Imple)'!$D$3:$D$112,$B25,'Tabla 2 - Ataques detec (Imple)'!$AQ$3:$AQ$112) -> 0 | BA25: =AVERAGEIF('Tabla 2 - Ataques detec (Imple)'!$D$3:$D$112,$B25,'Tabla 2 - Ataques detec (Imple)'!$AS$3:$AS$112) -> 0 | BB25: =SUMIF('Tabla 2 - Ataques detec (Imple)'!$D$3:$D$112,$B25,'Tabla 2 - Ataques detec (Imple)'!$AR$3:$AR$112) -> 0 | BC25: =SUMIF('Tabla 2 - Ataques detec (Imple)'!$D$3:$D$112,$B25,'Tabla 2 - Ataques detec (Imple)'!AT$3:AT$112) -> 3 | BD25: =SUMIF('Tabla 2 - Ataques detec (Imple)'!$D$3:$D$112,$B25,'Tabla 2 - Ataques detec (Imple)'!AU$3:AU$112) -> 3 | BE25: =BD25 & " (" & BC25 & ")" -> 3 (3) | BF25: =SUMIF('Tabla 2 - Ataques detec (Imple)'!$D$3:$D$112,$B25,'Tabla 2 - Ataques detec (Imple)'!$AV$3:$AV$112) -> 3 | BG25: =AVERAGEIF('Tabla 2 - Ataques detec (Imple)'!$D$3:$D$112,$B25,'Tabla 2 - Ataques detec (Imple)'!$AX$3:$AX$112) -> 1 | BH25: =SUMIF('Tabla 2 - Ataques detec (Imple)'!$D$3:$D$112,$B25,'Tabla 2 - Ataques detec (Imple)'!$AW$3:$AW$112) -> 1 | BI25: =SUMIF('Tabla 2 - Ataques detec (Imple)'!$D$3:$D$112,$B25,'Tabla 2 - Ataques detec (Imple)'!AY$3:AY$112) -> 3 | BJ25: =SUMIF('Tabla 2 - Ataques detec (Imple)'!$D$3:$D$112,$B25,'Tabla 2 - Ataques detec (Imple)'!AZ$3:AZ$112) -> 2 | BK25: =BJ25 & " (" & BI25 & ")" -> 2 (3) | BL25: =SUMIF('Tabla 2 - Ataques detec (Imple)'!$D$3:$D$112,$B25,'Tabla 2 - Ataques detec (Imple)'!BA$3:BA$112) -> 2 | BM25: =AVERAGEIF('Tabla 2 - Ataques detec (Imple)'!$D$3:$D$112,$B25,'Tabla 2 - Ataques detec (Imple)'!$BC$3:$BC$112) -> 1 | BN25: =SUMIF('Tabla 2 - Ataques detec (Imple)'!$D$3:$D$112,$B25,'Tabla 2 - Ataques detec (Imple)'!$BB$3:$BB$112) -> 1 | BO25: =SUMIF('Tabla 2 - Ataques detec (Imple)'!$D$3:$D$112,$B25,'Tabla 2 - Ataques detec (Imple)'!BD$3:BD$112) -> 4 | BP25: =SUMIF('Tabla 2 - Ataques detec (Imple)'!$D$3:$D$112,$B25,'Tabla 2 - Ataques detec (Imple)'!BE$3:BE$112) -> 3 | BQ25: =BP25 & " (" & BO25 & ")" -> 3 (4) | BR25: =SUMIF('Tabla 2 - Ataques detec (Imple)'!$D$3:$D$112,$B25,'Tabla 2 - Ataques detec (Imple)'!BF$3:BF$112) -> 2 | BS25: =SUMIF('Tabla 2 - Ataques detec (Imple)'!$D$3:$D$112,$B25,'Tabla 2 - Ataques detec (Imple)'!BG$3:BG$112) -> 1 | BT25: =AVERAGEIF('Tabla 2 - Ataques detec (Imple)'!$D$3:$D$112,$B25,'Tabla 2 - Ataques detec (Imple)'!$BI$3:$BI$112) -> 1 | BU25: =SUMIF('Tabla 2 - Ataques detec (Imple)'!$D$3:$D$112,$B25,'Tabla 2 - Ataques detec (Imple)'!$BH$3:$BH$112) -> 1 | BV25: 5 | BW25: 2 | BX25: =BW25 & " (" & BV25 & ")" -> 2 (5) | BY25: 2 | BZ25: 1 | CA25: 1 | CB25: 10 | CC25: 3 | CD25: =CC25 & " (" & CB25 & ")" -> 3 (10) | CE25: 2 | CF25: 1 | CG25: 1 | CH25: 1
A26: =A25+1 -> 24 | B26: =IFERROR(VLOOKUP(A26,'Tabla 2 - Ataques detec (Imple)'!$B$3:$D$112,3,FALSE),"") -> T1105 | C26: =IFERROR(VLOOKUP(B26,Techniques!$B$3:$H$213,2,FALSE),"") -> Ingress Tool Transfer | D26: =SUMPRODUCT( ('Tabla 2 - Ataques detec (Imple)'!$D$3:$D$112=$B26)* (LEN('Tabla 2 - Ataques detec (Imple)'!$C$3:$C$112)>0) ) -> 1 | E26: =SUMIF('Tabla 2 - Ataques detec (Imple)'!$D$3:$D$112,$B26,'Tabla 2 - Ataques detec (Imple)'!$E$3:$E$112) -> 7 | F26: =D26&" ("&E26&")" -> 1 (7) | G26: =SUMIF('Tabla 2 - Ataques detec (Imple)'!$D$3:$D$112,$B26,'Tabla 2 - Ataques detec (Imple)'!F$3:F$112) -> 6 | H26: =SUMIF('Tabla 2 - Ataques detec (Imple)'!$D$3:$D$112,$B26,'Tabla 2 - Ataques detec (Imple)'!G$3:G$112) -> 3 | I26: =H26 & " (" & G26 & ")" -> 3 (6) | J26: =SUMIF('Tabla 2 - Ataques detec (Imple)'!$D$3:$D$112,$B26,'Tabla 2 - Ataques detec (Imple)'!$H$3:$H$112) -> 2 | K26: =AVERAGEIF('Tabla 2 - Ataques detec (Imple)'!$D$3:$D$112,$B26,'Tabla 2 - Ataques detec (Imple)'!$J$3:$J$112) -> 1 | L26: =SUMIF('Tabla 2 - Ataques detec (Imple)'!$D$3:$D$112,$B26,'Tabla 2 - Ataques detec (Imple)'!$I$3:$I$112) -> 2 | M26: =SUMIF('Tabla 2 - Ataques detec (Imple)'!$D$3:$D$112,$B26,'Tabla 2 - Ataques detec (Imple)'!K$3:K$112) -> 4 | N26: =SUMIF('Tabla 2 - Ataques detec (Imple)'!$D$3:$D$112,$B26,'Tabla 2 - Ataques detec (Imple)'!L$3:L$112) -> 4 | O26: =N26 & " (" & M26 & ")" -> 4 (4) | P26: =SUMIF('Tabla 2 - Ataques detec (Imple)'!$D$3:$D$112,$B26,'Tabla 2 - Ataques detec (Imple)'!$M$3:$M$112) -> 2 | Q26: =AVERAGEIF('Tabla 2 - Ataques detec (Imple)'!$D$3:$D$112,$B26,'Tabla 2 - Ataques detec (Imple)'!$O$3:$O$112) -> 1 | R26: =SUMIF('Tabla 2 - Ataques detec (Imple)'!$D$3:$D$112,$B26,'Tabla 2 - Ataques detec (Imple)'!$N$3:$N$112) -> 4 | S26: =SUMIF('Tabla 2 - Ataques detec (Imple)'!$D$3:$D$112,$B26,'Tabla 2 - Ataques detec (Imple)'!P$3:P$112) -> 10 | T26: =SUMIF('Tabla 2 - Ataques detec (Imple)'!$D$3:$D$112,$B26,'Tabla 2 - Ataques detec (Imple)'!Q$3:Q$112) -> 7 | U26: =T26 & " (" & S26 & ")" -> 7 (10) | V26: =SUMIF('Tabla 2 - Ataques detec (Imple)'!$D$3:$D$112,$B26,'Tabla 2 - Ataques detec (Imple)'!$R$3:$R$112) -> 4 | W26: =AVERAGEIF('Tabla 2 - Ataques detec (Imple)'!$D$3:$D$112,$B26,'Tabla 2 - Ataques detec (Imple)'!$T$3:$T$112) -> 1 | X26: =SUMIF('Tabla 2 - Ataques detec (Imple)'!$D$3:$D$112,$B26,'Tabla 2 - Ataques detec (Imple)'!$S$3:$S$112) -> 4 | Y26: =SUMIF('Tabla 2 - Ataques detec (Imple)'!$D$3:$D$112,$B26,'Tabla 2 - Ataques detec (Imple)'!U$3:U$112) -> 7 | Z26: =SUMIF('Tabla 2 - Ataques detec (Imple)'!$D$3:$D$112,$B26,'Tabla 2 - Ataques detec (Imple)'!V$3:V$112) -> 4 | AA26: =Z26 & " (" & Y26 & ")" -> 4 (7) | AB26: =SUMIF('Tabla 2 - Ataques detec (Imple)'!$D$3:$D$112,$B26,'Tabla 2 - Ataques detec (Imple)'!$R$3:$R$112) -> 4 | AC26: =AVERAGEIF('Tabla 2 - Ataques detec (Imple)'!$D$3:$D$112,$B26,'Tabla 2 - Ataques detec (Imple)'!$Y$3:$Y$112) -> 1 | AD26: =SUMIF('Tabla 2 - Ataques detec (Imple)'!$D$3:$D$112,$B26,'Tabla 2 - Ataques detec (Imple)'!$X$3:$X$112) -> 2 | AE26: =SUMIF('Tabla 2 - Ataques detec (Imple)'!$D$3:$D$112,$B26,'Tabla 2 - Ataques detec (Imple)'!Z$3:Z$112) -> 11 | AF26: =SUMIF('Tabla 2 - Ataques detec (Imple)'!$D$3:$D$112,$B26,'Tabla 2 - Ataques detec (Imple)'!AA$3:AA$112) -> 9 | AG26: =AF26 & " (" & AE26 & ")" -> 9 (11) | AH26: =SUMIF('Tabla 2 - Ataques detec (Imple)'!$D$3:$D$112,$B26,'Tabla 2 - Ataques detec (Imple)'!$AB$3:$AB$112) -> 7 | AI26: =AVERAGEIF('Tabla 2 - Ataques detec (Imple)'!$D$3:$D$112,$B26,'Tabla 2 - Ataques detec (Imple)'!$AD$3:$AD$112) -> 1 | AJ26: =SUMIF('Tabla 2 - Ataques detec (Imple)'!$D$3:$D$112,$B26,'Tabla 2 - Ataques detec (Imple)'!$AC$3:$AC$112) -> 5 | AK26: =SUMIF('Tabla 2 - Ataques detec (Imple)'!$D$3:$D$112,$B26,'Tabla 2 - Ataques detec (Imple)'!AE$3:AE$112) -> 18 | AL26: =SUMIF('Tabla 2 - Ataques detec (Imple)'!$D$3:$D$112,$B26,'Tabla 2 - Ataques detec (Imple)'!AF$3:AF$112) -> 13 | AM26: =AL26 & " (" & AK26 & ")" -> 13 (18) | AN26: =SUMIF('Tabla 2 - Ataques detec (Imple)'!$D$3:$D$112,$B26,'Tabla 2 - Ataques detec (Imple)'!$AG$3:$AG$112) -> 10 | AO26: =AVERAGEIF('Tabla 2 - Ataques detec (Imple)'!$D$3:$D$112,$B26,'Tabla 2 - Ataques detec (Imple)'!$AI$3:$AI$112) -> 1 | AP26: =SUMIF('Tabla 2 - Ataques detec (Imple)'!$D$3:$D$112,$B26,'Tabla 2 - Ataques detec (Imple)'!$AH$3:$AH$112) -> 5 | AQ26: =SUMIF('Tabla 2 - Ataques detec (Imple)'!$D$3:$D$112,$B26,'Tabla 2 - Ataques detec (Imple)'!AJ$3:AJ$112) -> 0 | AR26: =SUMIF('Tabla 2 - Ataques detec (Imple)'!$D$3:$D$112,$B26,'Tabla 2 - Ataques detec (Imple)'!AK$3:AK$112) -> 0 | AS26: =AR26 & " (" & AQ26 & ")" -> 0 (0) | AT26: =SUMIF('Tabla 2 - Ataques detec (Imple)'!$D$3:$D$112,$B26,'Tabla 2 - Ataques detec (Imple)'!$AL$3:$AL$112) -> 0 | AU26: =AVERAGEIF('Tabla 2 - Ataques detec (Imple)'!$D$3:$D$112,$B26,'Tabla 2 - Ataques detec (Imple)'!$AN$3:$AN$112) -> 0 | AV26: =SUMIF('Tabla 2 - Ataques detec (Imple)'!$D$3:$D$112,$B26,'Tabla 2 - Ataques detec (Imple)'!$AM$3:$AM$112) -> 0 | AW26: =SUMIF('Tabla 2 - Ataques detec (Imple)'!$D$3:$D$112,$B26,'Tabla 2 - Ataques detec (Imple)'!AO$3:AO$112) -> 0 | AX26: =SUMIF('Tabla 2 - Ataques detec (Imple)'!$D$3:$D$112,$B26,'Tabla 2 - Ataques detec (Imple)'!AP$3:AP$112) -> 0 | AY26: =AX26 & " (" & AW26 & ")" -> 0 (0) | AZ26: =SUMIF('Tabla 2 - Ataques detec (Imple)'!$D$3:$D$112,$B26,'Tabla 2 - Ataques detec (Imple)'!$AQ$3:$AQ$112) -> 0 | BA26: =AVERAGEIF('Tabla 2 - Ataques detec (Imple)'!$D$3:$D$112,$B26,'Tabla 2 - Ataques detec (Imple)'!$AS$3:$AS$112) -> 0 | BB26: =SUMIF('Tabla 2 - Ataques detec (Imple)'!$D$3:$D$112,$B26,'Tabla 2 - Ataques detec (Imple)'!$AR$3:$AR$112) -> 0 | BC26: =SUMIF('Tabla 2 - Ataques detec (Imple)'!$D$3:$D$112,$B26,'Tabla 2 - Ataques detec (Imple)'!AT$3:AT$112) -> 10 | BD26: =SUMIF('Tabla 2 - Ataques detec (Imple)'!$D$3:$D$112,$B26,'Tabla 2 - Ataques detec (Imple)'!AU$3:AU$112) -> 7 | BE26: =BD26 & " (" & BC26 & ")" -> 7 (10) | BF26: =SUMIF('Tabla 2 - Ataques detec (Imple)'!$D$3:$D$112,$B26,'Tabla 2 - Ataques detec (Imple)'!$AV$3:$AV$112) -> 4 | BG26: =AVERAGEIF('Tabla 2 - Ataques detec (Imple)'!$D$3:$D$112,$B26,'Tabla 2 - Ataques detec (Imple)'!$AX$3:$AX$112) -> 1 | BH26: =SUMIF('Tabla 2 - Ataques detec (Imple)'!$D$3:$D$112,$B26,'Tabla 2 - Ataques detec (Imple)'!$AW$3:$AW$112) -> 4 | BI26: =SUMIF('Tabla 2 - Ataques detec (Imple)'!$D$3:$D$112,$B26,'Tabla 2 - Ataques detec (Imple)'!AY$3:AY$112) -> 1 | BJ26: =SUMIF('Tabla 2 - Ataques detec (Imple)'!$D$3:$D$112,$B26,'Tabla 2 - Ataques detec (Imple)'!AZ$3:AZ$112) -> 1 | BK26: =BJ26 & " (" & BI26 & ")" -> 1 (1) | BL26: =SUMIF('Tabla 2 - Ataques detec (Imple)'!$D$3:$D$112,$B26,'Tabla 2 - Ataques detec (Imple)'!BA$3:BA$112) -> 1 | BM26: =AVERAGEIF('Tabla 2 - Ataques detec (Imple)'!$D$3:$D$112,$B26,'Tabla 2 - Ataques detec (Imple)'!$BC$3:$BC$112) -> 1 | BN26: =SUMIF('Tabla 2 - Ataques detec (Imple)'!$D$3:$D$112,$B26,'Tabla 2 - Ataques detec (Imple)'!$BB$3:$BB$112) -> 1 | BO26: =SUMIF('Tabla 2 - Ataques detec (Imple)'!$D$3:$D$112,$B26,'Tabla 2 - Ataques detec (Imple)'!BD$3:BD$112) -> 6 | BP26: =SUMIF('Tabla 2 - Ataques detec (Imple)'!$D$3:$D$112,$B26,'Tabla 2 - Ataques detec (Imple)'!BE$3:BE$112) -> 2 | BQ26: =BP26 & " (" & BO26 & ")" -> 2 (6) | BR26: =SUMIF('Tabla 2 - Ataques detec (Imple)'!$D$3:$D$112,$B26,'Tabla 2 - Ataques detec (Imple)'!BF$3:BF$112) -> 1 | BS26: =SUMIF('Tabla 2 - Ataques detec (Imple)'!$D$3:$D$112,$B26,'Tabla 2 - Ataques detec (Imple)'!BG$3:BG$112) -> 1 | BT26: =AVERAGEIF('Tabla 2 - Ataques detec (Imple)'!$D$3:$D$112,$B26,'Tabla 2 - Ataques detec (Imple)'!$BI$3:$BI$112) -> 1 | BU26: =SUMIF('Tabla 2 - Ataques detec (Imple)'!$D$3:$D$112,$B26,'Tabla 2 - Ataques detec (Imple)'!$BH$3:$BH$112) -> 2 | BV26: 2 | BW26: 2 | BX26: =BW26 & " (" & BV26 & ")" -> 2 (2) | BY26: 1 | BZ26: 1 | CA26: 2 | CB26: 4 | CC26: 4 | CD26: =CC26 & " (" & CB26 & ")" -> 4 (4) | CE26: 1 | CF26: 1 | CG26: 1 | CH26: 2
